Workbook
Name Hoje: TODAY()
Name Incremento_de_rolagem: #REF!
Name Incremento_de_rolagem: #REF!
Name Incremento_de_rolagem: #REF!
Name Incremento_de_rolagem: #REF!
Name Incremento_de_rolagem: #REF!
Name Incremento_de_rolagem: #REF!
Name Incremento_de_rolagem: 'Grafico Gantt '!$F$4
Name Incremento_de_rolagem: #REF!
Name Incremento_de_rolagem: #REF!
Name Início_do_projeto: #REF!
Name Início_do_projeto: #REF!
Name Início_do_projeto: #REF!
Name Início_do_projeto: #REF!
Name Início_do_projeto: #REF!
Name Início_do_projeto: #REF!
Name Início_do_projeto: 'Grafico Gantt '!$F$3
Name Início_do_projeto: #REF!
Name Início_do_projeto: #REF!

Sheet EAP (2)

Sheet Dicionario EAP
D1: Lider | G1: Leandro Costa Ferreira | J1: DATA DE INICIO 13/08/2023 | M1: DATA DE ENTREGA 01/12/2022
D2: Equipe | G2: Pétrick Gomes
G3: Cosme Sousa
G4: Damião Sousa
G5: Nilton Guerra
G6: João Miranda
A7: PLANEJAMENTO | B7: Termo de Abertura do Projeto (TAP) | C7: Pacote de Trabalho | D7: Descrição | E7: Criterios de Aceitação | F7: (R) Responsavel | G7: (A) Autoridade | H7: (C) Consultado | I7: (I) Informado | J7: O quê? | K7: Por quê? | L7: Onde? | M7: quem? | N7: Como?
C8: Formalização do Projeto. | D8: A Formalização do Projeto, é uma garantia que o grupo tem para impulsionar adequadamento o projeto. É importante , pois oficializa as metas que foram cumpridas, gerandos obrigações. Serve para assegurar a entrega do projeto. | E8: Especificar o objetivo central do projeto. | F8: Todos integrantes | G8: Leandro Costa Ferreira Pétrick Gomes | H8: Todos integrantes | I8: Todos integrantes | J8: Formalizar o projeto e as obrigações de todos os integrantes. | K8: Criar responsabilidade para os integrantes do grupo, para auxiliar no desenvolvimento do projeto e inserção dos integrantes nele. | L8: Sala de aula C13. | M8: Todos os integrantes do grupo | N8: Através de um brainstorm de todos os integrantes que irá ser registrado na TAP no projeto
C10: Estrutura e organização das ideias do projeto. | D10: Estruturar e organizar o projeto é uma etapa importante para que os integrantes tenham o controle sobre as ideias e tarefas que serão executadas. | E10: Direcionar os integrantes a seus objetivos. | F10: Todos integrantes | G10: Leandro Costa Ferreira Pétrick Gomes | H10: Todos integrantes | I10: Todos integrantes | J10: Estruturar as ideias do projeto. | K10: Ter uma lógistica de tarefas fácil de se gerir . | L10: Sala de aula C13. | M10: Todos os integrantes do grupo | N10: Através de um brainstorm de todos os integrantes que irá ser registrado na TAP no projeto
C12: Análise dos Integrantes pelo metodo SWOT. | D12: Analisar os integrantes por meio do método SWOT é um ponto extremamente relevante que serve para conhecer as limitaçãoes de cada um, facilitandona definição de funções. | E12: Facilitar o reconhecimento das limitações e acrecismos dos integrantes do Projeto. | F12: Todos integrantes | G12: Leandro Costa | H12: Todos integrantes | I12: Todos integrantes | J12: verificar as forças e fraquezas de todos os integrantes do grupo. | K12: Facilitar na atribuição de tarefas de todos os integrantes do grupo. | L12: Sala de aula C13. | M12: Todos os integrantes do grupo | N12: Através de um brainstorm de todos os integrantes que irá ser registrado na TAP no projeto
C13: Atribuição de Responsabilidades e Funções. | D13: Atribuir responsabilidades e funções de acordo com a capacidade de cada um é um ponto importante para o desenvolvimento do trabalho, pois cada integrante pode ser responsabilizado por uma função que tenha maior facilidade na realização. | E13: Atribuição de reponsabilidades de integrantes expecificos em determinadas temas. | F13: Todos integrantes | G13: Leandro Costa Ferreira Pétrick Gomes | H13: Todos integrantes | I13: Todos integrantes | J13: Atribuir responsabilidades a todos os integrantes do grupo. | K13: Agilizar a realização do projeto | L13: Sala de aula C08 | M13: Todos os integrantes do grupo | N13: Através de um brainstorm de todos os integrantes que irá ser registrado na TAP no projeto
C15: Revisão. | D15: Revisar o que já foi feito nesta tarefa por cada integrante. Sempre visando o aperfeiçoamento do documento ou trabalho, caso necessário. | E15: Gerar um aprimoramento no que já foi feito. | F15: Todos integrantes | G15: Leandro Costa Ferreira | H15: Todos integrantes | I15: Todos integrantes | J15: Revisar o trabalho | K15: Corrigir possiveis erros gramáticais e | L15: Sala de aula C08 | M15: Todos os integrantes do grupo | N15: Consultando integrantes do grupo e professores.
C16: Validação. | D16: Validar o trabalho feito nesta etapa e revisar caso seja necessário. | E16: Cumprir com os criterios passados em sala de aula e do PMBOK. | F16: Orientadores | G16: Orientadores | H16: Orientadores | I16: Orientadores | J16: Validação | K16: Fazer uma segunda revisão para verificar possiveis erros. | L16: Sala de aula C08 | M16: Todos os integrantes do grupo | N16: Consultando professores
B17: Escopo | C17: Definição de Etapas. | D17: Definir a ordem de como e quando será feito cada etapa. | E17: Definir e separar as principais renponsabilidades em etapas. | F17: Cosme Sousa Damião Sousa Nilton Guerra | G17: Leandro Costa Ferreira Pétrick Gomes | H17: Todos integrantes | I17: Todos integrantes | J17: Definir como e quando serão realizadas as atividas e etapas do projeto. | K17: Facilitar a gestão do projeto. | L17: Sala de aula C08 | M17: Todos os integrantes do grupo | N17: Através de um brainstrom entre os integrantes do grupo e usando uma planilha do excel definimos as etapas do projeto
C20: Definição de Tarefas. | D20: Definir quais tarefas e subtarefas a serem executadas em cada etapa do processo. | E20: Desmembrar as etapas em tarefas. | F20: Cosme Sousa Damião Sousa Nilton Guerra | G20: Leandro Costa Ferreira Pétrick Gomes | H20: Todos integrantes | I20: Todos integrantes | J20: Definir como e quando serão realizadas as atividas e etapas do projeto. | K20: Facilitar na gestão do projeto | L20: Sala de aula C08 | M20: Todos os integrantes do grupo | N20: Através de um brainstrom entre os integrantes do grupo nos definimos onde cada tarefa se alocará
C23: Dicionario. | D23: Descrição de cada subtarefa e definir os responsaveis pela execução conforme o nivel de responsabilidade mostrado na tabela RACI e na analise SWOT. | E23: Direcionar de maneira mais profundada a todos os processos do projeto. | F23: Leandro Costa Ferreira Pétrick Gomes João Miranda | G23: Leandro Costa Ferreira Pétrick Gomes | H23: Todos integrantes | I23: Todos integrantes | J23: Descrever as tarefas a serem executadas pelos integrantes baseado na análise SWOT e RACI | K23: Facilitar na gestão do projeto e trazer mais facilidade na execução do trabalho | L23: Sala de aula C08 | M23: Todos os integrantes do grupo | N23: Através de uma divisão dos integrantes nos montamos o dicionário da EAP usando e software da microsoft Excel.
C26: Revisão. | D26: Revisar o que foi já feito nesta tarefa por cada integrante, aperfeiçoando o documento, caso necessário. | E26: Gerar um aprimoramento naquilo que já foi executado. | F26: Todos integrantes | G26: Leandro Costa Ferreira Pétrick Gomes | H26: Todos integrantes | I26: Todos integrantes | J26: Revisar o que se foi feito. | K26: verificar se o que foi feito está bom e sugerir possiveis melhorias. | L26: Sala de aula C08 | M26: Todos os integrantes do grupo | N26: Uma leitura da TAP pelo lider e vice-lider
C28: Validação. | D28: Validar o trabalho feito nesta etapa e revisar caso necessário. | E28: Cumprir com os criterios passados em sala de aula e do PMBOK. | F28: Orientadores | G28: Orientadores | H28: Orientadores | I28: Orientadores | J28: validar o trabalho que foi feito nessa etapa | K28: Verificar se o que foi feito está bom. | L28: Sala de aula C08 | M28: Todos os integrantes do grupo | N28: Uma leitura da TAP pelo lider e vice-lider
B29: Cronograma | C29: Análise do escopo | D29: Analisar o escopo é importante para a organização do grupo em relação a tarefas e responsabilidades. | E29: Finalidade do Projeto, a meta final. | F29: Leandro Costa Pétrick Gomes | G29: Leandro Costa Ferreira Pétrick Gomes | H29: Cosme Sousa Damião Sousa | I29: Todos integrantes | J29: Análisar o escopo | K29: Criar o sentimento para cada integrantes de responsabilidade com a tarefa atribuida a ele. | L29: C13 | M29: Leandro Costa Petrick Gomes | N29: Através de uma conversa entre os integrantes nos iremos revidar as divições das tarefas
C32: Definição do tempo de trabalho | D32: Definir o tempo de trabalho é de extrema importância, pois serve para estimar prazos e também para ter o controle do tempo que será gasto com cada etapa, facilitando a organização do projeto. | E32: Levar um tempo de trabalho necessario e esperado. | F32: Leandro Costa Pétrick Gomes | G32: Leandro Costa Ferreira Pétrick Gomes | H32: Todos integrantes | I32: Todos integrantes | J32: Definir o tempo para realizar cada etapa | K32: Permitir que entregue o projeto a tempo | L32: C13 | M32: Leandro Costa Petrick Gomes | N32: Através da formula de PER, usando o software Excel e uma brainstorm com todos os integrantes definimos as tarefas a serem realizadas.
C34: Definição de datas de entrega | D34: Designar as datas de entrega é extremamente importante para a organização e a finalização do projeto, com uma data de entrega pré-definida, os integrantes conseguem se organizar e definir tarefas facilmente. | E34: Levar uma elaboração antecipada. | F34: Leandro Costa Pétrick Gomes | G34: Leandro Costa Ferreira Pétrick Gomes | H34: Todos integrantes | I34: Todos integrantes | J34: Definir datas para a entrega de cada parte do trabalho | K34: Facilitar na gestão do projeto | L34: C13 | M34: Leandro Costa Petrick Gomes | N34: Através da formula de PER, usando o software Excel e uma brainstorm de todos os integrantes definimos as tarefas a serem realizadas.
C36: Revisão | D36: Revisar o que foi já feito nesta tarefa por cada integrante, aperfeiçoando o documento, caso necessário. | E36: Gerar um aprimoramento naquilo que já foi executado. | F36: Leandro Costa Pétrick Gomes | G36: Leandro Costa Ferreira Pétrick Gomes | H36: Todos integrantes | I36: Todos integrantes | J36: Revisar o que se foi feito. | K36: Sujerir posiveis melhorias e evitar possiveis erros | L36: C13 | M36: Leandro Costa Petrick Gomes | N36: Uma leitura da TAP pelo lider e vice-lider
C37: Validação | D37: Validar o documento feito nessa etapa e revisar caso necessário. | E37: Cumprir com os criterios passados em aula e do PMBOK. | F37: Orientadores | G37: Orientadores | H37: Orientadores | I37: Orientadores | J37: validar o que se foi feito | K37: Sujerir posiveis melhorias e evitar possiveis erros | L37: C13 | M37: Leandro Costa Petrick Gomes | N37: Uma leitura da TAP pelo lider e vice-lider
B38: Analises de Risco do Projeto | C38: Avaliação de impacto | D38: Avaliar os possiveis riscos que podem prejudicar o projeto. | E38: Levantar os possiveis riscos. | F38: Todos integrantes | G38: Leandro Costa Ferreira Pétrick Gomes | H38: Todos integrantes | I38: Todos integrantes | J38: Avaliar os possíveis riscos do projeto | K38: evitar/ amenizar os riscos ao projeto | L38: C13 | M38: Leandro Costa Ferreira Pétrick Gomes João Miranda | N38: Através de um brainstorm de todos os responsaveis iremos abordar possiveis estratégias para evitar os riscos.
C41: Avaliação de probabilidade | D41: Avaliar a probabilidade desses riscos acontecerem e quando pode ser que aconteçam. | E41: Preparar-se sob a probabilidade dos riscos. | F41: Todos integrantes | G41: Leandro Costa Ferreira Pétrick Gomes | H41: Todos integrantes | I41: Todos integrantes | J41: Avaliar a probabilidade dos riscos acontecerem. | K41: Fazer preparações de acordo com o nivel de probabilidade. | L41: C13 | M41: Leandro Costa Ferreira Pétrick Gomes João Miranda | N41: Através de um brainstorm de todos os responsaveis considerar quais os riscos mais prováveis.
C44: Peso de risco | D44: O quão pode ser prejucial caso algum risco aconteça e o que fazer para nos recuperar. | E44: Gerar possiveis consequencias. | F44: Todos integrantes | G44: Leandro Costa Ferreira Pétrick Gomes | H44: Todos integrantes | I44: Todos integrantes | J44: definir o quão grave é o risco e as medidas de supressão dele. | K44: definir o que será feito caso um risco aconteça. | L44: C13 | M44: Leandro Costa Ferreira Pétrick Gomes João Miranda | N44: Através de um brainstorm de todos os responsaveis iremos abordar possiveis estratégias para evitar os riscos.
C47: Burndown chart | D47: É um grafico que demonstra o tempo versus o trabalho a ser feito. | E47: Comparar o tempo trabalho com a meta. | F47: Todos integrantes | G47: Leandro Costa Ferreira Pétrick Gomes | H47: Todos integrantes | I47: Todos integrantes | J47: Fazer um gráfico de acompanhamento do trabalho | K47: Saber que velocidade o projeto está caminhando para poder gerar uma possivel data de entrega. | L47: C13 | M47: Leandro Costa Ferreira Pétrick Gomes João Miranda | N47: Através da formula de PER iremos desenvolver quanto tempo é necessário para a execução de cada tarefa do projeto e com essa informação iremos estimar uma valor em pontos para cada atividade que por fim será usado no gráfico do burndown chart juntamente com o tempo disponivel.
A50: INSTALAÇÃO | B50: Painéis | C50: Dimencionar quadro de distribuição | D50: Definir o tamanho do quadro de distribuição com o objetivo de trazer uma sensação visial melhor e facilitar possiveis aprimoramentos da instalação. | E50: permitir que todos os quadros de energia possam ser instalados dentro do quadro de distribuição | G50: Leandro Costa Ferreira Pétrick Gomes | H50: Leandro Costa Ferreira Pétrick Gomes | I50: Todos os integrantes | J50: Usar a escala de mm para definir o tamanho do quadro de distribuição que conterá os quadros de iluminação, CFTV e alarme de incêndio. | K50: Para trazer uma sensação visual melhor, evitar gastos desnecessários e facilitar possiveis aprimoramentos da instalação. | L50: oficina IELI 1 | M50: Cosme Alves Damião Alves | N50: Através de um técnico altamente treinado irá ser feito um dimenciosamento do sistema elétrico da instalação e com essa insformação iremos definir a quantidade de componentes necessarios para a instalação e assim a dimenção do quadro
C52: dimencionar quadro de força. | D52: Proteger os circuitos da instalação de qualquer anormalidade da rede de energia. | E52: proteger o circuito de iluminação | G52: Leandro Costa Ferreira Pétrick Gomes | H52: Leandro Costa Ferreira Pétrick Gomes | I52: Todos os integrantes | J52: Usar disjuntor, DPS e DR para a proteção do circuito de iluminação. | K52: proteger o circuito. | L52: oficina IELI 1 | M52: Cosme Alves Damião Alves | N52: Usando os conhecimento adquiridos pelo curso de eletroeletrônica do SENAI, iremos dimencionar o quadro de força
B54: Instalação do CFTV | C54: Passagem de cabos | D54: Fazer a transmição de dados e de energia elétrica através de eletrocalhas e eletrodutos | E54: Fazer a alimentação das câmeras e do DRV com condutores isolados e sem imendas nos eletrodutos. | F54: Damião sousa | G54: Leandro Costa Ferreira Pétrick Gomes | H54: Leandro Costa Ferreira Pétrick Gomes | I54: Todos os integrantes | J54: Passar os cabos pelos eletrodutos. | K54: Permitir a alimentação dos componentes | L54: oficina IELI 1 | M54: Nilton Guerra Cosme Alves | N54: Fazer o dimensionamento dos cabos para a instalação das câmeras
C56: Instalar câmeras | D56: colocar as câmeras nos locais previamente definidos para possibilitar o monitoramento dos locais. | E56: Fixar firme as câmeras e fazer a alimentação e a transmição de dados com facilidade. | F56: Damião sousa | G56: Leandro Costa Ferreira Pétrick Gomes | H56: Leandro Costa Ferreira Pétrick Gomes | I56: Todos os integrantes | J56: Instalar apoios para as câmeras através de parafusos e porcas, para logo em seguida colocar as câmeras. | K56: Para permitir a monitoração de locais previamentes desiginados. | L56: oficina IELI 1 | M56: Nilton Guerra Cosme Alves | N56: definir posição para instalação das câmeras
C58: Instalar Central | D58: Instalar o DVR e o monitor para possibilitar o acompanhamento da vigilância dos locais. | E58: Permitir a comunicação do monitor com o DRV | F58: Damião sousa | G58: Leandro Costa Ferreira | H58: Leandro Costa Ferreira | I58: Todos os integrantes | J58: usar o cabo VGA para comunicar o DVR com o monitor e alimentar ambos. | K58: Para permitir o acompanhamneto da vigilância dos locais pelo monitor. | L58: oficina IELI 1 | M58: Nilton Guerra Cosme Alves | N58: Interligação do DVR com o monitor
C60: Interligar as câmeras com a central | D60: Permitir a transmição de dados entre as câmeras e o DVR | E60: Permitir a visualização dos pontos de vigilância no monitor | F60: Damião sousa | G60: Leandro Costa Ferreira | H60: Leandro Costa Ferreira | I60: Todos os integrantes | J60: usando o conector P4 macho e fême e o cabo coaxial fazer o interligamento da câmera com o DVR. | K60: Comunicar o DVR com as câmeras. | L60: oficina IELI 1 | M60: Nilton Guerra | N60: Interligação das câmeras com Central para ser feito monitoriamento com DVR
B61: Instalação da central | C61: Passagem de cabos. | D61: Permitir que haja a transmição de energia | E61: Que os cabos passados sejam alimentados e devidamente isolados sem imentas nos eletrodutos. | F61: Nilton Gerra | G61: Leandro Costa Ferreira Pétrick Gomes | H61: Leandro Costa Ferreira Pétrick Gomes | I61: Todos os integrantes | J61: Passar os cabos pelos eletrodutos. | K61: Permitir a alimentação dos componentes | L61: oficina IELI 1 | M61: Nilton Guerra | N61: Usando um guia passa fio iremos direcionar os cabos para suas devidas posições já estipuladas no planejamento.
C63: Instalar sensores e atuadores manuais. | D63: permitir que haja a sensibilidade para captar fumaça. | E63: Ligar todas as coneções dos sensores corretamente. | F63: Nilton Gerra | G63: Leandro Costa Ferreira Pétrick Gomes | H63: Leandro Costa Ferreira Pétrick Gomes | I63: Todos os integrantes | J63: instalar os sensores de fumaça respeitando as suas coneções com a central de incêndio,1:1,2:2,3:3,4:4 | K63: Permitir a captura de fumaça | L63: oficina IELI 1 | M63: Nilton Guerra | N63: Usando a escada e uma chave de fenda iremos instalar os sensores de fumaça respeitando a posição de cada cabo.
C65: Instalar Central. | D65: Definir um local específico para gerenciar o controle de incêndios. | E65: Fazer a comunicação entre central de alarme de incêndio e sesores de fumaça. | F65: Nilton Gerra | G65: Leandro Costa Ferreira Pétrick Gomes | H65: Leandro Costa Ferreira Pétrick Gomes | I65: Todos os integrantes | J65: posicionar um local especifico para gerenciar o controle de incêndio | K65: ter um controle mais rápido e eficiente do sistema de incêndio | L65: oficina IELI 1 | M65: Nilton Guerra | N65: definir uma posição para a central de incêndio que não incomode ninguém
B67: Instalação de Iluminação | C67: Passagem de cabos | D67: Permitir que haja a transmição de energia | E67: Que os cabos passados sejam alimentados e devidamente isolados sem imentas nos eletrodutos. | F67: Cosme Sousa | G67: Leandro Costa Ferreira Pétrick Gomes | H67: Leandro Costa Ferreira Pétrick Gomes | I67: Todos os integrantes | J67: Passar os cabos pelos eletrodutos. | K67: Permitir a alimentação dos componentes | L67: oficina IELI 1 | M67: Cosme Sousa | N67: Usando um passa fio iremos direcionar os cabos para suas devidas posições já estipuladas no planejamento.
C69: Instalar lâmpadas LED | D69: Iluminar os recintos através de uma lampada LED de valor especificado na NBR5410. | E69: Fazer as lampadas acenderem. | F69: Cosme Sousa | G69: Leandro Costa Ferreira Pétrick Gomes | H69: Leandro Costa Ferreira Pétrick Gomes | I69: Todos os integrantes | J69: Fazer a instalação dos receptaculos, e logo em seguida colocar as lampadas LED | K69: Iluminar o ambiente | L69: oficina IELI 1 | M69: Cosme Sousa | N69: Usando uma escada iremos instalar a lampada no receptaculo.
C71: Instalação dos interruptores móveis. | D71: Facilitar a configução dos interruptores móvéis com o objetivo de trazer mais conforto no acionamento da iluminação do local. | E71: Fazer a instalação dos interruptores móveis com condutores sem imendas e sem partes de cobre a mostra. | F71: Cosme Sousa | G71: Leandro Costa Ferreira Pétrick Gomes | H71: Leandro Costa Ferreira Pétrick Gomes | I71: Todos os integrantes | J71: Instalação dos interruptores móveis | K71: configução dos interruptores móvéis com o objetivo de trazer conforto. | L71: oficina IELI 1 | M71: Cosme Sousa | N71: usando o interruptor móvel, um interruptor pulsador e o aplicativo do interruptor idemos sincronizar-los.
C73: Configuração dos interruptores móveis | D73: Configurar os interruptores móveis para que possa ocorrer o acionamento da iluminação do recintos de maneira mais cômoda. | E73: Fazer os interruptores móveis funcionarem | F73: Cosme Sousa | G73: Leandro Costa Ferreira Pétrick Gomes | H73: Leandro Costa Ferreira Pétrick Gomes | I73: Todos os integrantes | J73: configuração dos interruptores | K73: Fazer os interruptores móveis funcionarem | L73: oficina IELI 1 | M73: Cosme Sousa | N73: Usando o aplicativo do interruptor movél iremos configurar o aplicativo.
B74: Instalação do sistema de monitoramento | C74: Fixar o monitor de energia. | D74: Fazer a instalação do quadro de monitoramento de energia. | E74: Fazer o monitor de energia ligar. | F74: Leandro Costa Ferreira João Miranda | G74: Leandro Costa Ferreira Pétrick Gomes | H74: Pétrick Gomes | I74: Todos os integrantes | J74: Fazer a instalação do monitor de energia em um painel | K74: Maior conforto visual e segurança | L74: oficina IELI 1 | M74: Leandro Costa Ferreira João Miranda | N74: Instalação do quadro de monitoramento de energia ao lado do quadro de distribuição
C76: Interligar com o circuito das instalações. | D76: colocar o circuito em serie com o quadro de força com o objetivo de fazer a medição do consumo de energia. | E76: Fazer o monitor de energia funcionar. | F76: Leandro Costa Ferreira João Miranda | G76: Leandro Costa Ferreira Pétrick Gomes | H76: Leandro Costa Ferreira | I76: Todos os integrantes | J76: colocar o circuito em serie com o quadro de energia através de suas respectivas conexões | K76: monitorar o circuito | L76: oficina IELI 1 | M76: Leandro Costa Ferreira João Miranda | N76: Interligar com o circuito para fazer o monitoramento
C78: Conferir funcionamento. | D78: Verificarse se o monitor de energia está funcionando corretamente, com o objetivo de evitar possiveis erros de medição. | E78: confirmar que o monitor de energia está funcionando corretamente. | F78: Leandro Costa Ferreira João Miranda | G78: Leandro Costa Ferreira Pétrick Gomes | H78: Leandro Costa Ferreira Pétrick Gomes | I78: Todos os integrantes | J78: Usando um multimetro, o monitor de energia e uma carga verificar se os resultados batem | K78: Validar se o aparelho está funcionando corretamente | L78: oficina IELI 1 | M78: Leandro Costa Ferreira João Miranda | N78: Usando um multimetro iremos validar a medição do monitor de consumo de energia.
B80: Instalação da Assistente de Voz | C80: Configuração da assistente. | D80: Fazer a programação e configurações da alexa atraves do aplicativo. | E80: Controlar alexa pelo app. | F80: João Miranda Nilton Guerra | G80: Leandro Costa Ferreira Pétrick Gomes | H80: Leandro Costa Ferreirta | I80: Leandro Costa Ferreirta | J80: fazer a programação e configurações da alexa atraves do aplicativo | K80: Permitir que o acionamento da iluminação através do celular | L80: oficina IELI 1 | M80: Leandro Costa Ferreira João Miranda | N80: Usando o aplicativo da Alexa no smartfone iremos configurar a assistente de voz.
G82: Leandro Costa Ferreira Pétrick Gomes | I82: Pétrick Gomes
C83: testes de funcionamento | D83: fazer testes para conferir se a alexa está funcionando | E83: Alexa Responder aos comandos corretamente | F83: João Miranda Nilton Guerra | H83: Leandro Costa Ferreirta | I83: Leandro Costa Ferreirta | J83: fazer testes para conferir se a alexa está funcionando | K83: Trazer segurança e agilidade para instalação | L83: oficina IELI 1 | M83: João Miranda Nilton Guerra | N83: usando a voz iremos testar se a Alexa responde
C85: integração com outros dispositivos | D85: fazer a configuração da alexa com outros dispositivos | E85: Alexa controlar outros dispositivos | F85: João Miranda Nilton Guerra | G85: Leandro Costa Ferreira Pétrick Gomes | H85: Leandro Costa Ferreirta | I85: Leandro Costa Ferreira Pétrick Gomes | J85: fazer a configuração da alexa com outros dispositivos | K85: Fazer a integração de outro dispositivos com o objetivo de trazer mais conforto e praticidade | L85: oficina IELI 1 | M85: João Miranda Nilton Guerra | N85: Usando o aplicativo da alexa iremos sincronizar a alexa com outros equipamentos
B87: Instalação do interfone | C87: instalar dispositivo | D87: fazer a instalação do interfone na casa | E87: interfone estar fixado | F87: Cosme Sousa Damião Sousa Pétrick Gomes | G87: Leandro Costa Ferreira Pétrick Gomes | H87: Nilton Guerra | I87: NIlton Guerra Leandro Costa ferreira Pétrick Gomes | J87: fazer a instalação do interfone na local | K87: Trazer mais conforto e segurança para o local | L87: oficina IELI 1 | M87: Cosme Sousa Damião Sousa Pétrick | N87: Instalaçao e fixação das bases do Interfone.
C89: testar funcionamento | D89: fazer testes para conferir o funcionamento do interfone | E89: interfone está funcionando | F89: Cosme Sousa Damião Sousa Pétrick Gomes | G89: Leandro Costa Ferreira Pétrick Gomes | H89: Nilton Guerra | I89: NIlton Guerra Leandro Costa ferreira | J89: fazer testes para conferir o funcionamento do interfone | K89: Validar o funcionamento do interfone | L89: oficina IELI 1 | M89: Cosme Sousa Damião Sousa | N89: Energização e teste de funcionámento dos componentes.
C91: integrar com sistema de segurança | D91: fazer a integração do interfone com a trava automatica | E91: interfone funcionar junto ao sistema de segurança | F91: Cosme Sousa Damião Sousa Pétrick Gomes | G91: Leandro Costa Ferreira Pétrick Gomes | H91: Nilton Guerra | I91: NIlton Guerra Leandro Costa ferreira Pétrick Gomes | J91: fazer a integração do interfone com a trava automatica | K91: Trazer mais segurança | L91: oficina IELI 1 | M91: Cosme Sousa Damião Sousa Pétrick | N91: Fazer Passagem dos cabos einterligação do interfone e fechadura.
B93: Instalação trava automatica | C93: instalar dispositivo | D93: fazer a instalação das travas automaticas | E93: instalação das travas automaticas | F93: Leandro Costa Ferreira João Miranda Nilton Guerra | G93: Leandro Costa Ferreira Pétrick Gomes | H93: Nilton Guerra | I93: NIlton Guerra Leandro Costa ferreira Pétrick Gomes | J93: fazer a instalação das travas automaticas | K93: trazer mais segurança. | L93: oficina IELI 1 | M93: Leandro Costa Ferreira João Miranda Nilton Guerra | N93: seguindo o diagrama
C95: testar funcionamento | D95: fazer testes para conferir o funcionamento dos dispositivos | E95: Fazer o funcionamento da trava | F95: Leandro Costa Ferreira João Miranda Nilton Guerra | G95: Leandro Costa Ferreira Pétrick Gomes | H95: Nilton Guerra | I95: NIlton Guerra Leandro Costa ferreira Pétrick Gomes | J95: fazer testes para conferir o funcionamento dos dispositivos | K95: validar o funcionamento da trava automatica. | L95: oficina IELI 1 | M95: Leandro Costa Ferreira João Miranda Nilton Guerra | N95: Energização e teste dos componentes.
C97: integrar com sistema de segurança | D97: fazer a integração do interfone com alguns sistemas de segurançã | E97: integrar com sistema de segurança | F97: Leandro Costa Ferreira João Miranda Nilton Guerra | G97: Leandro Costa Ferreira Pétrick Gomes | H97: Nilton Guerra | I97: NIlton Guerra Leandro Costa ferreira Pétrick Gomes | J97: fazer a integração da trava automativa com o internofe | K97: Trazer mais segurança. | L97: oficina IELI 1 | M97: Leandro Costa Ferreira João Miranda Nilton Guerra | N97: Interligar interfone e fechadura com Central.
A99: CONFIGURAÇÃO | B99: Sistema de Monitoramento | C99: Levantamento dos equipamentos e manuais necessários | D99: Ferramentas e equipamentos necessario para a instalação do projeto. | E99: Acrescentar base ao projeto. | F99: Nilton Guerra Cosme Sousa | G99: Leandro Costa Ferreira Pétrick Gomes | H99: Nilton Guerra | I99: Todos integrantes | J99: Levantamento dos equipamentos e manuais necessários | K99: Ferramentas e equipamentos necessario para a instalação do projeto. | L99: oficina IELI 1 | M99: Nilton Guerra Cosme Sousa | N99: através de um dialogo com os professores iremos buscar informações em relação aos equipamentos procurar os
C101: Configurações remotas e manuais | D101: Fazer o acionamentvia wifi o e manualmente. | E101: Garantir material ao projeto. | F101: Nilton Guerra Cosme Sousa | G101: Leandro Costa Ferreira Pétrick Gomes | H101: Nilton Guerra | I101: Todos integrantes | J101: Configurações remotas e manuais | K101: Fazer o acionamentvia wifi o e manualmente. | L101: oficina IELI 1 | M101: Nilton Guerra Cosme Sousa | N101: baixar e configurar os aplicativos necessários, através do celular e fazer a configuração do DVR para o funcionamento da imagem das cameras
C103: Integração com centrais e redes sem fio | D103: Fazer o acionamentvia WIFI. | E103: Ser um meio de realização do trabalho. | F103: Nilton Guerra Cosme Sousa | G103: Leandro Costa Ferreira Pétrick Gomes | H103: Todos integrantes | I103: Todos integrantes | J103: Integração com centrais e redes sem fio | K103: Fazer o acionamentvia WIFI. | L103: oficina IELI 1 | M103: Nilton Guerra Cosme Sousa | N103: Fazer a separação e instalação dos cabos para a conexão do DVR com as cameras
C105: Integração com o cliente | D105: Verificar os pontos mas apropriados para instalação do equipamento de monitoramento. | E105: Sistema base do projeto. | F105: Nilton Guerra Cosme Sousa | G105: Leandro Costa Ferreira Pétrick Gomes | H105: Todos integrantes | I105: Todos integrantes | J105: Integração com o cliente | K105: Verificar os pontos mas apropriados para instalação do equipamento de monitoramento. | L105: oficina IELI 1 | M105: Nilton Guerra Cosme Sousa | N105: Falar com o cliente durante as etapas das intalações para ver se o mesmo esta de acordo
B107: Programação e configuração | C107: Central CFTV | D107: instalação do sistema de segurança e comunicação de acesso remoto por aplicativo e central de monitoramento. | E107: Fazer a comunicação das câmeras com a central | F107: Damião sousa | G107: Leandro Costa Pétrick Gomes | H107: Todos integrantes | I107: Todos integrantes | J107: Central CFTV | K107: Segurança | L107: oficina IELI 1 | M107: Damião sousa | N107: Instalação do DVR e monitor, fazendo a integração com as cameras
C108: Sistemas de iluminação automatizada | D108: Fazer a passagem da fiação pela eletrocalha e instalação do pontos de iluminação e fita LED | E108: O acionamento da iluminaçao manualmente | F108: Cosme Sousa | G108: Leandro Costa Pétrick Gomes | H108: Todos integrantes | I108: Todos integrantes | J108: Sistemas de iluminação automatizada | K108: Conforto e praticidade | L108: oficina IELI 1 | M108: Cosme Sousa | N108: Fazer a instalação e programação da alexa para fazer a integração com as lampadas e fazer seu funcionamento por comando de voz
C110: Central de alarme de incêndio | D110: Realizar a comunicação da central com os sensores de fumaça e termovelocimetricos. | E110: Comunicação da central com os sensores. | F110: Cosme Sousa | G110: Leandro Costa Pétrick Gomes | H110: Todos integrantes | I110: Todos integrantes | J110: Central de alarme de incêndio | K110: Segurança patrimonial | L110: oficina IELI 1 | M110: Cosme Sousa | N110: Fazer a conexão da central com os sensores de fumaça e do alarme de incendio
C111: Sistema de monitoramento de energia | D111: Realizar o monitoramento de consumo de energia em tempo real. | E111: Monitoramento do consumo de energia | F111: Leandro Costa Ferreira João Miranda | G111: Leandro Costa Pétrick Gomes | H111: Todos integrantes | I111: Todos integrantes | J111: Sistema de monitoramento de energia | K111: Praticidade e Economia | L111: oficina IELI 1 | M111: Leandro Costa Ferreira João Miranda | N111: Realizar a montagem do painel e a instalação do sensor para o monitoramento de energia
C113: Módulo CLP, IHM e sistema supervisório | D113: Configurar e fazer a comunicação com os dispositivos | E113: Confiigurar os dispositivos | F113: Leandro Costa Ferreira João Miranda | G113: Leandro Costa Pétrick Gomes | H113: Todos integrantes | I113: Todos integrantes | J113: Módulo CLP, IHM e sistema supervisório | K113: Fazer a interações aos dispositivos com o objetivo de trazer mais conforto e praticidade | L113: oficina IELI 1 | M113: Leandro Costa Ferreira João Miranda | N113: Fazer a instalação do CLP, integrando copm os circuitos da casa, para transmitir um sinal e realizar uma ação
C115: Roteador WI-fi | D115: Comunicação sem fio | E115: Fazer a comunicação via WI-FI | F115: Damião Sousa Pétrick Gomes | G115: Leandro Costa Pétrick Gomes | H115: Todos integrantes | I115: Todos integrantes | J115: Roteador WI-fi | K115: Comunicação sem fio | L115: oficina IELI 1 | M115: Leandro Costa Pétrick Gomes | N115: Instalação dos cabos e conexão com wi-fi para a integração e automatização dos comodos da casa
C117: Integração dos sistemas | D117: Realizar a comunicação entre os dispositivos. | E117: comunicação entre os dispositivos | F117: Damião Sousa Pétrick Gomes | G117: Leandro Costa Pétrick Gomes | H117: Todos integrantes | I117: Todos integrantes | J117: Integração dos sistemas | K117: Realizar a comunicação entre os dispositivos. | L117: oficina IELI 1 | M117: Leandro Costa Pétrick Gomes | N117: Fazer a integração dos comodos com o painel geral e com o painel de monitoramento de energia
A119: FINALIZAÇÃO | B119: Validação | C119: CFTV | D119: Alimentar o sistema de CFTV, certificar de que todas as câmeras estão se comunicando com a central, verificação das imagens e comunicação de acesso remoto. | E119: Analisar se as atividades realizadas satisfaz as expectativas da equipe. | F119: Damião sousa | G119: Leandro Costa Pétrick Gomes | H119: Leandro Costa Pétrick Gomes | I119: Todos integrantes | J119: CFTV | K119: Monitoramento por câmeras | L119: Laboratorio A13/A13 | M119: Damião sousa | N119: Alimentar o sistema de CFTV, certificar de que todas as câmeras estão se comunicando com a central, verificação das imagens e comunicação de acesso remoto.
C120: Central de Incêndio | D120: Certificar o funcionamento e comunicação de todos os sensores com a central. | E120: Analizar se as atividades realizadas satisfaz as expectativas da equipe. | F120: Nilton Guerra | G120: Leandro Costa Pétrick Gomes | H120: Leandro Costa Pétrick Gomes | I120: Todos integrantes | J120: Central de Incêndio | K120: Ele tem um botão, como se fosse um interruptor, que ao ser acionado envia para a central a localização da ocorrência. para rapiada ação. | L120: Laboratorio A13/A17 | M120: Nilton Guerra | N120: Certificar o funcionamento e comunicação de todos os sensores com a central.
C121: Alarme Patrimonial | D121: Conferir lugares que foram fixados de acordo com a Planta baixa, se estamos atendendo as necessidades do cliente, conferir ligações e fazer teste. | E121: Analizar se as atividades realizadas satisfaz as expectativas da equipe. | F121: Nilton Guerra | G121: Leandro Costa Pétrick Gomes | H121: Leandro Costa Pétrick Gomes | I121: Todos integrantes | J121: Alarme Patrimonial | K121: objetivo de proteger pessoas e bens patrimoniais contra condições e atos indesejáveis. | L121: Laboratorio A13/A17 | M121: Nilton Guerra | N121: Conferir lugares que foram fixados de acordo com a Planta baixa, se estamos atendendo as necessidades do cliente, conferir ligações e fazer teste.
C122: Iluminação Automatizada | D122: Realizar os testes de alimentação e funcionamento do sistema, processo de integração com a central e comunicação de acesso remoto. | E122: Analizar se as atividades realizadas satisfaz as expectativas da equipe. | F122: Cosme Sousa | G122: Leandro Costa Pétrick Gomes | H122: Leandro Costa Pétrick Gomes | I122: Todos integrantes | J122: Iluminação Automatizada | K122: Fazer a iluminaçao do anbiente, para garantir segurança. | L122: Laboratorio A13/A18 | M122: Cosme Sousa | N122: Realizar os testes de alimentação e funcionamento do sistema, processo de integração com a central e comunicação de acesso remoto.
C123: Sistema de Monitoramento | D123: Conferir lugares que foram fixados de acordo com a Planta baixa, se estamos atendendo as necessidades do cliente, conferir ligações e fazer teste. | E123: Analizar se as atividades realizadas satisfaz as expectativas da equipe. | F123: Leandro Costa Ferreira João Miranda | G123: Leandro Costa Pétrick Gomes | H123: Leandro Costa Pétrick Gomes | I123: Todos integrantes | J123: Sistema de Monitoramento | K123: Monitora em tempo real o consumo de énegia | L123: Laboratorio A13/A17 | M123: Leandro Costa Ferreira João Miranda | N123: Fazer fixação das cameras de acordo com a Planta baixa, atendendo as necessidades do cliente, conferir ligações e fazer teste.
C125: Módulo CLP, IHM e Sistema Supervisório | D125: Verificar modelo do módulo e IHM do Sistema Supervisório, qual entrada/saída comunica com o sistema que utilizaremos e definir configurações e comandos que serão utilizadas de acordo com o pedido do cliente. | E125: Analizar se as atividades realizadas satisfaz as expectativas da equipe. | F125: Leandro Costa Ferreira João Miranda | G125: Leandro Costa Pétrick Gomes | H125: Leandro Costa Pétrick Gomes | I125: Todos integrantes | J125: Sistema IHM, CLP e Sistema Surpervisorio. | K125: Fazer interface homem maquina | L125: Laboratorio A13/A13 | M125: Leandro Costa Ferreira João Miranda | N125: Fazer comunicação com o sistema IHM com Sistema Supervisório, definindo entrada/saída.
C127: Roteador Wifi ( Comunicação sem fio) | D127: Realizar os testes finais nos periféricos, interface, comunicação e aplicação no sistema. | E127: Analizar se as atividades realizadas satisfaz as expectativas da equipe. | F127: Damião Sousa Pétrick Gomes | G127: Leandro Costa Pétrick Gomes | H127: Leandro Costa Pétrick Gomes | I127: Todos integrantes | J127: Configurar a interação do sistema com as centrais e com sistema de redes sem fio. | K127: responsável por captar e emitir os sinais | L127: Laboratorio A13/A17 | M127: Damião Sousa Pétrick Gomes | N127: Testes finais nos periféricos, interface, comunicação e aplicação no sistema.
B129: Conclusão | C129: Reunião | D129: Reunir-se com o grupo para debatermos possiveis alterações no projeto. | E129: Garantir que tudo esteja nos conformes | F129: Todos integrantes | G129: Leandro Costa Pétrick Gomes | H129: Todos integrantes | I129: Todos integrantes | J129: Reunião | K129: Reunir-se com o grupo para debatermos possiveis alterações no projeto. | L129: Laboratorio A13/A17 | M129: Todos integrantes | N129: Sera discutido a validação das etapas afinalizada para Garantir que tudo esteja nos conformes.
C130: Apresentação de Resultados | D130: Demonstrar previamente o projeto. | E130: Garantir que tudo esteja nos conformes | F130: Leandro Costa Pétrick Gomes | G130: Leandro Costa Pétrick Gomes | H130: Todos integrantes | I130: Todos integrantes | J130: Apresentação de Resultados | K130: Demonstrar previamente o projeto e resultados. | L130: Laboratorio A13/A18 | M130: Leandro Costa Pétrick Gomes | N130: Demonstrar previamente o funcionamento do projeto.
C131: Integração do cliente com o sistema | D131: Relatar para o cliente os resultados do projeto. | E131: Aceitação do cliente de acordo com que foi pedido. | F131: Leandro Costa Pétrick Gomes | G131: Leandro Costa Pétrick Gomes | H131: Todos integrantes | I131: Todos integrantes | J131: Integração do cliente com o sistema | K131: Relatar para o cliente os resultados do projeto. | L131: Laboratorio A13/A18 | M131: Leandro Costa Pétrick Gomes | N131: Aceitação do cliente ser esta de acordo com que foi pedido.
C132: Feedbac+C128:K128k | D132: Fazer possiveis alterações de acordo com a vontade do cliente. | E132: satisfação do cliente | F132: Todos integrantes | G132: Leandro Costa Pétrick Gomes | H132: Todos integrantes | I132: Todos integrantes | J132: Feedback | K132: relatar possiveis auterações no projeto | L132: Laboratorio A13/A17 | M132: Todos integrantes | N132: Será dado retorno do andamento do projeto.
A133: Apresentação do TCC | B133: Entrega do Projeto | C133: Revisão Geral do Projeto | D133: Após o termino de todas as etapas e tarefas, realizar uma revisão completa do projeto, analisando os critérios críticos e desejaveis buscando o máximo de qualidade | E133: Garantir que tudo esteja nos conformes | F133: Todos integrantes | G133: Leandro Costa Pétrick Gomes | H133: Todos integrantes | I133: Todos integrantes | J133: Após o termino de todas as etapas e tarefas, realizar uma revisão completa do projeto, analisando os critérios críticos e desejaveis buscando o máximo de qualidade | K133: Para garantir que tudo esteja conforme o planejado | L133: Laboratorio A13/A17 | M133: Todos os integrantes | N133: consultando o que foi planejado e fazendo testes de funcionamento
C134: Validação com o Orientador | D134: Apresentar os resultados finais para os professores orientadores | E134: Aprovação dos Orientadores | F134: Todos integrantes | G134: Leandro Costa Pétrick Gomes | H134: Todos integrantes | I134: Todos integrantes | J134: Apresentar os resultados finais para os professores orientadores | K134: para ter uma opinião de fora e para que possamos arrumar o necessario | L134: Laboratorio A13/A18 | M134: Todos os integrantes | N134: conversando com o professor e mostrando nosso trabalho
C135: Recapitular e Alterar | D135: Após a válidação e revisão, se necessário, efetuar as modificações necessárias | E135: Gerar um melhoramento | F135: Todos integrantes | G135: Leandro Costa Pétrick Gomes | H135: Todos integrantes | I135: Todos integrantes | J135: Após a válidação e revisão, se necessário, efetuar as modificações necessárias | K135: para ter o melhor projeto possivel | L135: Laboratorio A13/A19 | M135: Todos os integrantes | N135: aplicando as dicas que o professor nos passou
C136: Realizar a Entrega da Documentação e do projeto | D136: Após todas as revisões, validações e modificações, efetuar a entrega do projeto. | E136: Executar entrega . | F136: Todos integrantes | G136: Leandro Costa Pétrick Gomes | H136: Todos integrantes | I136: Todos integrantes | J136: Após todas as revisões, validações e modificações, efetuar a entrega do projeto. | K136: para finalizar o projeto | L136: Laboratorio A13/A20 | M136: Leandro Costa Ferreira | N136: organizando todos os arquivos e enviando pelo teams
B137: Seminario | C137: Elaboração dos Slides | D137: Elaborar slides para auxiliar os integrantes da equipe, contendo imagens, videos, gráficos e tabelas. | E137: Fácil entendimento e que sirva de base para apresentação final. | F137: Todos integrantes | G137: Leandro Costa Pétrick Gomes | H137: Todos integrantes | I137: Todos integrantes | J137: Elaborar slides para auxiliar os integrantes da equipe, contendo imagens, videos, gráficos e tabelas. | K137: para apresentar nosso projeto á banca da melhor forma | L137: Laboratorio A13/A20 | M137: Nilton Guerra | N137: fazendo um resumo do nosso projeto atraves de imagens e videos etc.
C138: Ensaios | D138: Ensaiar a apresentação para preparar todos os integrantes do grupo para a apresentação final | E138: Demonstrar segurança para apresentação | F138: Todos integrantes | G138: Leandro Costa Pétrick Gomes | H138: Todos integrantes | I138: Todos integrantes | J138: Ensaiar a apresentação para preparar todos os integrantes do grupo para a apresentação final | K138: para apresentar nosso projeto á banca da melhor forma | L138: Auditorio | M138: Todos os integrantes | N138: em cima dos slides ensaiar tudo oque iremos apresentar no dia
C139: Revisão | D139: Revisar tudo que foi feito, analisar e corrigir erros ocorridos no ensaio, acertar os ultimos detalhes | E139: Mostrar que a equipe esta preparada para apresentação. | F139: Todos integrantes | G139: Leandro Costa Pétrick Gomes | H139: Todos integrantes | I139: Todos integrantes | J139: Revisar tudo que foi feito, analisar e corrigir erros ocorridos no ensaio, acertar os ultimos detalhes | K139: Mostrar que a equipe esta preparada para apresentação. | L139: Auditorio | M139: Todos os integrantes | N139: fazer a revisão e repassar tudo oque iremos apresentar
C140: Apresentação Final | D140: Apresentação final e conclusão do TCC. | E140: Apresentar para o Orientador e empresa parceira | F140: Todos integrantes | G140: Leandro Costa Pétrick Gomes | H140: Todos integrantes | I140: Todos integrantes | J140: Apresentação final e conclusão do TCC. | K140: fazer a apresntação para os orientadores e banca | L140: Auditorio | M140: Todos os integrantes | N140: Apresentar o projeto

Sheet Dicionario EAP2
D1: AUTOMOÇÃO PREDIAL | G1: LIDER | I1: LEANDRO COSTA FERREIRA | K1: DATA DE INICIO 13/08/2023 | M1: DATA DE ENTREGA 01/12/2022
W2: x
G7: EQUIPE | I7: Pétrick Gomes
I8: Cosme Sousa
I9: Damião Sousa
I10: Nilton Guerra | W10: AGOSTO | Z10: SETEMBRO | AD10: OUTUBRO | AI10: NOVEMBRO | AM10: DEZEMBRO
I11: João Miranda
W13: SEMANA 1 | X13: SEMANA 2 | Y13: SEMANA 3 | Z13: SEMANA 4 | AA13: SEMANA 5 | AB13: SEMANA 6 | AC13: SEMANA 7 | AD13: SEMANA 8 | AE13: SEMANA 9 | AF13: SEMANA 10 | AG13: SEMANA 11 | AH13: SEMANA 12 | AI13: SEMANA 13 | AJ13: SEMANA 14 | AK13: SEMANA 15 | AL13: SEMANA 16 | AM13: SEMANA 17
C14: Criterios de Aceitação | D14: O quê? | E14: Por quê? | F14: Onde? | G14: quem? | H14: Como? | I14: Quando? | N14: Quanto? | R14: RISCO | S14: PESO | T14: PROGRESO | U14: PESO EX | W14: 44421 | X14: =W14+7 -> 44428 | Y14: =X14+7 -> 44435 | Z14: =Y14+7 -> 44442 | AA14: =Z14+7 -> 44449 | AB14: =AA14+7 -> 44456 | AC14: =AB14+7 -> 44463 | AD14: =AC14+7 -> 44470 | AE14: =AD14+7 -> 44477 | ... AL14: =AK14+7 -> 44526 | AM14: =AL14+5 -> 44531
I15: inicio | J15: Otimista | K15: MP | L15: Pessimista | M15: Pert
A16: PLANEJAMENTO | B16: Termo de Abertura do Projeto (TAP | C16: Especificar o objetivo central do projeto. | D16: Formalizar o projeto e as obrigações de todos os integrantes. | E16: Criar responsabilidade para os integrantes do grupo, para auxiliar no desenvolvimento do projeto e inserção dos integrantes nele. | F16: Sala de aula C13. | G16: equipe | H16: Através de um brainstorm de todos os integrantes que irá ser registrado na TAP no projeto | I16: 44421 | J16: 4 | K16: 8 | L16: 12 | M16: =(J16+(4*K16)+L16)/6 -> 8 | N16: =SUM($S$93:$S$96)*M16 -> 809.2 | R16: 3 | S16: =ROUND((M16*R16),1) -> 24 | T16: =U16/S16 -> 1 | U16: =SUM(W16:AO16) -> 24 | W16: 24
C17: Direcionar os integrantes a seus objetivos. | D17: Estruturar as ideias do projeto. | E17: Ter uma lógistica de tarefas fácil de se gerir. | F17: Sala de aula C13. | G17: Todos os integrantes do grupo | H17: Através de um brainstorm de todos os integrantes que irá ser registrado na TAP no projeto | I17: 44425 | J17: 2 | K17: 4 | L17: 6 | M17: =(J17+(4*K17)+L17)/6 -> 4 | N17: =SUM($S$93:$S$96)*M17 -> 404.6 | R17: 2 | S17: =ROUND((M17*R17),1) -> 8 | T17: =U17/S17 -> 1 | U17: =SUM(W17:AO17) -> 8 | W17: 4 | X17: 4
C18: Facilitar o reconhecimento das limitações e acrecismos dos integrantes do Projeto. | D18: verificar as forças e fraquezas de todos os integrantes do grupo. | E18: Facilitar na atribuição de tarefas de todos os integrantes do grupo. | F18: Sala de aula C13. | G18: Todos os integrantes do grupo | H18: Através de um brainstorm de todos os integrantes que irá ser registrado na TAP no projeto | I18: 44421 | J18: 2 | K18: 4 | L18: 6 | M18: =(J18+(4*K18)+L18)/6 -> 4 | N18: =SUM($S$93:$S$96)*M18 -> 404.6 | R18: 2 | S18: =ROUND((M18*R18),1) -> 8 | T18: =U18/S18 -> 1 | U18: =SUM(W18:AO18) -> 8 | W18: 8
C19: Atribuição de reponsabilidades de integrantes especificos em determinadas temas. | D19: Atribuir responsabilidades a todos os integrantes do grupo. | E19: Agilizar a realização do projeto. | F19: Sala de aula C08 | G19: Todos os integrantes do grupo | H19: Através de um brainstorm de todos os integrantes que irá ser registrado na TAP no projeto | I19: 44427 | J19: 1 | K19: 3 | L19: 5 | M19: =(J19+(4*K19)+L19)/6 -> 3 | N19: =SUM($S$93:$S$96)*M19 -> 303.45 | R19: 2 | S19: =ROUND((M19*R19),1) -> 6 | T19: =U19/S19 -> 1 | U19: =SUM(W19:AO19) -> 6 | W19: 6
C20: Gerar um aprimoramento no que já foi realizado. | D20: Revisar o trabalho. | E20: Corrigir possiveis erros gramáticais. | F20: Sala de aula C08 | G20: Todos os integrantes do grupo | H20: Consultando integrantes do grupo e professores. | I20: 44432 | J20: 2 | K20: 4 | L20: 6 | M20: =(J20+(4*K20)+L20)/6 -> 4 | N20: =SUM($S$93:$S$96)*M20 -> 404.6 | R20: 1 | S20: =ROUND((M20*R20),1) -> 4 | T20: =U20/S20 -> 1 | U20: =SUM(W20:AO20) -> 4 | X20: 3 | Y20: 1
C21: Cumprir com os criterios passados em sala de aula e do PMBOK. | D21: Validação. | E21: Fazer uma segunda revisão para verificar possiveis erros. | F21: Sala de aula C08 | G21: Todos os integrantes do grupo | H21: Consultando professores | I21: 44434 | J21: 2 | K21: 4 | L21: 6 | M21: =(J21+(4*K21)+L21)/6 -> 4 | N21: =SUM($S$93:$S$96)*M21 -> 404.6 | R21: 2 | S21: =ROUND((M21*R21),1) -> 8 | T21: =U21/S21 -> 1 | U21: =SUM(W21:AO21) -> 8 | X21: 4 | Y21: 4
B22: Escopo | C22: Definir e separar as principais renponsabilidades em etapas. | D22: Definir como e quando serão realizadas as atividas e etapas do projeto. | E22: Facilitar a gestão do projeto. | F22: Sala de aula C08 | G22: Todos os integrantes do grupo | H22: Através de um brainstrom entre os integrantes do grupo e usando uma planilha do excel definimos as etapas do projeto | I22: 44432 | J22: 2 | K22: 4 | L22: 6 | M22: =(J22+(4*K22)+L22)/6 -> 4 | N22: =SUM($S$93:$S$96)*M22 -> 404.6 | R22: 1 | S22: =ROUND((M22*R22),1) -> 4 | T22: =U22/S22 -> 1 | U22: =SUM(W22:AO22) -> 4 | X22: 1 | Y22: 2 | Z22: 1
C23: Desmembrar as etapas em tarefas. | D23: Dividir o projeto em partes. | E23: Facilitar na gestão do projeto | F23: Sala de aula C08 | G23: Todos os integrantes do grupo | H23: Através de um brainstrom entre os integrantes do grupo nos definimos onde cada tarefa se alocará | I23: 44432 | J23: 3 | K23: 6 | L23: 15 | M23: =(J23+(4*K23)+L23)/6 -> 7 | N23: =SUM($S$93:$S$96)*M23 -> 708.05 | R23: 1 | S23: =ROUND((M23*R23),1) -> 7 | T23: =U23/S23 -> 1 | U23: =SUM(W23:AO23) -> 7 | X23: 1 | Y23: 3 | Z23: 3
C24: Direcionar de maneira mais profundada a todos os processos do projeto. | D24: Descrever as tarefas a serem executadas pelos integrantes baseado na análise SWOT e RACI. | E24: Facilitar na gestão do projeto e trazer mais facilidade no desenvolvimento do projeto. | F24: Sala de aula C08 | G24: Todos os integrantes do grupo | H24: Através de uma divisão dos integrantes nos montamos o dicionário da EAP usando e software da microsoft Excel. | I24: 44434 | J24: 6 | K24: 8 | L24: 16 | M24: =(J24+(4*K24)+L24)/6 -> 9 | N24: =SUM($S$93:$S$96)*M24 -> 910.35 | R24: 1 | S24: =ROUND((M24*R24),1) -> 9 | T24: =U24/S24 -> 1 | U24: =SUM(W24:AO24) -> 9 | X24: 2 | Y24: 2 | Z24: 5
C25: Gerar um aprimoramento naquilo que já foi executado. | D25: Revisar o que se foi realizado. | E25: verificar se o que foi feito está como planejado e sugerir possiveis melhorias. | F25: Sala de aula C08 | G25: Todos os integrantes do grupo | H25: Uma leitura da TAP pelo lider e vice-lider | I25: 44439 | J25: 4 | K25: 9 | L25: 20 | M25: =(J25+(4*K25)+L25)/6 -> 10 | N25: =SUM($S$93:$S$96)*M25 -> 1011.5 | R25: 1 | S25: =ROUND((M25*R25),1) -> 10 | T25: =U25/S25 -> 1 | U25: =SUM(W25:AO25) -> 10 | Y25: 4 | Z25: 4 | AA25: 2
C26: Cumprir com os criterios passados em sala de aula e do PMBOK. | D26: validar o trabalho que foi feito nessa etapa | E26: Verificar se o que foi feito está como planejado. | F26: Sala de aula C08 | G26: Todos os integrantes do grupo | H26: Uma leitura da TAP pelo lider e vice-lider | I26: 44439 | J26: 3 | K26: 6 | L26: 9 | M26: =(J26+(4*K26)+L26)/6 -> 6 | N26: =SUM(S103:S106)*M26 -> 0 | R26: 3 | S26: =ROUND((M26*R26),1) -> 18 | T26: =U26/S26 -> 1 | U26: =SUM(W26:AO26) -> 18 | Y26: 10 | Z26: 5 | AA26: 3
B27: Cronograma | C27: Finalidade do Projeto, a meta final. | D27: Análisar o escopo | E27: Criar um sentimento de responsabilidade para cada integrante do grupo com a tarefa atribuida a ele. | F27: C13 | G27: Leandro Costa Petrick Gomes | H27: Através de uma conversa entre os integrantes nos iremos revisar as divições das tarefas | I27: 44441 | J27: 2 | K27: 3 | L27: 6 | M27: =(J27+(4*K27)+L27)/6 -> 3.3333333 | N27: =SUM(S93+S94)*M27 -> 240 | R27: 3 | S27: =ROUND((M27*R27),1) -> 10 | T27: =U27/S27 -> 1 | U27: =SUM(W27:AO27) -> 10 | Y27: 5 | Z27: 5
C28: Levar um tempo de trabalho necessario e esperado. | D28: Definir o tempo para realizar cada etapa. | E28: Permitir que o projeto seja entregue a tempo. | F28: C13 | G28: Leandro Costa Petrick Gomes | H28: Através da formula de PER, usando o software Excel e uma brainstorm com todos os integrantes definimos as tarefas a serem realizadas. | I28: 44447 | J28: 5 | K28: 7 | L28: 11 | M28: =(J28+(4*K28)+L28)/6 -> 7.3333333 | N28: =SUM($S$94+$S$95)*M28 -> 298.46667 | R28: 3 | S28: =ROUND((M28*R28),1) -> 22 | T28: =U28/S28 -> 1 | U28: =SUM(W28:AO28) -> 22 | Z28: 4 | AA28: 4 | AB28: 14
C29: Levar uma elaboração antecipada. | D29: Definir datas para a entrega de cada etapa do projeto. | E29: Facilitar na gestão do projeto. | F29: C13 | G29: Leandro Costa Petrick Gomes | H29: Através da formula de PER, usando o software Excel e uma brainstorm de todos os integrantes definimos as tarefas a serem realizadas. | I29: 44448 | J29: 4 | K29: 6 | L29: 12 | M29: =(J29+(4*K29)+L29)/6 -> 6.6666667 | N29: =SUM($S$94+$S$95)*M29 -> 271.33333 | R29: 3 | S29: =ROUND((M29*R29),1) -> 20 | T29: =U29/S29 -> 1 | U29: =SUM(W29:AO29) -> 20 | Z29: 4 | AA29: 4 | AB29: 12
C30: Gerar um aprimoramento naquilo que já foi executado. | D30: Revisar o que ja foi realizado. | E30: Sujerir posiveis melhorias e evitar possiveis erros. | F30: C13 | G30: Leandro Costa Petrick Gomes | H30: Uma leitura da TAP pelo lider e vice-lider | I30: 44449 | J30: 2 | K30: 3 | L30: 7 | M30: =(J30+(4*K30)+L30)/6 -> 3.5 | N30: =SUM($S$94+$S$95)*M30 -> 142.45 | R30: 2 | S30: =ROUND((M30*R30),1) -> 7 | T30: =U30/S30 -> 1 | U30: =SUM(W30:AO30) -> 7 | AA30: 1 | AB30: 6
C31: Cumprir com os criterios passados em aula e do PMBOK. | D31: validar o que ja foi realizado. | E31: Sujerir posiveis melhorias e evitar possiveis erros | F31: C13 | G31: Leandro Costa Petrick Gomes | H31: Uma leitura da TAP pelo lider e vice-lider | I31: 44449 | J31: 2 | K31: 3 | L31: 6 | M31: =(J31+(4*K31)+L31)/6 -> 3.3333333 | N31: =SUM($S$94+$S$95)*M31 -> 135.66667 | R31: 3 | S31: =ROUND((M31*R31),1) -> 10 | T31: =U31/S31 -> 1 | U31: =SUM(W31:AO31) -> 10 | AA31: 1 | AB31: 9
B32: Analises de Risco do Projeto | C32: Levantar os possiveis riscos. | D32: Avaliar os possíveis riscos do projeto. | E32: Evitar/ amenizar os riscos ao projeto. | F32: C13 | G32: Cosme Sousa Damião Sousa | H32: Através de um brainstorm de todos os responsaveis iremos abordar possiveis estratégias para evitar os riscos. | I32: 44453 | J32: 4 | K32: 6 | L32: 8 | M32: =(J32+(4*K32)+L32)/6 -> 6 | N32: =($S$95+$S$96)*M32 -> 174.9 | R32: 2 | S32: =ROUND((M32*R32),1) -> 12 | T32: =U32/S32 -> 1 | U32: =SUM(W32:AO32) -> 12 | AA32: 5 | AB32: 7
C33: Preparar-se sob a probabilidade dos riscos. | D33: Avaliar a probabilidade dos riscos acontecerem. | E33: Fazer preparações de acordo com o nivel de probabilidade. | F33: C13 | G33: Cosme Sousa Damião Sousa | H33: Através de um brainstorm de todos os responsaveis considerar quais os riscos mais prováveis. | I33: 44455 | J33: 4 | K33: 6 | L33: 8 | M33: =(J33+(4*K33)+L33)/6 -> 6 | N33: =($S$95+$S$96)*M33 -> 174.9 | R33: 2 | S33: =ROUND((M33*R33),1) -> 12 | T33: =U33/S33 -> 1 | U33: =SUM(W33:AO33) -> 12 | AA33: 12
C34: Gerar possiveis consequências. | D34: Definir o quão grave é o risco e as medidas de supressão dele. | E34: Definir o que será feito, caso algum risco venha acontecer. | F34: C13 | G34: Cosme Sousa Damião Sousa | H34: Através de um brainstorm de todos os responsaveis iremos abordar possiveis estratégias para evitar os riscos. | I34: 44455 | J34: 4 | K34: 6 | L34: 8 | M34: =(J34+(4*K34)+L34)/6 -> 6 | N34: =($S$95+$S$96)*M34 -> 174.9 | R34: 3 | S34: =ROUND((M34*R34),1) -> 18 | T34: =U34/S34 -> 1 | U34: =SUM(W34:AO34) -> 18 | AA34: 18
C35: Comparar o tempo de trabalho com a meta. | D35: Fazer um gráfico de acompanhamento do trabalho. | E35: Avaliar o desenvolvimento do projeto e analisar se está caminhando de acordo com o planejado, para poder gerar uma possivel data de entrega. | F35: C13 | G35: Cosme Sousa Damião Sousa | H35: Através da formula de PER iremos desenvolver quanto tempo é necessário para a execução de cada tarefa do projeto e com essa informação iremos estimar uma valor em pontos para cada atividade que por fim será usado no gráfico do burndown chart juntamente com o tempo disponivel. | I35: 44455 | J35: 4 | K35: 6 | L35: 8 | M35: =(J35+(4*K35)+L35)/6 -> 6 | N35: =($S$95+$S$96)*M35 -> 174.9 | R35: 3 | S35: =ROUND((M35*R35),1) -> 18 | T35: =U35/S35 -> 1 | U35: =SUM(W35:AO35) -> 18 | AA35: 18
A36: INSTALAÇÃO | B36: Painéis | C36: Permitir que todos os quadros de energia possam ser instalados dentro do quadro de distribuição | D36: Usar a escala de mm para definir o tamanho do quadro de distribuição que conterá os quadros de iluminação, CFTV e alarme de incêndio. | E36: Para trazer uma sensação visual melhor, evitar gastos desnecessários e facilitar possiveis aprimoramentos da instalação. | F36: oficina IELI 1 | G36: Leandro Costa João Miranda | H36: Através de um técnico altamente treinado irá ser feito um dimenciosamento do sistema elétrico da instalação e com essa insformação iremos definir a quantidade de componentes necessarios para a instalação e assim a dimenção do quadro | I36: 44459 | J36: 4 | K36: 5 | L36: 8 | M36: =(J36+(4*K36)+L36)/6 -> 5.3333333 | N36: =($S$95+$S$96)*M36 -> 155.46667 | R36: 3 | S36: =ROUND((M36*R36),1) -> 16 | T36: =U36/S36 -> 1 | U36: =SUM(W36:AO36) -> 16 | AB36: 10 | AC36: 3 | AD36: 3
C37: Proteção de todos os circuitos da residência, seguindo a norma NR10. | D37: Usar dispositivos de proteção como: DR e DPS para a proteção dos circuitos. | E37: proteger o circuito. | F37: oficina IELI 1 | G37: Leandro Costa João Miranda | H37: Usando os conhecimento adquiridos pelo curso de eletroeletrônica do SENAI, iremos dimencionar o quadro de força | I37: 44459 | J37: 4 | K37: 5 | L37: 8 | M37: =(J37+(4*K37)+L37)/6 -> 5.3333333 | N37: =($S$95+$S$96)*M37 -> 155.46667 | R37: 3 | S37: =ROUND((M37*R37),1) -> 16 | T37: =U37/S37 -> 1 | U37: =SUM(W37:AO37) -> 16 | AB37: 13 | AC37: 3
B38: Instalação do CFTV | C38: Fazer a alimentação das câmeras e do DRV com condutores isolados e sem imendas nos eletrodutos. | D38: Passar os cabos pelos eletrodutos. | E38: Permitir a alimentação dos componentes. | F38: oficina IELI 1 | G38: Pétrick Gomes Cosme Sousa Damião Sousa Nilton Guerra | H38: Fazer o dimensionamento dos cabos para a instalação das câmeras | I38: 44461 | J38: 4 | K38: 5 | L38: 10 | M38: 1 | N38: =$S$95+(4*$S$96)*M38 -> 60.5 | R38: 3 | S38: =ROUND((M38*R38),1) -> 3 | T38: =U38/S38 -> 1 | U38: =SUM(W38:AO38) -> 3 | AB38: 3
C39: Fixar as câmeras e fazer a alimentação e a transmição de dados com facilidade. | D39: Instalar apoios para as câmeras através de parafusos e porcas, para logo em seguida colocar as câmeras. | E39: Para permitir a monitoração de locais previamentes desiginados. | F39: oficina IELI 1 | G39: Pétrick Gomes Cosme Sousa Damião Sousa Nilton Guerra | H39: definir posição para instalação das câmeras | I39: 44462 | J39: 2 | K39: 4 | L39: 6 | M39: 1 | N39: =$S$95+(4*$S$96)*M39 -> 60.5 | R39: 2 | S39: =ROUND((M39*R39),1) -> 2 | T39: =U39/S39 -> 1 | U39: =SUM(W39:AO39) -> 2 | AB39: 2
C40: Permitir a comunicação do monitor com o DRV | D40: usar o cabo VGA para comunicar o DVR com o monitor e alimentar ambos. | E40: Para permitir o acompanhamneto da vigilância dos locais pelo monitor. | F40: oficina IELI 1 | G40: Pétrick Gomes Cosme Sousa Damião Sousa Nilton Guerra | H40: Interligação do DVR com o monitor | I40: 44462 | J40: 2 | K40: 4 | L40: 6 | M40: 1 | N40: =$S$95+(4*$S$96)*M40 -> 60.5 | R40: 2 | S40: =ROUND((M40*R40),1) -> 2 | T40: =U40/S40 -> 1 | U40: =SUM(W40:AO40) -> 2 | AB40: 2
C41: Permitir a visualização dos pontos de vigilância no monitor | D41: usando o conector P4 macho e fêmea e o cabo coaxial fazer o interligamento da câmera com o DVR. | E41: Comunicar o DVR com as câmeras. | F41: oficina IELI 1 | G41: Pétrick Gomes Cosme Sousa Damião Sousa Nilton Guerra | H41: Interligação das câmeras com Central para ser feito monitoriamento com DVR | I41: 44462 | J41: 2 | K41: 4 | L41: 6 | M41: 1 | N41: =$S$95+(4*$S$96)*M41 -> 60.5 | R41: 3 | S41: =ROUND((M41*R41),1) -> 3 | T41: =U41/S41 -> 1 | U41: =SUM(W41:AO41) -> 3 | AB41: 3
B42: Instalação da central | C42: Que os cabos passados sejam alimentados e devidamente isolados sem imentas nos eletrodutos. | D42: Passar os cabos pelos eletrodutos. | E42: Permitir a alimentação dos componentes | F42: oficina IELI 1 | G42: Cosme Sousa Damião Sousa Pétrick Gomes Nilton Guerra | H42: Usando um guia passa fio iremos direcionar os cabos para suas devidas posições já estipuladas no planejamento. | I42: 44463 | J42: 2 | K42: 4 | L42: 6 | M42: 1 | N42: =$S$95+(4*$S$96)*M42 -> 60.5 | R42: 2 | S42: =ROUND((M42*R42),1) -> 2 | T42: =U42/S42 -> 1 | U42: =SUM(W42:AO42) -> 2 | AC42: 2
C43: Ligar todas as conexões dos sensores corretamente. | D43: Instalar os sensores de fumaça respeitando as suas coneções com a central de incêndio. | E43: Permitir que o sensor funcione corretamente. | F43: oficina IELI 1 | G43: Cosme Sousa Damião Sousa Pétrick Gomes Nilton Guerra | H43: Usando a escada e uma chave de fenda iremos instalar os sensores de fumaça respeitando a posição de cada cabo. | I43: 44463 | J43: 4 | K43: 6 | L43: 8 | M43: 1 | N43: =$S$95+(4*$S$96)*M43 -> 60.5 | R43: 3 | S43: =ROUND((M43*R43),1) -> 3 | T43: =U43/S43 -> 1 | U43: =SUM(W43:AO43) -> 3 | AC43: 3
C44: Fazer a comunicação entre central de alarme de incêndio e sensores de fumaça. | D44: Posicionar a centrtal em um local especifico para gerenciar o controle de incêndio. | E44: Ter um controle mais rápido e eficiente do sistema de incêndio | F44: oficina IELI 1 | G44: Cosme Sousa Damião Sousa Pétrick Gomes Nilton Guerra | H44: definir uma posição para a central de incêndio que não incomode ninguém | I44: 44466 | J44: 4 | K44: 6 | L44: 8 | M44: 1 | N44: =$S$95+(4*$S$96)*M44 -> 60.5 | R44: 2 | S44: =ROUND((M44*R44),1) -> 2 | T44: =U44/S44 -> 1 | U44: =SUM(W44:AO44) -> 2 | AB44: 2
B45: Instalação de Iluminação | C45: Que os cabos passados sejam alimentados e devidamente isolados sem emendas nos eletrodutos. | D45: Passar os cabos pelos eletrodutos. | E45: Permitir a alimentação dos componentes | F45: oficina IELI 1 | G45: Cosme Sousa Damião Sousa Pétrick Gomes Leandro Costa | H45: Usando um passa fio iremos direcionar os cabos para suas devidas posições já estipuladas no planejamento. | I45: 44474 | J45: 2 | K45: 5 | L45: 8 | M45: 6 | N45: =$S$95+(4*$S$96)*M45 -> 269.5 | R45: 2 | S45: =ROUND((M45*R45),1) -> 12 | T45: =U45/S45 -> 1 | U45: =SUM(W45:AO45) -> 12 | AD45: 5 | AE45: 5 | AF45: 2
C46: Fazer a instalação dos interruptores e lâmpadas | D46: Instalação dos interruptores e receptáculos, e logo em seguida colocar as lâmpadas nos respectivos cômodos da residência. | E46: Iluminar o ambiente. | F46: oficina IELI 1 | G46: Cosme Sousa Damião Sousa Pétrick Gomes Leandro Costa | H46: com a passagem dos cabos realizaremos a instalação dos dispositivos de iluminação | I46: 44476 | J46: 2 | K46: 3 | L46: 4 | M46: =(J46+(4*K46)+L46)/6 -> 3 | N46: =$S$95+(4*$S$96)*M46 -> 144.1 | R46: 3 | S46: =ROUND((M46*R46),1) -> 9 | T46: =U46/S46 -> 1 | U46: =SUM(W46:AO46) -> 9 | AD46: 2 | AE46: 7
C47: fazer a integração dos sistema de iluminação com os aplicativos (bluelux,sonoff). | D47: Instalação dos interruptores | E47: instalar interruptores e tomadas | F47: oficina IELI 1 | G47: Cosme Sousa Damião Sousa Pétrick Gomes Leandro Costa | H47: usando o interruptor móvel, um interruptor pulsador e o aplicativo do interruptor idemos sincronizar-los. | I47: 44477 | J47: 2 | K47: 3 | L47: 4 | M47: =(J47+(4*K47)+L47)/6 -> 3 | N47: =$S$95+(4*$S$96)*M47 -> 144.1 | R47: 3 | S47: =ROUND((M47*R47),1) -> 9 | T47: =U47/S47 -> 1 | U47: =SUM(W47:AO47) -> 9 | AE47: 9
C48: Verificar o funcionamento do sistema de iluminação controlado pelos dispositivos moveis. | D48: Verificação do sistema de iluminação. | E48: Verificar o correto funcionamento. | F48: oficina IELI 1 | G48: Cosme Sousa Damião Sousa Pétrick Gomes Leandro Costa | H48: Usando o aplicativo do interruptor movél iremos configurar o aplicativo. | I48: 44477 | J48: 1 | K48: 2 | L48: 3 | M48: =(J48+(4*K48)+L48)/6 -> 2 | N48: =$S$95+(4*$S$96)*M48 -> 102.3 | R48: 3 | S48: =ROUND((M48*R48),1) -> 6 | T48: =U48/S48 -> 1 | U48: =SUM(W48:AO48) -> 6 | AE48: 6
B49: Instalação do sistema de monitoramento de consumo de energia | C49: Fazer a instalação do monitor de energia no painel. | D49: Verificar ligação do monitor de energia. | E49: Maior conforto visual e segurança | F49: oficina IELI 1 | G49: Leandro Costa João Miranda | H49: Instalação do quadro de monitoramento de energia ao lado do quadro de distribuição | I49: 44487 | J49: 3 | K49: 4 | L49: 8 | M49: =(J49+(4*K49)+L49)/6 -> 4.5 | N49: =($S$95+$S$96)*M49 -> 131.175 | R49: 2 | S49: =ROUND((M49*R49),1) -> 9 | T49: =U49/S49 -> 1 | U49: =SUM(W49:AO49) -> 9 | AF49: 3 | AG49: 6
C50: verificar funcionamento do monitor de energia. | D50: Ultilizar TC`s para a leitura de corrente atráves do medidor e verificar as suas respectivas conexões. | E50: Monitorar o circuito, atrávez de parâmetros de leitura já definido pelo medidor. | F50: oficina IELI 1 | G50: Leandro Costa João Miranda | H50: Interligar com o circuito para fazer o monitoramento | I50: 44493 | J50: 2 | K50: 4 | L50: 6 | M50: =(J50+(4*K50)+L50)/6 -> 4 | N50: =($S$95+$S$96)*M50 -> 116.6 | R50: 2 | S50: =ROUND((M50*R50),1) -> 8 | T50: =U50/S50 -> 1 | U50: =SUM(W50:AO50) -> 8 | AG50: 8
C51: Verificar se o monitor de energia está funcionando corretamente. | D51: Usando um multimetro, o monitor de energia e uma carga verificar se os resultados de leitura estão corretos. | E51: Validar se o aparelho está funcionando corretamente | F51: oficina IELI 1 | G51: Leandro Costa João Miranda | H51: Usando um multimetro iremos validar a medição do monitor de consumo de energia. | I51: 44493 | J51: 1 | K51: 3 | L51: 5 | M51: =(J51+(4*K51)+L51)/6 -> 3 | N51: =($S$95+$S$96)*M51 -> 87.45 | R51: 3 | S51: =ROUND((M51*R51),1) -> 9 | T51: =U51/S51 -> 1 | U51: =SUM(W51:AO51) -> 9 | AG51: 9
B52: Instalação da Assistente de Voz | C52: Controlar alexa pelo app. | D52: fazer a programação e configurações da alexa atraves do aplicativo. | E52: Permitir o acionamento da iluminação através do celular. | F52: oficina IELI 1 | G52: Pétrick Gomes João Miranda Nilton Guerra | H52: Usando o aplicativo da Alexa no smartfone iremos configurar a assistente de voz. | I52: 44497 | J52: 4 | K52: 6 | L52: 8 | M52: =(J52+(4*K52)+L52)/6 -> 6 | N52: =$S$95+(2*$S$96)*M52 -> 144.1 | R52: 1 | S52: =ROUND((M52*R52),1) -> 6 | T52: =U52/S52 -> 1 | U52: =SUM(W52:AO52) -> 6 | AG52: 6
C53: Alexa Responder aos comandos corretamente. | D53: Realizar testes para conferir o funcionamento da alexa. | E53: Trazer segurança e agilidade para instalação. Além de um conforto maior. | F53: oficina IELI 1 | G53: Pétrick Gomes João Miranda Nilton Guerra | H53: usando a voz iremos testar se a Alexa responde | I53: 44497 | J53: 2 | K53: 4 | L53: 6 | M53: =(J53+(4*K53)+L53)/6 -> 4 | N53: =$S$95+(2*$S$96)*M53 -> 102.3 | R53: 2 | S53: =ROUND((M53*R53),1) -> 8 | T53: =U53/S53 -> 1 | U53: =SUM(W53:AO53) -> 8 | AG53: 8
C54: Alexa controlar outros dispositivos. | D54: Fazer a configuração da alexa com outros dispositivos. | E54: Fazer a integração de outro dispositivos com o objetivo de trazer mais conforto e praticidade. | F54: oficina IELI 1 | G54: Pétrick Gomes João Miranda Nilton Guerra | H54: Usando o aplicativo da alexa iremos sincronizar a alexa com outros equipamentos | I54: 44504 | J54: 4 | K54: 6 | L54: 8 | M54: =(J54+(4*K54)+L54)/6 -> 6 | N54: =$S$95+(2*$S$96)*M54 -> 144.1 | R54: 1 | S54: =ROUND((M54*R54),1) -> 6 | T54: =U54/S54 -> 1 | U54: =SUM(W54:AO54) -> 6 | AH54: 6
B55: Instalação do interfone | C55: Interfone estar fixado. | D55: fazer a instalação do interfone na local. | E55: Trazer mais conforto e segurança para o local. | F55: oficina IELI 1 | G55: Nilton Guerra | H55: Instalaçao e fixação das bases do Interfone. | I55: 44469 | J55: 2 | K55: 4 | L55: 6 | M55: =(J55+(4*K55)+L55)/6 -> 4 | N55: =$S$95*M55 -> 74.8 | R55: 2 | S55: =ROUND((M55*R55),1) -> 8 | T55: =U55/S55 -> 1 | U55: =SUM(W55:AO55) -> 8 | AC55: 8
C56: Verificar o funcionando do interfone | D56: Fazer testes para conferir o funcionamento do interfone. | E56: Validar o funcionamento do interfone. | F56: oficina IELI 1 | G56: Nilton Guerra | H56: Energização e teste de funcionámento dos componentes. | I56: 44470 | J56: 1 | K56: 2 | L56: 6 | M56: =(J56+(4*K56)+L56)/6 -> 2.5 | N56: =$S$95*M56 -> 46.75 | R56: 2 | S56: =ROUND((M56*R56),1) -> 5 | T56: =U56/S56 -> 1 | U56: =SUM(W56:AO56) -> 5 | AD56: 5
C57: Interfone funcionar junto ao sistema de segurança | D57: Fazer a integração do interfone com a trava automatica. | E57: Trazer mais segurança. | F57: oficina IELI 1 | G57: Nilton Guerra | H57: Fazer Passagem dos cabos einterligação do interfone e fechadura. | I57: 44470 | J57: 2 | K57: 3 | L57: 6 | M57: =(J57+(4*K57)+L57)/6 -> 3.3333333 | N57: =$S$95*M57 -> 62.333333 | R57: 3 | S57: =ROUND((M57*R57),1) -> 10 | T57: =U57/S57 -> 1 | U57: =SUM(W57:AO57) -> 10 | AD57: 10
B58: Instalação trava automatica | C58: Instalação das travas automaticas. | D58: Fazer a instalação das travas automaticas. | E58: trazer mais segurança. | F58: oficina IELI 1 | G58: Nilton Guerra | H58: seguindo o diagrama | I58: 44470 | J58: 2 | K58: 3 | L58: 6 | M58: =(J58+(4*K58)+L58)/6 -> 3.3333333 | N58: =$S$95*M58 -> 62.333333 | R58: 3 | S58: =ROUND((M58*R58),1) -> 10 | T58: =U58/S58 -> 1 | U58: =SUM(W58:AO58) -> 10 | AD58: 10
C59: Verificar o funcionamento da trava. | D59: Fazer testes para conferir o funcionamento dos dispositivos. | E59: validar o funcionamento da trava automatica. | F59: oficina IELI 1 | G59: Nilton Guerra | H59: Energização e teste dos componentes. | I59: 44470 | J59: 2 | K59: 4 | L59: 6 | M59: =(J59+(4*K59)+L59)/6 -> 4 | N59: =$S$95*M59 -> 74.8 | R59: 2 | S59: =ROUND((M59*R59),1) -> 8 | T59: =U59/S59 -> 1 | U59: =SUM(W59:AO59) -> 8 | AD59: 8
C60: Integrar com sistema de segurança | D60: Fazer a integração da trava automativa com o internofe. | E60: Trazer mais segurança. | F60: oficina IELI 1 | G60: Nilton Guerra | H60: Interligar interfone e fechadura com Central. | I60: 44470 | J60: 2 | K60: 3 | L60: 6 | M60: =(J60+(4*K60)+L60)/6 -> 3.3333333 | N60: =$S$95*M60 -> 62.333333 | R60: 3 | S60: =ROUND((M60*R60),1) -> 10 | T60: =U60/S60 -> 1 | U60: =SUM(W60:AO60) -> 10 | AD60: 10
A61: CONFIGURAÇÃO | B61: Sistema de Monitoramento | C61: Acrescentar base ao projeto. | D61: Levantamento dos equipamentos e manuais necessários | E61: Ferramentas e equipamentos necessario para a instalação do projeto. | F61: oficina IELI 1 | G61: Nilton Guerra Cosme Sousa | H61: através de um dialogo com os professores iremos buscar informações em relação aos equipamentos procurar os | J61: 4 | K61: 6 | L61: 8 | M61: =(J61+(4*K61)+L61)/6 -> 6 | R61: 3 | S61: =ROUND((M61*R61),1) -> 18 | T61: =U61/S61 -> 0 | U61: =SUM(W61:AO61) -> 0
C62: Garantir material ao projeto. | D62: Configurações remotas e manuais | E62: Fazer o acionamentvia wifi o e manualmente. | F62: oficina IELI 1 | G62: Nilton Guerra Cosme Sousa | H62: baixar e configurar os aplicativos necessários, através do celular e fazer a configuração do DVR para o funcionamento da imagem das cameras | J62: 4 | M62: =(J62+(4*K62)+L62)/6 -> 0.66666667 | R62: 1 | S62: =ROUND((M62*R62),1) -> 0.7 | T62: =U62/S62 -> 0 | U62: =SUM(W62:AO62) -> 0
C63: Ser um meio de realização do trabalho. | D63: Integração com centrais e redes sem fio | E63: Fazer o acionamentvia WIFI. | F63: oficina IELI 1 | G63: Nilton Guerra Cosme Sousa | H63: Fazer a separação e instalação dos cabos para a conexão do DVR com as cameras | J63: 4 | M63: =(J63+(4*K63)+L63)/6 -> 0.66666667 | R63: 2 | S63: =ROUND((M63*R63),1) -> 1.3 | T63: =U63/S63 -> 0 | U63: =SUM(W63:AO63) -> 0
C64: Sistema base do projeto. | D64: Integração com o cliente | E64: Verificar os pontos mas apropriados para instalação do equipamento de monitoramento. | F64: oficina IELI 1 | G64: Nilton Guerra Cosme Sousa | H64: Falar com o cliente durante as etapas das intalações para ver se o mesmo esta de acordo | J64: 4 | M64: =(J64+(4*K64)+L64)/6 -> 0.66666667 | R64: 2 | S64: =ROUND((M64*R64),1) -> 1.3 | T64: =U64/S64 -> 0 | U64: =SUM(W64:AO64) -> 0
B65: Programação e configuração | C65: Fazer a comunicação das câmeras com a central. | D65: Central CFTV | E65: Segurança. | F65: oficina IELI 1 | G65: Pétrick Gomes Cosme Sousa Damião Sousa Nilton Guerra | H65: Instalação do DVR e monitor, fazendo a integração com as cameras | I65: 44462 | J65: 2 | K65: 3 | L65: 6 | M65: =(J65+(4*K65)+L65)/6 -> 3.3333333 | N65: =$S$95+($S$96*3)*M65 -> 123.2 | R65: 3 | S65: =ROUND((M65*R65),1) -> 10 | T65: =U65/S65 -> 1 | U65: =SUM(W65:AO65) -> 10 | AB65: 10
C66: O acionamento da iluminaçao remotamente. | D66: Sistemas de iluminação automatizada. | E66: Conforto e praticidade. | F66: oficina IELI 1 | G66: Pétrick Gomes Cosme Sousa Damião Sousa Nilton Guerra | H66: Fazer a instalação e programação da alexa para fazer a integração com as lampadas e fazer seu funcionamento por comando de voz | I66: 44474 | J66: 1 | K66: 3 | L66: 5 | M66: =(J66+(4*K66)+L66)/6 -> 3 | N66: =$S$95+($S$96*3)*M66 -> 112.75 | R66: 2 | S66: =ROUND((M66*R66),1) -> 6 | T66: =U66/S66 -> 1 | U66: =SUM(W66:AO66) -> 6 | AD66: 3 | AE66: 3
C67: Comunicação da central com os sensores. | D67: Central de alarme de incêndio. | E67: Segurança patrimonial. | F67: oficina IELI 1 | G67: Cosme Sousa Damião Sousa Pétrick Gomes Nilton Guerra | H67: Fazer a conexão da central com os sensores de fumaça e do alarme de incendio | I67: 44466 | J67: 4 | K67: 6 | L67: 8 | M67: =(J67+(4*K67)+L67)/6 -> 6 | N67: =$S$95+($S$96*3)*M67 -> 206.8 | R67: 3 | S67: =ROUND((M67*R67),1) -> 18 | T67: =U67/S67 -> 1 | U67: =SUM(W67:AO67) -> 18 | AC67: 18
C68: Monitoramento do consumo de energia. | D68: Sistema de monitoramento de energia. | E68: Praticidade e Acompanhamento em tempo real. | F68: oficina IELI 1 | G68: Leandro Costa João Miranda | H68: Realizar a montagem do painel e a instalação do sensor para o monitoramento de energia | I68: 44487 | J68: 4 | K68: 6 | L68: 8 | M68: =(J68+(4*K68)+L68)/6 -> 6 | N68: =($S$95+$S$96)*M68 -> 174.9 | R68: 2 | S68: =ROUND((M68*R68),1) -> 12 | T68: =U68/S68 -> 1 | U68: =SUM(W68:AO68) -> 12 | AG68: 12
C69: Fazer a comunicação via WI-FI. | D69: Roteador WI-fi. | E69: Comunicação sem fio. | F69: oficina IELI 1 | G69: Leandro Costa João Miranda | H69: Instalação dos cabos e conexão com wi-fi para a integração e automatização dos comodos da casa | I69: 44487 | J69: 4 | K69: 6 | L69: 8 | M69: =(J69+(4*K69)+L69)/6 -> 6 | N69: =($S$95+$S$96)*M69 -> 174.9 | R69: 2 | S69: =ROUND((M69*R69),1) -> 12 | T69: =U69/S69 -> 1 | U69: =SUM(W69:AO69) -> 12 | AF69: 12
C70: Comunicação entre os dispositivos. | D70: Integração dos sistemas. | E70: Realizar a comunicação entre os dispositivos. | F70: oficina IELI 1 | G70: Leandro Costa Pétrick Gomes | H70: Fazer a integração dos comodos com o painel geral e com o painel de monitoramento de energia | I70: 44498 | J70: 4 | K70: 6 | L70: 8 | M70: =(J70+(4*K70)+L70)/6 -> 6 | N70: =($S$95+$S$96)*M70 -> 174.9 | R70: 2 | S70: =ROUND((M70*R70),1) -> 12 | T70: =U70/S70 -> 1 | U70: =SUM(W70:AO70) -> 12 | AG70: 12
A71: FINALIZAÇÃO | B71: Validação | C71: Analisar se as atividades realizadas satisfaz as expectativas da equipe. | D71: CFTV. | E71: Monitoramento das câmeras | F71: Laboratorio A13/A13 | G71: Damião sousa | H71: Alimentar o sistema de CFTV, certificar de que todas as câmeras estão se comunicando com a central, verificação das imagens e comunicação de acesso remoto. | I71: 44501 | J71: 2 | K71: 4 | L71: 6 | M71: =(J71+(4*K71)+L71)/6 -> 4 | N71: =M71*$S$95 -> 74.8 | R71: 2 | S71: =ROUND((M71*R71),1) -> 8 | T71: =U71/S71 -> 1 | U71: =SUM(W71:AO71) -> 8 | AH71: 8
C72: Analizar se as atividades realizadas satisfaz as expectativas da equipe. | D72: Central de Incêndio | E72: Ele tem um botão, como se fosse um interruptor, que ao ser acionado envia para a central a localização da ocorrência. para rapiada ação. | F72: Laboratorio A13/A17 | G72: Nilton Guerra | H72: Certificar o funcionamento e comunicação de todos os sensores com a central. | I72: 44501 | J72: 2 | K72: 4 | L72: 6 | M72: =(J72+(4*K72)+L72)/6 -> 4 | N72: =M72*$S$95 -> 74.8 | R72: 2 | S72: =ROUND((M72*R72),1) -> 8 | T72: =U72/S72 -> 1 | U72: =SUM(W72:AO72) -> 8 | AH72: 8
C73: Analizar se as atividades realizadas satisfaz as expectativas da equipe. | D73: Iluminação Automatizada | E73: Fazer a iluminaçao do ambiente, para garantir segurança. | F73: Laboratorio A13/A18 | G73: Cosme Sousa | H73: Realizar os testes de alimentação e funcionamento do sistema, processo de integração com a central e comunicação de acesso remoto. | I73: 44501 | J73: 2 | K73: 4 | L73: 6 | M73: =(J73+(4*K73)+L73)/6 -> 4 | N73: =M73*$S$95 -> 74.8 | R73: 2 | S73: =ROUND((M73*R73),1) -> 8 | T73: =U73/S73 -> 1 | U73: =SUM(W73:AO73) -> 8 | AH73: 5 | AI73: 3
C74: Analizar se as atividades realizadas satisfaz as expectativas da equipe. | D74: Sistema de Monitoramento | E74: Monitora em tempo real o consumo de energia. | F74: Laboratorio A13/A17 | G74: Leandro Costa João Miranda | H74: Fazer fixação das cameras de acordo com a Planta baixa, atendendo as necessidades do cliente, conferir ligações e fazer teste. | I74: 44501 | J74: 2 | K74: 4 | L74: 6 | M74: =(J74+(4*K74)+L74)/6 -> 4 | N74: =($S$95+$S$96)*M74 -> 116.6 | R74: 2 | S74: =ROUND((M74*R74),1) -> 8 | T74: =U74/S74 -> 1 | U74: =SUM(W74:AO74) -> 8 | AH74: 8
C75: Analizar se as atividades realizadas satisfaz as expectativas da equipe. | D75: Configurar a interação do sistema com as centrais e com sistema de redes sem fio. | E75: responsável por captar e emitir os sinais | F75: Laboratorio A13/A17 | G75: Damião Sousa Pétrick Gomes | H75: Testes finais nos periféricos, interface, comunicação e aplicação no sistema. | I75: 44501 | J75: 2 | K75: 4 | L75: 6 | M75: =(J75+(4*K75)+L75)/6 -> 4 | N75: =($S$95+$S$96)*M75 -> 116.6 | R75: 3 | S75: =ROUND((M75*R75),1) -> 12 | T75: =U75/S75 -> 1 | U75: =SUM(W75:AO75) -> 12 | AH75: 12
B76: Conclusão | C76: Garantir que tudo esteja como planejado. | D76: Reunião | E76: Reunir-se com o grupo para debatermos possiveis alterações no projeto. | F76: Laboratorio A13/A17 | G76: Todos integrantes | H76: Sera discutido a validação das etapas afinalizada para Garantir que tudo esteja nos conformes. | I76: 44516 | J76: 4 | K76: 6 | L76: 8 | M76: =(J76+(4*K76)+L76)/6 -> 6 | N76: =SUM($S$93:$S$96)*M76 -> 606.9 | R76: 3 | S76: =ROUND((M76*R76),1) -> 18 | T76: =U76/S76 -> 1 | U76: =SUM(W76:AO76) -> 18 | AI76: 18
C77: Garantir que tudo esteja nos conformes | D77: Apresentação de Resultados. | E77: Demonstrar previamente o projeto e resultados. | F77: Laboratorio A13/A18 | G77: Leandro Costa Pétrick Gomes | H77: Demonstrar previamente o funcionamento do projeto. | I77: 44503 | J77: 4 | K77: 6 | L77: 8 | M77: =(J77+(4*K77)+L77)/6 -> 6 | N77: =($S$95+$S$96)*M77 -> 174.9 | R77: 3 | S77: =ROUND((M77*R77),1) -> 18 | T77: =U77/S77 -> 1 | U77: =SUM(W77:AO77) -> 18 | AH77: 18
C78: Aceitação do cliente de acordo com que foi pedido. | D78: Integração do cliente com o sistema. | E78: Relatar para o cliente os resultados do projeto. | F78: Laboratorio A13/A18 | G78: Leandro Costa Pétrick Gomes | H78: Aceitação do cliente ser esta de acordo com que foi pedido. | I78: 44518 | J78: 4 | K78: 6 | L78: 8 | M78: =(J78+(4*K78)+L78)/6 -> 6 | N78: =($S$95+$S$96)*M78 -> 174.9 | R78: 3 | S78: =ROUND((M78*R78),1) -> 18 | T78: =U78/S78 -> 1 | U78: =SUM(W78:AO78) -> 18 | AJ78: 18
C79: Satisfação do cliente. | D79: Feedback | E79: Relatar possiveis alterações no projeto. | F79: Laboratorio A13/A17 | G79: Todos integrantes | H79: Será dado retorno do andamento do projeto. | I79: 44518 | J79: 4 | K79: 6 | L79: 8 | M79: =(J79+(4*K79)+L79)/6 -> 6 | N79: =SUM($S$93:$S$96)*M79 -> 606.9 | R79: 3 | S79: =ROUND((M79*R79),1) -> 18 | T79: =U79/S79 -> 1 | U79: =SUM(W79:AO79) -> 18 | AJ79: 18
A80: Apresentação do TCC | B80: Entrega do Projeto | C80: Garantir que tudo esteja como planejado. | D80: Após o termino de todas as etapas e tarefas, realizar uma revisão completa do projeto, analisando os critérios críticos e desejaveis buscando o máximo de qualidade. | E80: Para garantir que tudo esteja conforme o planejado. | F80: Laboratorio A13/A17 | G80: Todos os integrantes | H80: consultando o que foi planejado e fazendo testes de funcionamento | I80: 44516 | J80: 4 | K80: 6 | L80: 9 | M80: =(J80+(4*K80)+L80)/6 -> 6.1666667 | N80: =SUM($S$93:$S$96)*M80 -> 623.75833 | R80: 3 | S80: =ROUND((M80*R80),1) -> 18.5 | T80: =U80/S80 -> 1.027027 | U80: =SUM(W80:AO80) -> 19 | AI80: 19
C81: Aprovação dos Orientadores. | D81: Apresentar os resultados finais para os professores orientadores. | E81: Para ter uma opinião forte e para que possamos arrumar o necessario. | F81: Laboratorio A13/A18 | G81: Todos os integrantes | H81: conversando com o professor e mostrando nosso trabalho | I81: 44523 | J81: 4 | K81: 6 | L81: 8 | M81: =(J81+(4*K81)+L81)/6 -> 6 | N81: =SUM($S$93:$S$96)*M81 -> 606.9 | R81: 3 | S81: =ROUND((M81*R81),1) -> 18 | T81: =U81/S81 -> 1 | U81: =SUM(W81:AO81) -> 18 | AK81: 18
C82: Gerar um melhoramento naquilo que já foi executado. | D82: Após a válidação e revisão, se necessário, efetuar as modificações necessárias. | E82: Para se ter um melhor projeto dentro das expectavivas. | F82: Laboratorio A13/A19 | G82: Todos os integrantes | H82: aplicando as dicas que o professor nos passou | I82: 44524 | J82: 4 | K82: 6 | L82: 8 | M82: =(J82+(4*K82)+L82)/6 -> 6 | N82: =SUM($S$93:$S$96)*M82 -> 606.9 | R82: 3 | S82: =ROUND((M82*R82),1) -> 18 | T82: =U82/S82 -> 1 | U82: =SUM(W82:AO82) -> 18 | AK82: 18
C83: Executar entrega. | D83: Após todas as revisões, validações e modificações, efetuar a entrega do projeto. | E83: Para finalizar o projeto. | F83: Laboratorio A13/A20 | G83: Leandro Costa | H83: organizando todos os arquivos e enviando pelo teams | I83: 44525 | J83: 4 | K83: 6 | L83: 8 | M83: =(J83+(4*K83)+L83)/6 -> 6 | N83: =$S$95*M83 -> 112.2 | R83: 3 | S83: =ROUND((M83*R83),1) -> 18 | T83: =U83/S83 -> 1 | U83: =SUM(W83:AO83) -> 18 | AK83: 10 | AL83: 8
B84: Seminario | C84: Fácil entendimento e que sirva de base para apresentação final. | D84: Elaborar slides para auxiliar os integrantes da equipe, contendo imagens, videos, gráficos e tabelas. | E84: Para apresentar nosso projeto a banca da melhor forma. | F84: Laboratorio A13/A20 | G84: Nilton Guerra | H84: fazendo um resumo do nosso projeto atraves de imagens e videos etc. | I84: 44477 | J84: 8 | K84: 10 | L84: 16 | M84: =(J84+(4*K84)+L84)/6 -> 10.666667 | N84: =$S$95*M84 -> 199.46667 | R84: 3 | S84: =ROUND((M84*R84),1) -> 32 | T84: =U84/S84 -> 1 | U84: =SUM(W84:AO84) -> 32 | AE84: 32
C85: Demonstrar segurança para apresentação. | D85: Ensaiar a apresentação para preparar todos os integrantes do grupo para a apresentação final. | E85: Para apresentar nosso projeto a banca da melhor forma. | F85: Auditorio | G85: Todos os integrantes | H85: em cima dos slides ensaiar tudo oque iremos apresentar no dia | I85: 44523 | J85: 10 | K85: 11 | L85: 12 | M85: 15 | N85: =SUM($S$93:$S$96)*M85 -> 1517.25 | R85: 3 | S85: =ROUND((M85*R85),1) -> 45 | T85: =U85/S85 -> 1 | U85: =SUM(W85:AO85) -> 45 | AL85: 45
C86: Mostrar que a equipe está preparada para apresentação. | D86: Revisar tudo que foi feito, analisar e corrigir erros ocorridos no ensaio, acertar os ultimos detalhes. | E86: Mostrar que a equipe esta preparada para apresentação. | F86: Auditorio | G86: Todos os integrantes | H86: fazer a revisão e repassar tudo oque iremos apresentar | I86: 44524 | J86: 8 | K86: 10 | L86: 12 | M86: =(J86+(4*K86)+L86)/6 -> 10 | N86: =SUM($S$93:$S$96)*M86 -> 1011.5 | R86: 3 | S86: =ROUND((M86*R86),1) -> 30 | T86: =U86/S86 -> 1 | U86: =SUM(W86:AO86) -> 30 | AL86: 30
C87: Apresentar para o Orientador e empresa parceira. | D87: Apresentação final e conclusão do TCC. | E87: fazer a apresntação para os orientadores e banca. | F87: Auditorio | G87: Todos os integrantes | H87: Apresentar o projeto | I87: 44531 | J87: 1 | K87: 2 | L87: 3 | M87: =(J87+(4*K87)+L87)/6 -> 2 | N87: =SUM($S$93:$S$96)*M87 -> 202.3 | R87: 3 | S87: =ROUND((M87*R87),1) -> 6 | T87: =U87/S87 -> 5.5 | U87: =SUM(W87:AO87) -> 33 | AM87: 33
N88: =SUM(N16:N87) -> 17925.5 | R88: TOTAL | S88: =SUM(S16:S87) -> 809.8 | V88: RESTANTE | W88: =S88-SUM(W16:W87) -> 767.8 | X88: =W88-SUM(X16:X87) -> 752.8 | Y88: =X88-SUM(Y16:Y87) -> 721.8 | Z88: =Y88-SUM(Z16:Z87) -> 690.8 | AA88: =Z88-SUM(AA16:AA87) -> 622.8 | AB88: =AA88-SUM(AB16:AB87) -> 529.8 | AC88: =AB88-SUM(AC16:AC87) -> 492.8 | AD88: =AC88-SUM(AD16:AD87) -> 436.8 | AE88: =AD88-SUM(AE16:AE87) -> 374.8 | ... AM88: =AL88-SUM(AM16:AM87) -> -6.2
S89: =S88/17 -> 47.635294 | T89: =ROUND(S89,0) -> 48 | V89: ESTIMADO | W89: =S88-T89 -> 761.8 | X89: =W89-$T89 -> 713.8 | Y89: =X89-$T89 -> 665.8 | Z89: =Y89-$T89 -> 617.8 | AA89: =Z89-$T89 -> 569.8 | AB89: =AA89-$T89 -> 521.8 | AC89: =AB89-$T89 -> 473.8 | AD89: =AC89-$T89 -> 425.8 | AE89: =AD89-$T89 -> 377.8 | ... AM89: =AL89-$T89 -> -6.2
A91: cargo | B91: salário | C91: Descontos | R91: Sálario final | S91: Salário por hora do funcionário
C92: INSS | F92: Periculosidade | H92: IRRF | J92: FGTS | L92: Convênio | N92: vale transporte | P92: contribuição sindical | S92: (20 horas semanais/100 horas mensais)
A93: Gerente | B93: 5000 | C93: 0.14 | D93: =B93*0.09 -> 450 | E93: =B93-D93 -> 4550 | F93: NA | G93: 0 | H93: 27,5% e parcela de R$ 869,36 a deduzir do imposto | I93: =(E93*0.275)-869.36 -> 381.89 | J93: 0.08 | K93: =B93*0.08 -> 400 | L93: 0.015 | M93: =B93*0.015 -> 75 | N93: 0.06 | O93: =B93*0.06 -> 300 | P93: 0 | Q93: 0 | R93: =B93-D93-I93-K93-M93-O93-Q93 -> 3393.11 | S93: =B93/100 -> 50
A94: Supervisor | B94: 2200 | C94: 0.09 | D94: =B94*0.09 -> 198 | E94: =B94-D94 -> 2002 | F94: 0.3 | G94: =B94*0.3 -> 660 | H94: 22,5% e parcela de R$ 636,13 a deduzir do imposto | I94: =(E94*0.075)-142.8 -> 7.35 | J94: 0.08 | K94: =B94*0.08 -> 176 | L94: 0.015 | M94: =B94*0.015 -> 33 | N94: 0.06 | O94: =B94*0.06 -> 132 | P94: 0 | Q94: 0 | R94: =B94-D94-I94-K94-M94-O94-Q94 -> 1653.65 | S94: =B94/100 -> 22
A95: Técnico | B95: 1870 | C95: 0.09 | D95: =B95*0.09 -> 168.3 | E95: =B95-D95 -> 1701.7 | F95: 0.3 | G95: =B95*0.3 -> 561 | H95: Isento | I95: NA | J95: 0.08 | K95: =B95*0.08 -> 149.6 | L95: 0.015 | M95: =B95*0.015 -> 28.05 | N95: 0.06 | O95: =B95*0.06 -> 112.2 | P95: 0.02 | Q95: =B95*0.02 -> 37.4 | R95: =B95-D95-K95-M95-O95-Q95 -> 1374.45 | S95: =B95/100 -> 18.7
A96: Auxiliar | B96: 1045 | C96: 0.075 | D96: =B96*0.09 -> 94.05 | E96: =B96-D96 -> 950.95 | F96: 0.3 | G96: =B96*0.3 -> 313.5 | H96: Isento | I96: NA | J96: 0.08 | K96: =B96*0.08 -> 83.6 | L96: 0.015 | M96: =B96*0.015 -> 15.675 | N96: 0.06 | O96: =B96*0.06 -> 62.7 | P96: 0.02 | Q96: =B96*0.02 -> 20.9 | R96: =B96-D96-K96-M96-O96-Q96 -> 768.075 | S96: =B96/100 -> 10.45

Sheet Checklist
B2: PROJETO AUTOMOÇÃO PREDIAL | C2: Lista de Conteudos e Apresentações | K2: A Fazer | L2: =COUNTIF(A4:A77,"FALSO") -> 0 | M2: =L2/COUNTA(F4:F77) -> 0
C3: Tema | E3: Data | F3: Estado | H3: Revisão | I3: Notas | K3: Feito | L3: =COUNTIF(A4:A77,TRUE) -> 20 | M3: =L3/COUNTA(A4:A22) -> 1.0526316
A4: TRUE | D4: ='Dicionario EAP2'!C16 -> Especificar o objetivo central do projeto. | E4: ='Dicionario EAP2'!I16 -> 44421 | F4: =IF(A4=FALSE,"A Fazer","Feito") -> Feito | H4: =IF(J4=FALSE,"Pendente","Revisado") -> Pendente | J4: FALSE
A5: TRUE | D5: ='Dicionario EAP2'!C17 -> Direcionar os integrantes a seus objetivos. | E5: ='Dicionario EAP2'!I17 -> 44425 | F5: =IF(A5=FALSE,"A Fazer","Feito") -> Feito | H5: =IF(J5=FALSE,"Pendente","Revisado") -> Revisado | J5: TRUE
A6: TRUE | D6: ='Dicionario EAP2'!C18 -> Facilitar o reconhecimento das limitações e acrecismos dos integrantes do Projeto. | E6: ='Dicionario EAP2'!I18 -> 44421 | F6: =IF(A6=FALSE,"A Fazer","Feito") -> Feito | H6: =IF(J6=FALSE,"Pendente","Revisado") -> Pendente | J6: FALSE
A7: TRUE | D7: ='Dicionario EAP2'!C19 -> Atribuição de reponsabilidades de integrantes especificos em determinadas temas. | E7: ='Dicionario EAP2'!I19 -> 44427 | F7: =IF(A7=FALSE,"A Fazer","Feito") -> Feito | H7: =IF(J7=FALSE,"Pendente","Revisado") -> Pendente | J7: FALSE
A8: TRUE | D8: ='Dicionario EAP2'!C20 -> Gerar um aprimoramento no que já foi realizado. | E8: ='Dicionario EAP2'!I20 -> 44432 | F8: =IF(A8=FALSE,"A Fazer","Feito") -> Feito | H8: =IF(J8=FALSE,"Pendente","Revisado") -> Pendente | J8: FALSE
A9: TRUE | D9: ='Dicionario EAP2'!C21 -> Cumprir com os criterios passados em sala de aula e do PMBOK. | E9: ='Dicionario EAP2'!I21 -> 44434 | F9: =IF(A9=FALSE,"A Fazer","Feito") -> Feito | H9: =IF(J9=FALSE,"Pendente","Revisado") -> Pendente | J9: FALSE
A10: TRUE | D10: ='Dicionario EAP2'!C22 -> Definir e separar as principais renponsabilidades em etapas. | E10: ='Dicionario EAP2'!I22 -> 44432 | F10: =IF(A10=FALSE,"A Fazer","Feito") -> Feito | H10: =IF(J10=FALSE,"Pendente","Revisado") -> Pendente | J10: FALSE
A11: TRUE | D11: ='Dicionario EAP2'!C23 -> Desmembrar as etapas em tarefas. | E11: ='Dicionario EAP2'!I23 -> 44432 | F11: =IF(A11=FALSE,"A Fazer","Feito") -> Feito | H11: =IF(J11=FALSE,"Pendente","Revisado") -> Pendente | J11: FALSE
A12: TRUE | D12: ='Dicionario EAP2'!C24 -> Direcionar de maneira mais profundada a todos os processos do projeto. | E12: ='Dicionario EAP2'!I24 -> 44434 | F12: =IF(A12=FALSE,"A Fazer","Feito") -> Feito | H12: =IF(J12=FALSE,"Pendente","Revisado") -> Pendente | J12: FALSE
A13: TRUE | D13: ='Dicionario EAP2'!C25 -> Gerar um aprimoramento naquilo que já foi executado. | E13: ='Dicionario EAP2'!I25 -> 44439 | F13: =IF(A13=FALSE,"A Fazer","Feito") -> Feito | H13: =IF(J13=FALSE,"Pendente","Revisado") -> Pendente | J13: FALSE
A14: TRUE | D14: ='Dicionario EAP2'!C26 -> Cumprir com os criterios passados em sala de aula e do PMBOK. | E14: ='Dicionario EAP2'!I26 -> 44439 | F14: =IF(A14=FALSE,"A Fazer","Feito") -> Feito | H14: =IF(J14=FALSE,"Pendente","Revisado") -> Pendente | J14: FALSE
A15: TRUE | D15: ='Dicionario EAP2'!C27 -> Finalidade do Projeto, a meta final. | E15: ='Dicionario EAP2'!I27 -> 44441 | F15: =IF(A15=FALSE,"A Fazer","Feito") -> Feito | H15: =IF(J15=FALSE,"Pendente","Revisado") -> Pendente | J15: FALSE | K15: Pendente | L15: =COUNTIF(J4:J22,"FALSO") -> 17 | M15: =L15/COUNTA(H4:H22) -> 0.89473684
A16: TRUE | D16: ='Dicionario EAP2'!C28 -> Levar um tempo de trabalho necessario e esperado. | E16: ='Dicionario EAP2'!I28 -> 44447 | F16: =IF(A16=FALSE,"A Fazer","Feito") -> Feito | H16: =IF(J16=FALSE,"Pendente","Revisado") -> Pendente | J16: FALSE | K16: Revisado | L16: =COUNTIF(J4:J22,TRUE) -> 2 | M16: =L16/COUNTA(H4:H22) -> 0.10526316
A17: TRUE | D17: ='Dicionario EAP2'!C29 -> Levar uma elaboração antecipada. | E17: ='Dicionario EAP2'!I29 -> 44448 | F17: =IF(A17=FALSE,"A Fazer","Feito") -> Feito | H17: =IF(J17=FALSE,"Pendente","Revisado") -> Pendente | J17: FALSE
A18: TRUE | D18: ='Dicionario EAP2'!C30 -> Gerar um aprimoramento naquilo que já foi executado. | E18: ='Dicionario EAP2'!I30 -> 44449 | F18: =IF(A18=FALSE,"A Fazer","Feito") -> Feito | H18: =IF(J18=FALSE,"Pendente","Revisado") -> Pendente | J18: FALSE
A19: TRUE | D19: ='Dicionario EAP2'!C31 -> Cumprir com os criterios passados em aula e do PMBOK. | E19: ='Dicionario EAP2'!I31 -> 44449 | F19: =IF(A19=FALSE,"A Fazer","Feito") -> Feito | H19: =IF(J19=FALSE,"Pendente","Revisado") -> Pendente | J19: FALSE
A20: TRUE | D20: ='Dicionario EAP2'!C32 -> Levantar os possiveis riscos. | E20: ='Dicionario EAP2'!I32 -> 44453 | F20: =IF(A20=FALSE,"A Fazer","Feito") -> Feito | H20: =IF(J20=FALSE,"Pendente","Revisado") -> Pendente | J20: FALSE
A21: TRUE | D21: ='Dicionario EAP2'!C33 -> Preparar-se sob a probabilidade dos riscos. | E21: ='Dicionario EAP2'!I33 -> 44455 | F21: =IF(A21=FALSE,"A Fazer","Feito") -> Feito | H21: =IF(J21=FALSE,"Pendente","Revisado") -> Pendente | J21: FALSE
A22: TRUE | D22: ='Dicionario EAP2'!C34 -> Gerar possiveis consequências. | E22: ='Dicionario EAP2'!I34 -> 44455 | F22: =IF(A22=FALSE,"A Fazer","Feito") -> Feito | H22: =IF(J22=FALSE,"Pendente","Revisado") -> Revisado | J22: TRUE
A23: TRUE | D23: ='Dicionario EAP2'!C35 -> Comparar o tempo de trabalho com a meta. | E23: ='Dicionario EAP2'!I35 -> 44455 | F23: =IF(A23=FALSE,"A Fazer","Feito") -> Feito | H23: =IF(J23=FALSE,"Pendente","Revisado") -> Revisado | J23: TRUE
D24: ='Dicionario EAP2'!C36 -> Permitir que todos os quadros de energia possam ser instalados dentro do quadro de distribuição | E24: ='Dicionario EAP2'!I36 -> 44459 | F24: =IF(A24=FALSE,"A Fazer","Feito") -> A Fazer | H24: =IF(J24=FALSE,"Pendente","Revisado") -> Revisado | J24: TRUE
D25: ='Dicionario EAP2'!C37 -> Proteção de todos os circuitos da residência, seguindo a norma NR10. | E25: ='Dicionario EAP2'!I37 -> 44459 | F25: =IF(A25=FALSE,"A Fazer","Feito") -> A Fazer | H25: =IF(J25=FALSE,"Pendente","Revisado") -> Pendente | J25: FALSE
D26: ='Dicionario EAP2'!C38 -> Fazer a alimentação das câmeras e do DRV com condutores isolados e sem imendas nos eletrodutos. | E26: ='Dicionario EAP2'!I38 -> 44461 | F26: =IF(A26=FALSE,"A Fazer","Feito") -> A Fazer | H26: =IF(J26=FALSE,"Pendente","Revisado") -> Revisado | J26: TRUE
D27: ='Dicionario EAP2'!C39 -> Fixar as câmeras e fazer a alimentação e a transmição de dados com facilidade. | E27: ='Dicionario EAP2'!I39 -> 44462 | F27: =IF(A27=FALSE,"A Fazer","Feito") -> A Fazer | H27: =IF(J27=FALSE,"Pendente","Revisado") -> Revisado | J27: TRUE
D28: ='Dicionario EAP2'!C40 -> Permitir a comunicação do monitor com o DRV | E28: ='Dicionario EAP2'!I40 -> 44462 | F28: =IF(A28=FALSE,"A Fazer","Feito") -> A Fazer | H28: =IF(J28=FALSE,"Pendente","Revisado") -> Revisado | J28: TRUE
D29: ='Dicionario EAP2'!C41 -> Permitir a visualização dos pontos de vigilância no monitor | E29: ='Dicionario EAP2'!I41 -> 44462 | F29: =IF(A29=FALSE,"A Fazer","Feito") -> A Fazer | H29: =IF(J29=FALSE,"Pendente","Revisado") -> Revisado | J29: TRUE
D30: ='Dicionario EAP2'!C42 -> Que os cabos passados sejam alimentados e devidamente isolados sem imentas nos eletrodutos. | E30: ='Dicionario EAP2'!I42 -> 44463 | F30: =IF(A30=FALSE,"A Fazer","Feito") -> A Fazer | H30: =IF(J30=FALSE,"Pendente","Revisado") -> Revisado | J30: TRUE
D31: ='Dicionario EAP2'!C43 -> Ligar todas as conexões dos sensores corretamente. | E31: ='Dicionario EAP2'!I43 -> 44463 | F31: =IF(A31=FALSE,"A Fazer","Feito") -> A Fazer | H31: =IF(J31=FALSE,"Pendente","Revisado") -> Revisado | J31: TRUE
D32: ='Dicionario EAP2'!C44 -> Fazer a comunicação entre central de alarme de incêndio e sensores de fumaça. | E32: ='Dicionario EAP2'!I44 -> 44466 | F32: =IF(A32=FALSE,"A Fazer","Feito") -> A Fazer | H32: =IF(J32=FALSE,"Pendente","Revisado") -> Revisado | J32: TRUE
D33: ='Dicionario EAP2'!C45 -> Que os cabos passados sejam alimentados e devidamente isolados sem emendas nos eletrodutos. | E33: ='Dicionario EAP2'!I45 -> 44474 | F33: =IF(A33=FALSE,"A Fazer","Feito") -> A Fazer | H33: =IF(J33=FALSE,"Pendente","Revisado") -> Revisado | J33: TRUE
D34: ='Dicionario EAP2'!C46 -> Fazer a instalação dos interruptores e lâmpadas | E34: ='Dicionario EAP2'!I46 -> 44476 | F34: =IF(A34=FALSE,"A Fazer","Feito") -> A Fazer | H34: =IF(J34=FALSE,"Pendente","Revisado") -> Revisado | J34: TRUE
D35: ='Dicionario EAP2'!C47 -> fazer a integração dos sistema de iluminação com os aplicativos (bluelux,sonoff). | E35: ='Dicionario EAP2'!I47 -> 44477 | F35: =IF(A35=FALSE,"A Fazer","Feito") -> A Fazer | H35: =IF(J35=FALSE,"Pendente","Revisado") -> Revisado | J35: TRUE
... D39: ='Dicionario EAP2'!C51 -> Verificar se o monitor de energia está funcionando corretamente. | E39: ='Dicionario EAP2'!I51 -> 44493 | F39: =IF(A39=FALSE,"A Fazer","Feito") -> A Fazer | H39: =IF(J39=FALSE,"Pendente","Revisado") -> Revisado | J39: TRUE
D40: ='Dicionario EAP2'!C52 -> Controlar alexa pelo app. | E40: ='Dicionario EAP2'!I53 -> 44497 | F40: =IF(A40=FALSE,"A Fazer","Feito") -> A Fazer | H40: =IF(J40=FALSE,"Pendente","Revisado") -> Revisado | J40: TRUE
D41: ='Dicionario EAP2'!C53 -> Alexa Responder aos comandos corretamente. | E41: ='Dicionario EAP2'!#REF! -> #REF! | F41: =IF(A41=FALSE,"A Fazer","Feito") -> A Fazer | H41: =IF(J41=FALSE,"Pendente","Revisado") -> Revisado | J41: TRUE
D42: ='Dicionario EAP2'!C54 -> Alexa controlar outros dispositivos. | E42: ='Dicionario EAP2'!I54 -> 44504 | F42: =IF(A42=FALSE,"A Fazer","Feito") -> A Fazer | H42: =IF(J42=FALSE,"Pendente","Revisado") -> Revisado | J42: TRUE
D43: ='Dicionario EAP2'!C55 -> Interfone estar fixado. | E43: ='Dicionario EAP2'!I55 -> 44469 | F43: =IF(A43=FALSE,"A Fazer","Feito") -> A Fazer | H43: =IF(J43=FALSE,"Pendente","Revisado") -> Revisado | J43: TRUE
D44: ='Dicionario EAP2'!C56 -> Verificar o funcionando do interfone | E44: ='Dicionario EAP2'!I56 -> 44470 | F44: =IF(A44=FALSE,"A Fazer","Feito") -> A Fazer | H44: =IF(J44=FALSE,"Pendente","Revisado") -> Revisado | J44: TRUE
D45: ='Dicionario EAP2'!C57 -> Interfone funcionar junto ao sistema de segurança | E45: ='Dicionario EAP2'!I57 -> 44470 | F45: =IF(A45=FALSE,"A Fazer","Feito") -> A Fazer | H45: =IF(J45=FALSE,"Pendente","Revisado") -> Revisado | J45: TRUE
D46: ='Dicionario EAP2'!C58 -> Instalação das travas automaticas. | E46: ='Dicionario EAP2'!I58 -> 44470 | F46: =IF(A46=FALSE,"A Fazer","Feito") -> A Fazer | H46: =IF(J46=FALSE,"Pendente","Revisado") -> Pendente
D47: ='Dicionario EAP2'!C59 -> Verificar o funcionamento da trava. | E47: ='Dicionario EAP2'!I59 -> 44470 | F47: =IF(A47=FALSE,"A Fazer","Feito") -> A Fazer | H47: =IF(J47=FALSE,"Pendente","Revisado") -> Pendente
D48: ='Dicionario EAP2'!C60 -> Integrar com sistema de segurança | E48: ='Dicionario EAP2'!I60 -> 44470 | F48: =IF(A48=FALSE,"A Fazer","Feito") -> A Fazer | H48: =IF(J48=FALSE,"Pendente","Revisado") -> Pendente
D49: ='Dicionario EAP2'!C61 -> Acrescentar base ao projeto. | E49: ='Dicionario EAP2'!I61 -> 0 | F49: =IF(A49=FALSE,"A Fazer","Feito") -> A Fazer | H49: =IF(J49=FALSE,"Pendente","Revisado") -> Pendente
D50: ='Dicionario EAP2'!C62 -> Garantir material ao projeto. | E50: ='Dicionario EAP2'!I62 -> 0 | F50: =IF(A50=FALSE,"A Fazer","Feito") -> A Fazer | H50: =IF(J50=FALSE,"Pendente","Revisado") -> Pendente
D51: ='Dicionario EAP2'!C63 -> Ser um meio de realização do trabalho. | E51: ='Dicionario EAP2'!I63 -> 0 | F51: =IF(A51=FALSE,"A Fazer","Feito") -> A Fazer | H51: =IF(J51=FALSE,"Pendente","Revisado") -> Pendente
D52: ='Dicionario EAP2'!C64 -> Sistema base do projeto. | E52: ='Dicionario EAP2'!I64 -> 0 | F52: =IF(A52=FALSE,"A Fazer","Feito") -> A Fazer | H52: =IF(J52=FALSE,"Pendente","Revisado") -> Pendente
D53: ='Dicionario EAP2'!C65 -> Fazer a comunicação das câmeras com a central. | E53: ='Dicionario EAP2'!I65 -> 44462 | F53: =IF(A53=FALSE,"A Fazer","Feito") -> A Fazer | H53: =IF(J53=FALSE,"Pendente","Revisado") -> Pendente
D54: ='Dicionario EAP2'!C66 -> O acionamento da iluminaçao remotamente. | E54: ='Dicionario EAP2'!I66 -> 44474 | F54: =IF(A54=FALSE,"A Fazer","Feito") -> A Fazer | H54: =IF(J54=FALSE,"Pendente","Revisado") -> Pendente
D55: ='Dicionario EAP2'!C67 -> Comunicação da central com os sensores. | E55: ='Dicionario EAP2'!I67 -> 44466 | F55: =IF(A55=FALSE,"A Fazer","Feito") -> A Fazer | H55: =IF(J55=FALSE,"Pendente","Revisado") -> Pendente
D56: ='Dicionario EAP2'!C68 -> Monitoramento do consumo de energia. | E56: ='Dicionario EAP2'!I68 -> 44487 | F56: =IF(A56=FALSE,"A Fazer","Feito") -> A Fazer | H56: =IF(J56=FALSE,"Pendente","Revisado") -> Pendente
D57: ='Dicionario EAP2'!#REF! -> #REF! | E57: ='Dicionario EAP2'!#REF! -> #REF! | F57: =IF(A57=FALSE,"A Fazer","Feito") -> A Fazer | H57: =IF(J57=FALSE,"Pendente","Revisado") -> Pendente
D58: ='Dicionario EAP2'!C69 -> Fazer a comunicação via WI-FI. | E58: ='Dicionario EAP2'!I69 -> 44487 | F58: =IF(A58=FALSE,"A Fazer","Feito") -> A Fazer | H58: =IF(J58=FALSE,"Pendente","Revisado") -> Pendente
D59: ='Dicionario EAP2'!C70 -> Comunicação entre os dispositivos. | E59: ='Dicionario EAP2'!I70 -> 44498 | F59: =IF(A59=FALSE,"A Fazer","Feito") -> A Fazer | H59: =IF(J59=FALSE,"Pendente","Revisado") -> Pendente
D60: ='Dicionario EAP2'!C71 -> Analisar se as atividades realizadas satisfaz as expectativas da equipe. | E60: ='Dicionario EAP2'!I71 -> 44501 | F60: =IF(A60=FALSE,"A Fazer","Feito") -> A Fazer | H60: =IF(J60=FALSE,"Pendente","Revisado") -> Pendente
D61: ='Dicionario EAP2'!C72 -> Analizar se as atividades realizadas satisfaz as expectativas da equipe. | E61: ='Dicionario EAP2'!I72 -> 44501 | F61: =IF(A61=FALSE,"A Fazer","Feito") -> A Fazer | H61: =IF(J61=FALSE,"Pendente","Revisado") -> Pendente
D62: ='Dicionario EAP2'!C73 -> Analizar se as atividades realizadas satisfaz as expectativas da equipe. | E62: ='Dicionario EAP2'!I73 -> 44501 | F62: =IF(A62=FALSE,"A Fazer","Feito") -> A Fazer | H62: =IF(J62=FALSE,"Pendente","Revisado") -> Pendente
D63: ='Dicionario EAP2'!C74 -> Analizar se as atividades realizadas satisfaz as expectativas da equipe. | E63: ='Dicionario EAP2'!I74 -> 44501 | F63: =IF(A63=FALSE,"A Fazer","Feito") -> A Fazer | H63: =IF(J63=FALSE,"Pendente","Revisado") -> Pendente
D64: ='Dicionario EAP2'!#REF! -> #REF! | E64: ='Dicionario EAP2'!#REF! -> #REF! | F64: =IF(A64=FALSE,"A Fazer","Feito") -> A Fazer | H64: =IF(J64=FALSE,"Pendente","Revisado") -> Pendente
D65: ='Dicionario EAP2'!C75 -> Analizar se as atividades realizadas satisfaz as expectativas da equipe. | E65: ='Dicionario EAP2'!I75 -> 44501 | F65: =IF(A65=FALSE,"A Fazer","Feito") -> A Fazer | H65: =IF(J65=FALSE,"Pendente","Revisado") -> Pendente
D66: ='Dicionario EAP2'!C76 -> Garantir que tudo esteja como planejado. | E66: ='Dicionario EAP2'!I76 -> 44516 | F66: =IF(A66=FALSE,"A Fazer","Feito") -> A Fazer | H66: =IF(J66=FALSE,"Pendente","Revisado") -> Pendente
D67: ='Dicionario EAP2'!C77 -> Garantir que tudo esteja nos conformes | E67: ='Dicionario EAP2'!I77 -> 44503 | F67: =IF(A67=FALSE,"A Fazer","Feito") -> A Fazer | H67: =IF(J67=FALSE,"Pendente","Revisado") -> Pendente
D68: ='Dicionario EAP2'!C78 -> Aceitação do cliente de acordo com que foi pedido. | E68: ='Dicionario EAP2'!I78 -> 44518 | F68: =IF(A68=FALSE,"A Fazer","Feito") -> A Fazer | H68: =IF(J68=FALSE,"Pendente","Revisado") -> Pendente
D69: ='Dicionario EAP2'!C79 -> Satisfação do cliente. | E69: ='Dicionario EAP2'!I79 -> 44518 | F69: =IF(A69=FALSE,"A Fazer","Feito") -> A Fazer | H69: =IF(J69=FALSE,"Pendente","Revisado") -> Pendente
D70: ='Dicionario EAP2'!C80 -> Garantir que tudo esteja como planejado. | E70: ='Dicionario EAP2'!I80 -> 44516 | F70: =IF(A70=FALSE,"A Fazer","Feito") -> A Fazer | H70: =IF(J70=FALSE,"Pendente","Revisado") -> Pendente
D71: ='Dicionario EAP2'!C81 -> Aprovação dos Orientadores. | E71: ='Dicionario EAP2'!I81 -> 44523 | F71: =IF(A71=FALSE,"A Fazer","Feito") -> A Fazer | H71: =IF(J71=FALSE,"Pendente","Revisado") -> Pendente
D72: ='Dicionario EAP2'!C82 -> Gerar um melhoramento naquilo que já foi executado. | E72: ='Dicionario EAP2'!I82 -> 44524 | F72: =IF(A72=FALSE,"A Fazer","Feito") -> A Fazer | H72: =IF(J72=FALSE,"Pendente","Revisado") -> Pendente
D73: ='Dicionario EAP2'!C83 -> Executar entrega. | E73: ='Dicionario EAP2'!I83 -> 44525 | F73: =IF(A73=FALSE,"A Fazer","Feito") -> A Fazer | H73: =IF(J73=FALSE,"Pendente","Revisado") -> Pendente
D74: ='Dicionario EAP2'!C84 -> Fácil entendimento e que sirva de base para apresentação final. | E74: ='Dicionario EAP2'!I84 -> 44477 | F74: =IF(A74=FALSE,"A Fazer","Feito") -> A Fazer | H74: =IF(J74=FALSE,"Pendente","Revisado") -> Pendente
D75: ='Dicionario EAP2'!C85 -> Demonstrar segurança para apresentação. | E75: ='Dicionario EAP2'!I85 -> 44523 | F75: =IF(A75=FALSE,"A Fazer","Feito") -> A Fazer | H75: =IF(J75=FALSE,"Pendente","Revisado") -> Pendente
D76: ='Dicionario EAP2'!C86 -> Mostrar que a equipe está preparada para apresentação. | E76: ='Dicionario EAP2'!I86 -> 44524 | F76: =IF(A76=FALSE,"A Fazer","Feito") -> A Fazer | H76: =IF(J76=FALSE,"Pendente","Revisado") -> Pendente
D77: ='Dicionario EAP2'!C87 -> Apresentar para o Orientador e empresa parceira. | E77: ='Dicionario EAP2'!I87 -> 44531 | F77: =IF(A77=FALSE,"A Fazer","Feito") -> A Fazer | H77: =IF(J77=FALSE,"Pendente","Revisado") -> Pendente

Sheet Grafico Gantt 
B1: Automação Predial | I1: Legenda:
I2: Baixo risco | N2: Médio risco | S2: Alto risco
B3: Leandro Costa Fereira | D3: Data de início do projeto: | F3: 44420 | H3: PESO: | I3: 1 | N3: 2 | S3: 3
D4: Incremento de rolagem: | F4: 44 | I4: =TEXT(I5,"mmmm") -> setembro
I5: =IFERROR(Início_do_projeto+Incremento_de_rolagem,TODAY()) -> 44464 | J5: =I5+1 -> 44465 | K5: =J5+1 -> 44466 | L5: =K5+1 -> 44467 | M5: =L5+1 -> 44468 | N5: =M5+1 -> 44469 | O5: =N5+1 -> 44470 | P5: =O5+1 -> 44471 | Q5: =P5+1 -> 44472 | ... BL5: =BK5+1 -> 44519
A6: A barra de rolagem está nas células I6 a BL6. O incremento para percorrer os dados está definido como duas páginas por vez e pode ser ajustado nas configurações da barra de controle. Para ir para a frente ou para trás na linha do tempo, insira um valor de 0 ou mais na célula F4. O valor 0 leva você ao início do gráfico.
A7: Etapas | B7: Descrição do marco | C7: Risco | D7: Atribuído a | E7: Progresso | F7: Início | G7: Nº de dias | I7: =LEFT(TEXT(I5,"ddd"),3) -> sáb | J7: =LEFT(TEXT(J5,"ddd"),3) -> dom | K7: =LEFT(TEXT(K5,"ddd"),3) -> seg | L7: =LEFT(TEXT(L5,"ddd"),3) -> ter | M7: =LEFT(TEXT(M5,"ddd"),3) -> qua | N7: =LEFT(TEXT(N5,"ddd"),3) -> qui | O7: =LEFT(TEXT(O5,"ddd"),3) -> sex | P7: =LEFT(TEXT(P5,"ddd"),3) -> sáb | ... BL7: =LEFT(TEXT(BL5,"ddd"),3) -> sex
A8: Não exclua esta planilha. Esta linha ficará oculta para preservar uma fórmula usada para realçar o dia atual no cronograma do projeto.
A9: Especificar o objetivo central do projeto. | B9: Formalizar o projeto e as obrigações de todos os integrantes. | C9: Alto risco | D9: ='Dicionario EAP2'!G16 -> equipe | E9: ='Dicionario EAP2'!T16 -> 1 | F9: ='Dicionario EAP2'!I16 -> 44421 | G9: 5 | I9: =IF(AND($C9="Objetivo",I$5>=$F9,I$5<=$F9+$G9-1),2,IF(AND($C9="Marco",I$5>=$F9,I$5<=$F9+$G9-1),1,"")) | J9: =IF(AND($C9="Objetivo",J$5>=$F9,J$5<=$F9+$G9-1),2,IF(AND($C9="Marco",J$5>=$F9,J$5<=$F9+$G9-1),1,"")) | K9: =IF(AND($C9="Objetivo",K$5>=$F9,K$5<=$F9+$G9-1),2,IF(AND($C9="Marco",K$5>=$F9,K$5<=$F9+$G9-1),1,"")) | L9: =IF(AND($C9="Objetivo",L$5>=$F9,L$5<=$F9+$G9-1),2,IF(AND($C9="Marco",L$5>=$F9,L$5<=$F9+$G9-1),1,"")) | M9: =IF(AND($C9="Objetivo",M$5>=$F9,M$5<=$F9+$G9-1),2,IF(AND($C9="Marco",M$5>=$F9,M$5<=$F9+$G9-1),1,"")) | N9: =IF(AND($C9="Objetivo",N$5>=$F9,N$5<=$F9+$G9-1),2,IF(AND($C9="Marco",N$5>=$F9,N$5<=$F9+$G9-1),1,"")) | O9: =IF(AND($C9="Objetivo",O$5>=$F9,O$5<=$F9+$G9-1),2,IF(AND($C9="Marco",O$5>=$F9,O$5<=$F9+$G9-1),1,"")) | P9: =IF(AND($C9="Objetivo",P$5>=$F9,P$5<=$F9+$G9-1),2,IF(AND($C9="Marco",P$5>=$F9,P$5<=$F9+$G9-1),1,"")) | ... BL9: =IF(AND($C9="Objetivo",BL$5>=$F9,BL$5<=$F9+$G9-1),2,IF(AND($C9="Marco",BL$5>=$F9,BL$5<=$F9+$G9-1),1,""))
A10: Direcionar os integrantes a seus objetivos. | B10: Estruturar as ideias do projeto. | C10: Médio risco | D10: ='Dicionario EAP2'!G17 -> Todos os integrantes do grupo | E10: ='Dicionario EAP2'!T17 -> 1 | F10: ='Dicionario EAP2'!I17 -> 44425 | G10: 4 | I10: =IF(AND($C10="Objetivo",I$5>=$F10,I$5<=$F10+$G10-1),2,IF(AND($C10="Marco",I$5>=$F10,I$5<=$F10+$G10-1),1,"")) | J10: =IF(AND($C10="Objetivo",J$5>=$F10,J$5<=$F10+$G10-1),2,IF(AND($C10="Marco",J$5>=$F10,J$5<=$F10+$G10-1),1,"")) | K10: =IF(AND($C10="Objetivo",K$5>=$F10,K$5<=$F10+$G10-1),2,IF(AND($C10="Marco",K$5>=$F10,K$5<=$F10+$G10-1),1,"")) | L10: =IF(AND($C10="Objetivo",L$5>=$F10,L$5<=$F10+$G10-1),2,IF(AND($C10="Marco",L$5>=$F10,L$5<=$F10+$G10-1),1,"")) | M10: =IF(AND($C10="Objetivo",M$5>=$F10,M$5<=$F10+$G10-1),2,IF(AND($C10="Marco",M$5>=$F10,M$5<=$F10+$G10-1),1,"")) | N10: =IF(AND($C10="Objetivo",N$5>=$F10,N$5<=$F10+$G10-1),2,IF(AND($C10="Marco",N$5>=$F10,N$5<=$F10+$G10-1),1,"")) | O10: =IF(AND($C10="Objetivo",O$5>=$F10,O$5<=$F10+$G10-1),2,IF(AND($C10="Marco",O$5>=$F10,O$5<=$F10+$G10-1),1,"")) | P10: =IF(AND($C10="Objetivo",P$5>=$F10,P$5<=$F10+$G10-1),2,IF(AND($C10="Marco",P$5>=$F10,P$5<=$F10+$G10-1),1,"")) | ... BL10: =IF(AND($C10="Objetivo",BL$5>=$F10,BL$5<=$F10+$G10-1),2,IF(AND($C10="Marco",BL$5>=$F10,BL$5<=$F10+$G10-1),1,""))
A11: Facilitar o reconhecimento das limitações e acrecismos dos integrantes do Projeto. | B11: verificar as forças e fraquezas de todos os integrantes do grupo. | C11: Médio risco | D11: ='Dicionario EAP2'!G18 -> Todos os integrantes do grupo | E11: ='Dicionario EAP2'!T18 -> 1 | F11: ='Dicionario EAP2'!I18 -> 44421 | G11: 5
A12: Atribuição de reponsabilidades de integrantes expecificos em determinadas temas. | B12: Atribuir responsabilidades a todos os integrantes do grupo. | C12: Médio risco | D12: ='Dicionario EAP2'!G19 -> Todos os integrantes do grupo | E12: ='Dicionario EAP2'!T19 -> 1 | F12: ='Dicionario EAP2'!I19 -> 44427 | G12: 1
A13: Gerar um aprimoramento no que já foi feito. | B13: Revisar o trabalho | C13: Baixo risco | D13: ='Dicionario EAP2'!G20 -> Todos os integrantes do grupo | E13: ='Dicionario EAP2'!T20 -> 1 | F13: ='Dicionario EAP2'!I20 -> 44432 | G13: 2 | I13: =IF(AND($C13="Objetivo",I$5>=$F13,I$5<=$F13+$G13-1),2,IF(AND($C13="Marco",I$5>=$F13,I$5<=$F13+$G13-1),1,"")) | J13: =IF(AND($C13="Objetivo",J$5>=$F13,J$5<=$F13+$G13-1),2,IF(AND($C13="Marco",J$5>=$F13,J$5<=$F13+$G13-1),1,"")) | K13: =IF(AND($C13="Objetivo",K$5>=$F13,K$5<=$F13+$G13-1),2,IF(AND($C13="Marco",K$5>=$F13,K$5<=$F13+$G13-1),1,"")) | L13: =IF(AND($C13="Objetivo",L$5>=$F13,L$5<=$F13+$G13-1),2,IF(AND($C13="Marco",L$5>=$F13,L$5<=$F13+$G13-1),1,"")) | M13: =IF(AND($C13="Objetivo",M$5>=$F13,M$5<=$F13+$G13-1),2,IF(AND($C13="Marco",M$5>=$F13,M$5<=$F13+$G13-1),1,"")) | N13: =IF(AND($C13="Objetivo",N$5>=$F13,N$5<=$F13+$G13-1),2,IF(AND($C13="Marco",N$5>=$F13,N$5<=$F13+$G13-1),1,"")) | O13: =IF(AND($C13="Objetivo",O$5>=$F13,O$5<=$F13+$G13-1),2,IF(AND($C13="Marco",O$5>=$F13,O$5<=$F13+$G13-1),1,"")) | P13: =IF(AND($C13="Objetivo",P$5>=$F13,P$5<=$F13+$G13-1),2,IF(AND($C13="Marco",P$5>=$F13,P$5<=$F13+$G13-1),1,"")) | ... BL13: =IF(AND($C13="Objetivo",BL$5>=$F13,BL$5<=$F13+$G13-1),2,IF(AND($C13="Marco",BL$5>=$F13,BL$5<=$F13+$G13-1),1,""))
A14: Cumprir com os criterios passados em sala de aula e do PMBOK. | B14: Validação | C14: Médio risco | D14: ='Dicionario EAP2'!G21 -> Todos os integrantes do grupo | E14: ='Dicionario EAP2'!T21 -> 1 | F14: ='Dicionario EAP2'!I21 -> 44434 | G14: 2 | I14: =IF(AND($C14="Objetivo",I$5>=$F14,I$5<=$F14+$G14-1),2,IF(AND($C14="Marco",I$5>=$F14,I$5<=$F14+$G14-1),1,"")) | J14: =IF(AND($C14="Objetivo",J$5>=$F14,J$5<=$F14+$G14-1),2,IF(AND($C14="Marco",J$5>=$F14,J$5<=$F14+$G14-1),1,"")) | K14: =IF(AND($C14="Objetivo",K$5>=$F14,K$5<=$F14+$G14-1),2,IF(AND($C14="Marco",K$5>=$F14,K$5<=$F14+$G14-1),1,"")) | L14: =IF(AND($C14="Objetivo",L$5>=$F14,L$5<=$F14+$G14-1),2,IF(AND($C14="Marco",L$5>=$F14,L$5<=$F14+$G14-1),1,"")) | M14: =IF(AND($C14="Objetivo",M$5>=$F14,M$5<=$F14+$G14-1),2,IF(AND($C14="Marco",M$5>=$F14,M$5<=$F14+$G14-1),1,"")) | N14: =IF(AND($C14="Objetivo",N$5>=$F14,N$5<=$F14+$G14-1),2,IF(AND($C14="Marco",N$5>=$F14,N$5<=$F14+$G14-1),1,"")) | O14: =IF(AND($C14="Objetivo",O$5>=$F14,O$5<=$F14+$G14-1),2,IF(AND($C14="Marco",O$5>=$F14,O$5<=$F14+$G14-1),1,"")) | P14: =IF(AND($C14="Objetivo",P$5>=$F14,P$5<=$F14+$G14-1),2,IF(AND($C14="Marco",P$5>=$F14,P$5<=$F14+$G14-1),1,"")) | ... BL14: =IF(AND($C14="Objetivo",BL$5>=$F14,BL$5<=$F14+$G14-1),2,IF(AND($C14="Marco",BL$5>=$F14,BL$5<=$F14+$G14-1),1,""))
A15: Definir e separar as principais renponsabilidades em etapas. | B15: Definir como e quando serão realizadas as atividas e etapas do projeto. | C15: Baixo risco | D15: ='Dicionario EAP2'!G22 -> Todos os integrantes do grupo | E15: ='Dicionario EAP2'!T22 -> 1 | F15: ='Dicionario EAP2'!I22 -> 44432 | G15: 11 | I15: =IF(AND($C15="Objetivo",I$5>=$F15,I$5<=$F15+$G15-1),2,IF(AND($C15="Marco",I$5>=$F15,I$5<=$F15+$G15-1),1,"")) | J15: =IF(AND($C15="Objetivo",J$5>=$F15,J$5<=$F15+$G15-1),2,IF(AND($C15="Marco",J$5>=$F15,J$5<=$F15+$G15-1),1,"")) | K15: =IF(AND($C15="Objetivo",K$5>=$F15,K$5<=$F15+$G15-1),2,IF(AND($C15="Marco",K$5>=$F15,K$5<=$F15+$G15-1),1,"")) | L15: =IF(AND($C15="Objetivo",L$5>=$F15,L$5<=$F15+$G15-1),2,IF(AND($C15="Marco",L$5>=$F15,L$5<=$F15+$G15-1),1,"")) | M15: =IF(AND($C15="Objetivo",M$5>=$F15,M$5<=$F15+$G15-1),2,IF(AND($C15="Marco",M$5>=$F15,M$5<=$F15+$G15-1),1,"")) | N15: =IF(AND($C15="Objetivo",N$5>=$F15,N$5<=$F15+$G15-1),2,IF(AND($C15="Marco",N$5>=$F15,N$5<=$F15+$G15-1),1,"")) | O15: =IF(AND($C15="Objetivo",O$5>=$F15,O$5<=$F15+$G15-1),2,IF(AND($C15="Marco",O$5>=$F15,O$5<=$F15+$G15-1),1,"")) | P15: =IF(AND($C15="Objetivo",P$5>=$F15,P$5<=$F15+$G15-1),2,IF(AND($C15="Marco",P$5>=$F15,P$5<=$F15+$G15-1),1,"")) | ... BL15: =IF(AND($C15="Objetivo",BL$5>=$F15,BL$5<=$F15+$G15-1),2,IF(AND($C15="Marco",BL$5>=$F15,BL$5<=$F15+$G15-1),1,""))
A16: Desmembrar as etapas em tarefas. | B16: Definir como e quando serão realizadas as atividas e etapas do projeto. | C16: Baixo risco | D16: ='Dicionario EAP2'!G23 -> Todos os integrantes do grupo | E16: ='Dicionario EAP2'!T23 -> 1 | F16: ='Dicionario EAP2'!I23 -> 44432 | G16: 13
A17: Direcionar de maneira mais profundada a todos os processos do projeto. | B17: Descrever as tarefas a serem executadas pelos integrantes baseado na análise SWOT e RACI | C17: Baixo risco | D17: ='Dicionario EAP2'!G24 -> Todos os integrantes do grupo | E17: ='Dicionario EAP2'!T24 -> 1 | F17: ='Dicionario EAP2'!I24 -> 44434 | G17: 9
A18: Gerar um aprimoramento naquilo que já foi executado. | B18: Revisar o que se foi feito. | C18: Baixo risco | D18: ='Dicionario EAP2'!G25 -> Todos os integrantes do grupo | E18: ='Dicionario EAP2'!T25 -> 1 | F18: ='Dicionario EAP2'!I25 -> 44439 | G18: 11
A19: Cumprir com os criterios passados em sala de aula e do PMBOK. | B19: validar o trabalho que foi feito nessa etapa | C19: Alto risco | D19: ='Dicionario EAP2'!G26 -> Todos os integrantes do grupo | E19: ='Dicionario EAP2'!T26 -> 1 | F19: ='Dicionario EAP2'!I26 -> 44439 | G19: 12
A20: Finalidade do Projeto, a meta final. | B20: Análisar o escopo | C20: Alto risco | D20: ='Dicionario EAP2'!G27 -> Leandro Costa Petrick Gomes | E20: ='Dicionario EAP2'!T27 -> 1 | F20: ='Dicionario EAP2'!I27 -> 44441 | G20: 2 | I20: =IF(AND($C20="Objetivo",I$5>=$F20,I$5<=$F20+$G20-1),2,IF(AND($C20="Marco",I$5>=$F20,I$5<=$F20+$G20-1),1,"")) | J20: =IF(AND($C20="Objetivo",J$5>=$F20,J$5<=$F20+$G20-1),2,IF(AND($C20="Marco",J$5>=$F20,J$5<=$F20+$G20-1),1,"")) | K20: =IF(AND($C20="Objetivo",K$5>=$F20,K$5<=$F20+$G20-1),2,IF(AND($C20="Marco",K$5>=$F20,K$5<=$F20+$G20-1),1,"")) | L20: =IF(AND($C20="Objetivo",L$5>=$F20,L$5<=$F20+$G20-1),2,IF(AND($C20="Marco",L$5>=$F20,L$5<=$F20+$G20-1),1,"")) | M20: =IF(AND($C20="Objetivo",M$5>=$F20,M$5<=$F20+$G20-1),2,IF(AND($C20="Marco",M$5>=$F20,M$5<=$F20+$G20-1),1,"")) | N20: =IF(AND($C20="Objetivo",N$5>=$F20,N$5<=$F20+$G20-1),2,IF(AND($C20="Marco",N$5>=$F20,N$5<=$F20+$G20-1),1,"")) | O20: =IF(AND($C20="Objetivo",O$5>=$F20,O$5<=$F20+$G20-1),2,IF(AND($C20="Marco",O$5>=$F20,O$5<=$F20+$G20-1),1,"")) | P20: =IF(AND($C20="Objetivo",P$5>=$F20,P$5<=$F20+$G20-1),2,IF(AND($C20="Marco",P$5>=$F20,P$5<=$F20+$G20-1),1,"")) | ... BL20: =IF(AND($C20="Objetivo",BL$5>=$F20,BL$5<=$F20+$G20-1),2,IF(AND($C20="Marco",BL$5>=$F20,BL$5<=$F20+$G20-1),1,""))
A21: Levar um tempo de trabalho necessario e esperado. | B21: Definir o tempo para realizar cada etapa | C21: Alto risco | D21: ='Dicionario EAP2'!G28 -> Leandro Costa Petrick Gomes | E21: ='Dicionario EAP2'!T28 -> 1 | F21: ='Dicionario EAP2'!I28 -> 44447 | G21: 9
A22: Levar uma elaboração antecipada. | B22: Definir datas para a entrega de cada parte do trabalho | C22: Alto risco | D22: ='Dicionario EAP2'!G29 -> Leandro Costa Petrick Gomes | E22: ='Dicionario EAP2'!T29 -> 1 | F22: ='Dicionario EAP2'!I29 -> 44448 | G22: 8
A23: Gerar um aprimoramento naquilo que já foi executado. | B23: Revisar o que se foi feito. | C23: Médio risco | D23: ='Dicionario EAP2'!G30 -> Leandro Costa Petrick Gomes | E23: ='Dicionario EAP2'!T30 -> 1 | F23: ='Dicionario EAP2'!I30 -> 44449 | G23: 7
A24: Cumprir com os criterios passados em aula e do PMBOK. | B24: validar o que se foi feito | C24: Alto risco | D24: ='Dicionario EAP2'!G31 -> Leandro Costa Petrick Gomes | E24: ='Dicionario EAP2'!T31 -> 1 | F24: ='Dicionario EAP2'!I31 -> 44449 | G24: 7
A25: Levantar os possiveis riscos. | B25: Avaliar os possíveis riscos do projeto | C25: Médio risco | D25: ='Dicionario EAP2'!G32 -> Cosme Sousa Damião Sousa | E25: ='Dicionario EAP2'!T32 -> 1 | F25: ='Dicionario EAP2'!I32 -> 44453 | G25: 3
A26: Preparar-se sob a probabilidade dos riscos. | B26: Avaliar a probabilidade dos riscos acontecerem. | C26: Médio risco | D26: ='Dicionario EAP2'!G33 -> Cosme Sousa Damião Sousa | E26: ='Dicionario EAP2'!T33 -> 1 | F26: ='Dicionario EAP2'!I33 -> 44455 | G26: 1 | I26: =IF(AND($C26="Objetivo",I$5>=$F26,I$5<=$F26+$G26-1),2,IF(AND($C26="Marco",I$5>=$F26,I$5<=$F26+$G26-1),1,"")) | J26: =IF(AND($C26="Objetivo",J$5>=$F26,J$5<=$F26+$G26-1),2,IF(AND($C26="Marco",J$5>=$F26,J$5<=$F26+$G26-1),1,"")) | K26: =IF(AND($C26="Objetivo",K$5>=$F26,K$5<=$F26+$G26-1),2,IF(AND($C26="Marco",K$5>=$F26,K$5<=$F26+$G26-1),1,"")) | L26: =IF(AND($C26="Objetivo",L$5>=$F26,L$5<=$F26+$G26-1),2,IF(AND($C26="Marco",L$5>=$F26,L$5<=$F26+$G26-1),1,"")) | M26: =IF(AND($C26="Objetivo",M$5>=$F26,M$5<=$F26+$G26-1),2,IF(AND($C26="Marco",M$5>=$F26,M$5<=$F26+$G26-1),1,"")) | N26: =IF(AND($C26="Objetivo",N$5>=$F26,N$5<=$F26+$G26-1),2,IF(AND($C26="Marco",N$5>=$F26,N$5<=$F26+$G26-1),1,"")) | O26: =IF(AND($C26="Objetivo",O$5>=$F26,O$5<=$F26+$G26-1),2,IF(AND($C26="Marco",O$5>=$F26,O$5<=$F26+$G26-1),1,"")) | P26: =IF(AND($C26="Objetivo",P$5>=$F26,P$5<=$F26+$G26-1),2,IF(AND($C26="Marco",P$5>=$F26,P$5<=$F26+$G26-1),1,"")) | ... BL26: =IF(AND($C26="Objetivo",BL$5>=$F26,BL$5<=$F26+$G26-1),2,IF(AND($C26="Marco",BL$5>=$F26,BL$5<=$F26+$G26-1),1,""))
A27: Gerar possiveis consequencias. | B27: definir o quão grave é o risco e as medidas de supressão dele. | C27: Alto risco | D27: ='Dicionario EAP2'!G34 -> Cosme Sousa Damião Sousa | E27: ='Dicionario EAP2'!T34 -> 1 | F27: ='Dicionario EAP2'!I34 -> 44455 | G27: 1 | I27: =IF(AND($C27="Objetivo",I$5>=$F27,I$5<=$F27+$G27-1),2,IF(AND($C27="Marco",I$5>=$F27,I$5<=$F27+$G27-1),1,"")) | J27: =IF(AND($C27="Objetivo",J$5>=$F27,J$5<=$F27+$G27-1),2,IF(AND($C27="Marco",J$5>=$F27,J$5<=$F27+$G27-1),1,"")) | K27: =IF(AND($C27="Objetivo",K$5>=$F27,K$5<=$F27+$G27-1),2,IF(AND($C27="Marco",K$5>=$F27,K$5<=$F27+$G27-1),1,"")) | L27: =IF(AND($C27="Objetivo",L$5>=$F27,L$5<=$F27+$G27-1),2,IF(AND($C27="Marco",L$5>=$F27,L$5<=$F27+$G27-1),1,"")) | M27: =IF(AND($C27="Objetivo",M$5>=$F27,M$5<=$F27+$G27-1),2,IF(AND($C27="Marco",M$5>=$F27,M$5<=$F27+$G27-1),1,"")) | N27: =IF(AND($C27="Objetivo",N$5>=$F27,N$5<=$F27+$G27-1),2,IF(AND($C27="Marco",N$5>=$F27,N$5<=$F27+$G27-1),1,"")) | O27: =IF(AND($C27="Objetivo",O$5>=$F27,O$5<=$F27+$G27-1),2,IF(AND($C27="Marco",O$5>=$F27,O$5<=$F27+$G27-1),1,"")) | P27: =IF(AND($C27="Objetivo",P$5>=$F27,P$5<=$F27+$G27-1),2,IF(AND($C27="Marco",P$5>=$F27,P$5<=$F27+$G27-1),1,"")) | ... BL27: =IF(AND($C27="Objetivo",BL$5>=$F27,BL$5<=$F27+$G27-1),2,IF(AND($C27="Marco",BL$5>=$F27,BL$5<=$F27+$G27-1),1,""))
A28: Comparar o tempo trabalho com a meta. | B28: Fazer um gráfico de acompanhamento do trabalho | C28: Alto risco | D28: ='Dicionario EAP2'!G35 -> Cosme Sousa Damião Sousa | E28: ='Dicionario EAP2'!T35 -> 1 | F28: ='Dicionario EAP2'!I35 -> 44455 | G28: 1 | I28: =IF(AND($C28="Objetivo",I$5>=$F28,I$5<=$F28+$G28-1),2,IF(AND($C28="Marco",I$5>=$F28,I$5<=$F28+$G28-1),1,"")) | J28: =IF(AND($C28="Objetivo",J$5>=$F28,J$5<=$F28+$G28-1),2,IF(AND($C28="Marco",J$5>=$F28,J$5<=$F28+$G28-1),1,"")) | K28: =IF(AND($C28="Objetivo",K$5>=$F28,K$5<=$F28+$G28-1),2,IF(AND($C28="Marco",K$5>=$F28,K$5<=$F28+$G28-1),1,"")) | L28: =IF(AND($C28="Objetivo",L$5>=$F28,L$5<=$F28+$G28-1),2,IF(AND($C28="Marco",L$5>=$F28,L$5<=$F28+$G28-1),1,"")) | M28: =IF(AND($C28="Objetivo",M$5>=$F28,M$5<=$F28+$G28-1),2,IF(AND($C28="Marco",M$5>=$F28,M$5<=$F28+$G28-1),1,"")) | N28: =IF(AND($C28="Objetivo",N$5>=$F28,N$5<=$F28+$G28-1),2,IF(AND($C28="Marco",N$5>=$F28,N$5<=$F28+$G28-1),1,"")) | O28: =IF(AND($C28="Objetivo",O$5>=$F28,O$5<=$F28+$G28-1),2,IF(AND($C28="Marco",O$5>=$F28,O$5<=$F28+$G28-1),1,"")) | P28: =IF(AND($C28="Objetivo",P$5>=$F28,P$5<=$F28+$G28-1),2,IF(AND($C28="Marco",P$5>=$F28,P$5<=$F28+$G28-1),1,"")) | ... BL28: =IF(AND($C28="Objetivo",BL$5>=$F28,BL$5<=$F28+$G28-1),2,IF(AND($C28="Marco",BL$5>=$F28,BL$5<=$F28+$G28-1),1,""))
A29: permitir que todos os quadros de energia possam ser instalados dentro do quadro de distribuição | B29: Usar a escala de mm para definir o tamanho do quadro de distribuição que conterá os quadros de iluminação, CFTV e alarme de incêndio. | C29: Alto risco | D29: ='Dicionario EAP2'!G36 -> Leandro Costa João Miranda | E29: ='Dicionario EAP2'!T36 -> 1 | F29: ='Dicionario EAP2'!I36 -> 44459 | G29: 14 | I29: =IF(AND($C29="Objetivo",I$5>=$F29,I$5<=$F29+$G29-1),2,IF(AND($C29="Marco",I$5>=$F29,I$5<=$F29+$G29-1),1,"")) | J29: =IF(AND($C29="Objetivo",J$5>=$F29,J$5<=$F29+$G29-1),2,IF(AND($C29="Marco",J$5>=$F29,J$5<=$F29+$G29-1),1,"")) | K29: =IF(AND($C29="Objetivo",K$5>=$F29,K$5<=$F29+$G29-1),2,IF(AND($C29="Marco",K$5>=$F29,K$5<=$F29+$G29-1),1,"")) | L29: =IF(AND($C29="Objetivo",L$5>=$F29,L$5<=$F29+$G29-1),2,IF(AND($C29="Marco",L$5>=$F29,L$5<=$F29+$G29-1),1,"")) | M29: =IF(AND($C29="Objetivo",M$5>=$F29,M$5<=$F29+$G29-1),2,IF(AND($C29="Marco",M$5>=$F29,M$5<=$F29+$G29-1),1,"")) | N29: =IF(AND($C29="Objetivo",N$5>=$F29,N$5<=$F29+$G29-1),2,IF(AND($C29="Marco",N$5>=$F29,N$5<=$F29+$G29-1),1,"")) | O29: =IF(AND($C29="Objetivo",O$5>=$F29,O$5<=$F29+$G29-1),2,IF(AND($C29="Marco",O$5>=$F29,O$5<=$F29+$G29-1),1,"")) | P29: =IF(AND($C29="Objetivo",P$5>=$F29,P$5<=$F29+$G29-1),2,IF(AND($C29="Marco",P$5>=$F29,P$5<=$F29+$G29-1),1,"")) | ... BL29: =IF(AND($C29="Objetivo",BL$5>=$F29,BL$5<=$F29+$G29-1),2,IF(AND($C29="Marco",BL$5>=$F29,BL$5<=$F29+$G29-1),1,""))
A30: proteger o circuito de iluminação | B30: Usar disjuntor, DPS e DR para a proteção do circuito de iluminação. | C30: Alto risco | D30: ='Dicionario EAP2'!G37 -> Leandro Costa João Miranda | E30: ='Dicionario EAP2'!T37 -> 1 | F30: ='Dicionario EAP2'!I37 -> 44459 | G30: 14 | I30: =IF(AND($C30="Objetivo",I$5>=$F30,I$5<=$F30+$G30-1),2,IF(AND($C30="Marco",I$5>=$F30,I$5<=$F30+$G30-1),1,"")) | J30: =IF(AND($C30="Objetivo",J$5>=$F30,J$5<=$F30+$G30-1),2,IF(AND($C30="Marco",J$5>=$F30,J$5<=$F30+$G30-1),1,"")) | K30: =IF(AND($C30="Objetivo",K$5>=$F30,K$5<=$F30+$G30-1),2,IF(AND($C30="Marco",K$5>=$F30,K$5<=$F30+$G30-1),1,"")) | L30: =IF(AND($C30="Objetivo",L$5>=$F30,L$5<=$F30+$G30-1),2,IF(AND($C30="Marco",L$5>=$F30,L$5<=$F30+$G30-1),1,"")) | M30: =IF(AND($C30="Objetivo",M$5>=$F30,M$5<=$F30+$G30-1),2,IF(AND($C30="Marco",M$5>=$F30,M$5<=$F30+$G30-1),1,"")) | N30: =IF(AND($C30="Objetivo",N$5>=$F30,N$5<=$F30+$G30-1),2,IF(AND($C30="Marco",N$5>=$F30,N$5<=$F30+$G30-1),1,"")) | O30: =IF(AND($C30="Objetivo",O$5>=$F30,O$5<=$F30+$G30-1),2,IF(AND($C30="Marco",O$5>=$F30,O$5<=$F30+$G30-1),1,"")) | P30: =IF(AND($C30="Objetivo",P$5>=$F30,P$5<=$F30+$G30-1),2,IF(AND($C30="Marco",P$5>=$F30,P$5<=$F30+$G30-1),1,"")) | ... BL30: =IF(AND($C30="Objetivo",BL$5>=$F30,BL$5<=$F30+$G30-1),2,IF(AND($C30="Marco",BL$5>=$F30,BL$5<=$F30+$G30-1),1,""))
A31: Fazer a alimentação das câmeras e do DRV com condutores isolados e sem imendas nos eletrodutos. | B31: Passar os cabos pelos eletrodutos. | C31: Alto risco | D31: Nilton Guerra Cosme Alvez Damião Alves Pétrick Gomes | E31: ='Dicionario EAP2'!T38 -> 1 | F31: ='Dicionario EAP2'!I38 -> 44461 | G31: 2 | I31: =IF(AND($C31="Objetivo",I$5>=$F31,I$5<=$F31+$G31-1),2,IF(AND($C31="Marco",I$5>=$F31,I$5<=$F31+$G31-1),1,"")) | J31: =IF(AND($C31="Objetivo",J$5>=$F31,J$5<=$F31+$G31-1),2,IF(AND($C31="Marco",J$5>=$F31,J$5<=$F31+$G31-1),1,"")) | L31: =IF(AND($C31="Objetivo",L$5>=$F31,L$5<=$F31+$G31-1),2,IF(AND($C31="Marco",L$5>=$F31,L$5<=$F31+$G31-1),1,"")) | M31: =IF(AND($C31="Objetivo",M$5>=$F31,M$5<=$F31+$G31-1),2,IF(AND($C31="Marco",M$5>=$F31,M$5<=$F31+$G31-1),1,"")) | N31: =IF(AND($C31="Objetivo",N$5>=$F31,N$5<=$F31+$G31-1),2,IF(AND($C31="Marco",N$5>=$F31,N$5<=$F31+$G31-1),1,"")) | O31: =IF(AND($C31="Objetivo",O$5>=$F31,O$5<=$F31+$G31-1),2,IF(AND($C31="Marco",O$5>=$F31,O$5<=$F31+$G31-1),1,"")) | P31: =IF(AND($C31="Objetivo",P$5>=$F31,P$5<=$F31+$G31-1),2,IF(AND($C31="Marco",P$5>=$F31,P$5<=$F31+$G31-1),1,"")) | Q31: =IF(AND($C31="Objetivo",Q$5>=$F31,Q$5<=$F31+$G31-1),2,IF(AND($C31="Marco",Q$5>=$F31,Q$5<=$F31+$G31-1),1,"")) | R31: =IF(AND($C31="Objetivo",R$5>=$F31,R$5<=$F31+$G31-1),2,IF(AND($C31="Marco",R$5>=$F31,R$5<=$F31+$G31-1),1,"")) | S31: =IF(AND($C31="Objetivo",S$5>=$F31,S$5<=$F31+$G31-1),2,IF(AND($C31="Marco",S$5>=$F31,S$5<=$F31+$G31-1),1,"")) | ... BL31: =IF(AND($C31="Objetivo",BL$5>=$F31,BL$5<=$F31+$G31-1),2,IF(AND($C31="Marco",BL$5>=$F31,BL$5<=$F31+$G31-1),1,""))
A32: Fixar firme as câmeras e fazer a alimentação e a transmição de dados com facilidade. | B32: Instalar apoios para as câmeras através de parafusos e porcas, para logo em seguida colocar as câmeras. | C32: Médio risco | D32: Nilton Guerra Cosme Alvez Damião Alves Pétrick Gomes | E32: ='Dicionario EAP2'!T39 -> 1 | F32: ='Dicionario EAP2'!I39 -> 44462 | G32: 1 | I32: =IF(AND($C32="Objetivo",I$5>=$F32,I$5<=$F32+$G32-1),2,IF(AND($C32="Marco",I$5>=$F32,I$5<=$F32+$G32-1),1,"")) | J32: =IF(AND($C32="Objetivo",J$5>=$F32,J$5<=$F32+$G32-1),2,IF(AND($C32="Marco",J$5>=$F32,J$5<=$F32+$G32-1),1,"")) | K32: =IF(AND($C32="Objetivo",K$5>=$F32,K$5<=$F32+$G32-1),2,IF(AND($C32="Marco",K$5>=$F32,K$5<=$F32+$G32-1),1,"")) | L32: =IF(AND($C32="Objetivo",L$5>=$F32,L$5<=$F32+$G32-1),2,IF(AND($C32="Marco",L$5>=$F32,L$5<=$F32+$G32-1),1,"")) | M32: =IF(AND($C32="Objetivo",M$5>=$F32,M$5<=$F32+$G32-1),2,IF(AND($C32="Marco",M$5>=$F32,M$5<=$F32+$G32-1),1,"")) | N32: =IF(AND($C32="Objetivo",N$5>=$F32,N$5<=$F32+$G32-1),2,IF(AND($C32="Marco",N$5>=$F32,N$5<=$F32+$G32-1),1,"")) | O32: =IF(AND($C32="Objetivo",O$5>=$F32,O$5<=$F32+$G32-1),2,IF(AND($C32="Marco",O$5>=$F32,O$5<=$F32+$G32-1),1,"")) | P32: =IF(AND($C32="Objetivo",P$5>=$F32,P$5<=$F32+$G32-1),2,IF(AND($C32="Marco",P$5>=$F32,P$5<=$F32+$G32-1),1,"")) | ... BL32: =IF(AND($C32="Objetivo",BL$5>=$F32,BL$5<=$F32+$G32-1),2,IF(AND($C32="Marco",BL$5>=$F32,BL$5<=$F32+$G32-1),1,""))
A33: Permitir a comunicação do monitor com o DRV | B33: usar o cabo VGA para comunicar o DVR com o monitor e alimentar ambos. | C33: Médio risco | D33: Nilton Guerra Cosme Alvez Damião Alves Pétrick Gomes | E33: ='Dicionario EAP2'!T40 -> 1 | F33: ='Dicionario EAP2'!I40 -> 44462 | G33: 1 | I33: =IF(AND($C33="Objetivo",I$5>=$F33,I$5<=$F33+$G33-1),2,IF(AND($C33="Marco",I$5>=$F33,I$5<=$F33+$G33-1),1,"")) | J33: =IF(AND($C33="Objetivo",J$5>=$F33,J$5<=$F33+$G33-1),2,IF(AND($C33="Marco",J$5>=$F33,J$5<=$F33+$G33-1),1,"")) | K33: =IF(AND($C33="Objetivo",K$5>=$F33,K$5<=$F33+$G33-1),2,IF(AND($C33="Marco",K$5>=$F33,K$5<=$F33+$G33-1),1,"")) | L33: =IF(AND($C33="Objetivo",L$5>=$F33,L$5<=$F33+$G33-1),2,IF(AND($C33="Marco",L$5>=$F33,L$5<=$F33+$G33-1),1,"")) | M33: =IF(AND($C33="Objetivo",M$5>=$F33,M$5<=$F33+$G33-1),2,IF(AND($C33="Marco",M$5>=$F33,M$5<=$F33+$G33-1),1,"")) | N33: =IF(AND($C33="Objetivo",N$5>=$F33,N$5<=$F33+$G33-1),2,IF(AND($C33="Marco",N$5>=$F33,N$5<=$F33+$G33-1),1,"")) | O33: =IF(AND($C33="Objetivo",O$5>=$F33,O$5<=$F33+$G33-1),2,IF(AND($C33="Marco",O$5>=$F33,O$5<=$F33+$G33-1),1,"")) | P33: =IF(AND($C33="Objetivo",P$5>=$F33,P$5<=$F33+$G33-1),2,IF(AND($C33="Marco",P$5>=$F33,P$5<=$F33+$G33-1),1,"")) | ... BL33: =IF(AND($C33="Objetivo",BL$5>=$F33,BL$5<=$F33+$G33-1),2,IF(AND($C33="Marco",BL$5>=$F33,BL$5<=$F33+$G33-1),1,""))
A34: Permitir a visualização dos pontos de vigilância no monitor | B34: usando o conector P4 macho e fêmea e o cabo coaxial fazer o interligamento da câmera com o DVR. | C34: Alto risco | D34: Nilton Guerra Cosme Alvez Damião Alves Pétrick Gomes | E34: ='Dicionario EAP2'!T41 -> 1 | F34: ='Dicionario EAP2'!I41 -> 44462 | G34: 1 | I34: =IF(AND($C34="Objetivo",I$5>=$F34,I$5<=$F34+$G34-1),2,IF(AND($C34="Marco",I$5>=$F34,I$5<=$F34+$G34-1),1,"")) | J34: =IF(AND($C34="Objetivo",J$5>=$F34,J$5<=$F34+$G34-1),2,IF(AND($C34="Marco",J$5>=$F34,J$5<=$F34+$G34-1),1,"")) | K34: =IF(AND($C34="Objetivo",K$5>=$F34,K$5<=$F34+$G34-1),2,IF(AND($C34="Marco",K$5>=$F34,K$5<=$F34+$G34-1),1,"")) | L34: =IF(AND($C34="Objetivo",L$5>=$F34,L$5<=$F34+$G34-1),2,IF(AND($C34="Marco",L$5>=$F34,L$5<=$F34+$G34-1),1,"")) | M34: =IF(AND($C34="Objetivo",M$5>=$F34,M$5<=$F34+$G34-1),2,IF(AND($C34="Marco",M$5>=$F34,M$5<=$F34+$G34-1),1,"")) | N34: =IF(AND($C34="Objetivo",N$5>=$F34,N$5<=$F34+$G34-1),2,IF(AND($C34="Marco",N$5>=$F34,N$5<=$F34+$G34-1),1,"")) | O34: =IF(AND($C34="Objetivo",O$5>=$F34,O$5<=$F34+$G34-1),2,IF(AND($C34="Marco",O$5>=$F34,O$5<=$F34+$G34-1),1,"")) | P34: =IF(AND($C34="Objetivo",P$5>=$F34,P$5<=$F34+$G34-1),2,IF(AND($C34="Marco",P$5>=$F34,P$5<=$F34+$G34-1),1,"")) | ... BL34: =IF(AND($C34="Objetivo",BL$5>=$F34,BL$5<=$F34+$G34-1),2,IF(AND($C34="Marco",BL$5>=$F34,BL$5<=$F34+$G34-1),1,""))
A35: Que os cabos passados sejam alimentados e devidamente isolados sem imentas nos eletrodutos. | B35: Passar os cabos pelos eletrodutos. | C35: Médio risco | D35: ='Dicionario EAP2'!G42 -> Cosme Sousa Damião Sousa Pétrick Gomes Nilton Guerra | E35: ='Dicionario EAP2'!T42 -> 1 | F35: ='Dicionario EAP2'!I42 -> 44463 | G35: 1 | I35: =IF(AND($C35="Objetivo",I$5>=$F35,I$5<=$F35+$G35-1),2,IF(AND($C35="Marco",I$5>=$F35,I$5<=$F35+$G35-1),1,"")) | J35: =IF(AND($C35="Objetivo",J$5>=$F35,J$5<=$F35+$G35-1),2,IF(AND($C35="Marco",J$5>=$F35,J$5<=$F35+$G35-1),1,"")) | K35: =IF(AND($C35="Objetivo",K$5>=$F35,K$5<=$F35+$G35-1),2,IF(AND($C35="Marco",K$5>=$F35,K$5<=$F35+$G35-1),1,"")) | L35: =IF(AND($C35="Objetivo",L$5>=$F35,L$5<=$F35+$G35-1),2,IF(AND($C35="Marco",L$5>=$F35,L$5<=$F35+$G35-1),1,"")) | M35: =IF(AND($C35="Objetivo",M$5>=$F35,M$5<=$F35+$G35-1),2,IF(AND($C35="Marco",M$5>=$F35,M$5<=$F35+$G35-1),1,"")) | N35: =IF(AND($C35="Objetivo",N$5>=$F35,N$5<=$F35+$G35-1),2,IF(AND($C35="Marco",N$5>=$F35,N$5<=$F35+$G35-1),1,"")) | O35: =IF(AND($C35="Objetivo",O$5>=$F35,O$5<=$F35+$G35-1),2,IF(AND($C35="Marco",O$5>=$F35,O$5<=$F35+$G35-1),1,"")) | P35: =IF(AND($C35="Objetivo",P$5>=$F35,P$5<=$F35+$G35-1),2,IF(AND($C35="Marco",P$5>=$F35,P$5<=$F35+$G35-1),1,"")) | ... BL35: =IF(AND($C35="Objetivo",BL$5>=$F35,BL$5<=$F35+$G35-1),2,IF(AND($C35="Marco",BL$5>=$F35,BL$5<=$F35+$G35-1),1,""))
A36: Ligar todas as conexões dos sensores corretamente. | B36: instalar os sensores de fumaça respeitando as suas coneções com a central de incêndio. | C36: Alto risco | D36: ='Dicionario EAP2'!G43 -> Cosme Sousa Damião Sousa Pétrick Gomes Nilton Guerra | E36: ='Dicionario EAP2'!T43 -> 1 | F36: ='Dicionario EAP2'!I43 -> 44463 | G36: 1 | I36: =IF(AND($C36="Objetivo",I$5>=$F36,I$5<=$F36+$G36-1),2,IF(AND($C36="Marco",I$5>=$F36,I$5<=$F36+$G36-1),1,"")) | J36: =IF(AND($C36="Objetivo",J$5>=$F36,J$5<=$F36+$G36-1),2,IF(AND($C36="Marco",J$5>=$F36,J$5<=$F36+$G36-1),1,"")) | K36: =IF(AND($C36="Objetivo",K$5>=$F36,K$5<=$F36+$G36-1),2,IF(AND($C36="Marco",K$5>=$F36,K$5<=$F36+$G36-1),1,"")) | L36: =IF(AND($C36="Objetivo",L$5>=$F36,L$5<=$F36+$G36-1),2,IF(AND($C36="Marco",L$5>=$F36,L$5<=$F36+$G36-1),1,"")) | M36: =IF(AND($C36="Objetivo",M$5>=$F36,M$5<=$F36+$G36-1),2,IF(AND($C36="Marco",M$5>=$F36,M$5<=$F36+$G36-1),1,"")) | N36: =IF(AND($C36="Objetivo",N$5>=$F36,N$5<=$F36+$G36-1),2,IF(AND($C36="Marco",N$5>=$F36,N$5<=$F36+$G36-1),1,"")) | O36: =IF(AND($C36="Objetivo",O$5>=$F36,O$5<=$F36+$G36-1),2,IF(AND($C36="Marco",O$5>=$F36,O$5<=$F36+$G36-1),1,"")) | P36: =IF(AND($C36="Objetivo",P$5>=$F36,P$5<=$F36+$G36-1),2,IF(AND($C36="Marco",P$5>=$F36,P$5<=$F36+$G36-1),1,"")) | ... BL36: =IF(AND($C36="Objetivo",BL$5>=$F36,BL$5<=$F36+$G36-1),2,IF(AND($C36="Marco",BL$5>=$F36,BL$5<=$F36+$G36-1),1,""))
A37: Fazer a comunicação entre central de alarme de incêndio e sesores de fumaça. | B37: posicionar um local especifico para gerenciar o controle de incêndio | C37: Médio risco | D37: ='Dicionario EAP2'!G44 -> Cosme Sousa Damião Sousa Pétrick Gomes Nilton Guerra | E37: ='Dicionario EAP2'!T44 -> 1 | F37: ='Dicionario EAP2'!I44 -> 44466 | G37: 1 | I37: =IF(AND($C37="Objetivo",I$5>=$F37,I$5<=$F37+$G37-1),2,IF(AND($C37="Marco",I$5>=$F37,I$5<=$F37+$G37-1),1,"")) | J37: =IF(AND($C37="Objetivo",J$5>=$F37,J$5<=$F37+$G37-1),2,IF(AND($C37="Marco",J$5>=$F37,J$5<=$F37+$G37-1),1,"")) | K37: =IF(AND($C37="Objetivo",K$5>=$F37,K$5<=$F37+$G37-1),2,IF(AND($C37="Marco",K$5>=$F37,K$5<=$F37+$G37-1),1,"")) | L37: =IF(AND($C37="Objetivo",L$5>=$F37,L$5<=$F37+$G37-1),2,IF(AND($C37="Marco",L$5>=$F37,L$5<=$F37+$G37-1),1,"")) | M37: =IF(AND($C37="Objetivo",M$5>=$F37,M$5<=$F37+$G37-1),2,IF(AND($C37="Marco",M$5>=$F37,M$5<=$F37+$G37-1),1,"")) | N37: =IF(AND($C37="Objetivo",N$5>=$F37,N$5<=$F37+$G37-1),2,IF(AND($C37="Marco",N$5>=$F37,N$5<=$F37+$G37-1),1,"")) | O37: =IF(AND($C37="Objetivo",O$5>=$F37,O$5<=$F37+$G37-1),2,IF(AND($C37="Marco",O$5>=$F37,O$5<=$F37+$G37-1),1,"")) | P37: =IF(AND($C37="Objetivo",P$5>=$F37,P$5<=$F37+$G37-1),2,IF(AND($C37="Marco",P$5>=$F37,P$5<=$F37+$G37-1),1,"")) | ... BL37: =IF(AND($C37="Objetivo",BL$5>=$F37,BL$5<=$F37+$G37-1),2,IF(AND($C37="Marco",BL$5>=$F37,BL$5<=$F37+$G37-1),1,""))
A38: Que os cabos passados sejam alimentados e devidamente isolados sem imentas nos eletrodutos. | B38: ='Dicionario EAP2'!D45 -> Passar os cabos pelos eletrodutos. | C38: Médio risco | D38: ='Dicionario EAP2'!G45 -> Cosme Sousa Damião Sousa Pétrick Gomes Leandro Costa | E38: ='Dicionario EAP2'!T45 -> 1 | F38: ='Dicionario EAP2'!I45 -> 44474 | G38: 4 | I38: =IF(AND($C38="Objetivo",I$5>=$F38,I$5<=$F38+$G38-1),2,IF(AND($C38="Marco",I$5>=$F38,I$5<=$F38+$G38-1),1,"")) | J38: =IF(AND($C38="Objetivo",J$5>=$F38,J$5<=$F38+$G38-1),2,IF(AND($C38="Marco",J$5>=$F38,J$5<=$F38+$G38-1),1,"")) | K38: =IF(AND($C38="Objetivo",K$5>=$F38,K$5<=$F38+$G38-1),2,IF(AND($C38="Marco",K$5>=$F38,K$5<=$F38+$G38-1),1,"")) | L38: =IF(AND($C38="Objetivo",L$5>=$F38,L$5<=$F38+$G38-1),2,IF(AND($C38="Marco",L$5>=$F38,L$5<=$F38+$G38-1),1,"")) | M38: =IF(AND($C38="Objetivo",M$5>=$F38,M$5<=$F38+$G38-1),2,IF(AND($C38="Marco",M$5>=$F38,M$5<=$F38+$G38-1),1,"")) | N38: =IF(AND($C38="Objetivo",N$5>=$F38,N$5<=$F38+$G38-1),2,IF(AND($C38="Marco",N$5>=$F38,N$5<=$F38+$G38-1),1,"")) | O38: =IF(AND($C38="Objetivo",O$5>=$F38,O$5<=$F38+$G38-1),2,IF(AND($C38="Marco",O$5>=$F38,O$5<=$F38+$G38-1),1,"")) | P38: =IF(AND($C38="Objetivo",P$5>=$F38,P$5<=$F38+$G38-1),2,IF(AND($C38="Marco",P$5>=$F38,P$5<=$F38+$G38-1),1,"")) | ... BL38: =IF(AND($C38="Objetivo",BL$5>=$F38,BL$5<=$F38+$G38-1),2,IF(AND($C38="Marco",BL$5>=$F38,BL$5<=$F38+$G38-1),1,""))
A39: Fazer as lampadas acenderem. | B39: ='Dicionario EAP2'!E46 -> Iluminar o ambiente. | C39: Alto risco | D39: ='Dicionario EAP2'!G46 -> Cosme Sousa Damião Sousa Pétrick Gomes Leandro Costa | E39: ='Dicionario EAP2'!T46 -> 1 | F39: ='Dicionario EAP2'!I46 -> 44476 | G39: 2 | I39: =IF(AND($C39="Objetivo",I$5>=$F39,I$5<=$F39+$G39-1),2,IF(AND($C39="Marco",I$5>=$F39,I$5<=$F39+$G39-1),1,"")) | J39: =IF(AND($C39="Objetivo",J$5>=$F39,J$5<=$F39+$G39-1),2,IF(AND($C39="Marco",J$5>=$F39,J$5<=$F39+$G39-1),1,"")) | K39: =IF(AND($C39="Objetivo",K$5>=$F39,K$5<=$F39+$G39-1),2,IF(AND($C39="Marco",K$5>=$F39,K$5<=$F39+$G39-1),1,"")) | L39: =IF(AND($C39="Objetivo",L$5>=$F39,L$5<=$F39+$G39-1),2,IF(AND($C39="Marco",L$5>=$F39,L$5<=$F39+$G39-1),1,"")) | M39: =IF(AND($C39="Objetivo",M$5>=$F39,M$5<=$F39+$G39-1),2,IF(AND($C39="Marco",M$5>=$F39,M$5<=$F39+$G39-1),1,"")) | N39: =IF(AND($C39="Objetivo",N$5>=$F39,N$5<=$F39+$G39-1),2,IF(AND($C39="Marco",N$5>=$F39,N$5<=$F39+$G39-1),1,"")) | O39: =IF(AND($C39="Objetivo",O$5>=$F39,O$5<=$F39+$G39-1),2,IF(AND($C39="Marco",O$5>=$F39,O$5<=$F39+$G39-1),1,"")) | P39: =IF(AND($C39="Objetivo",P$5>=$F39,P$5<=$F39+$G39-1),2,IF(AND($C39="Marco",P$5>=$F39,P$5<=$F39+$G39-1),1,"")) | ... BL39: =IF(AND($C39="Objetivo",BL$5>=$F39,BL$5<=$F39+$G39-1),2,IF(AND($C39="Marco",BL$5>=$F39,BL$5<=$F39+$G39-1),1,""))
A40: Fazer a instalação dos interruptores móveis com condutores sem imendas e sem partes de cobre a mostra. | B40: ='Dicionario EAP2'!E47 -> instalar interruptores e tomadas | C40: Alto risco | D40: ='Dicionario EAP2'!G47 -> Cosme Sousa Damião Sousa Pétrick Gomes Leandro Costa | E40: ='Dicionario EAP2'!T47 -> 1 | F40: ='Dicionario EAP2'!I47 -> 44477 | G40: 3 | I40: =IF(AND($C40="Objetivo",I$5>=$F40,I$5<=$F40+$G40-1),2,IF(AND($C40="Marco",I$5>=$F40,I$5<=$F40+$G40-1),1,"")) | J40: =IF(AND($C40="Objetivo",J$5>=$F40,J$5<=$F40+$G40-1),2,IF(AND($C40="Marco",J$5>=$F40,J$5<=$F40+$G40-1),1,"")) | K40: =IF(AND($C40="Objetivo",K$5>=$F40,K$5<=$F40+$G40-1),2,IF(AND($C40="Marco",K$5>=$F40,K$5<=$F40+$G40-1),1,"")) | L40: =IF(AND($C40="Objetivo",L$5>=$F40,L$5<=$F40+$G40-1),2,IF(AND($C40="Marco",L$5>=$F40,L$5<=$F40+$G40-1),1,"")) | M40: =IF(AND($C40="Objetivo",M$5>=$F40,M$5<=$F40+$G40-1),2,IF(AND($C40="Marco",M$5>=$F40,M$5<=$F40+$G40-1),1,"")) | N40: =IF(AND($C40="Objetivo",N$5>=$F40,N$5<=$F40+$G40-1),2,IF(AND($C40="Marco",N$5>=$F40,N$5<=$F40+$G40-1),1,"")) | O40: =IF(AND($C40="Objetivo",O$5>=$F40,O$5<=$F40+$G40-1),2,IF(AND($C40="Marco",O$5>=$F40,O$5<=$F40+$G40-1),1,"")) | P40: =IF(AND($C40="Objetivo",P$5>=$F40,P$5<=$F40+$G40-1),2,IF(AND($C40="Marco",P$5>=$F40,P$5<=$F40+$G40-1),1,"")) | ... BL40: =IF(AND($C40="Objetivo",BL$5>=$F40,BL$5<=$F40+$G40-1),2,IF(AND($C40="Marco",BL$5>=$F40,BL$5<=$F40+$G40-1),1,""))
A41: Fazer os interruptores móveis funcionarem | B41: ='Dicionario EAP2'!E48 -> Verificar o correto funcionamento. | C41: Alto risco | D41: ='Dicionario EAP2'!G48 -> Cosme Sousa Damião Sousa Pétrick Gomes Leandro Costa | E41: ='Dicionario EAP2'!T48 -> 1 | F41: ='Dicionario EAP2'!I48 -> 44477 | G41: 1 | I41: =IF(AND($C41="Objetivo",I$5>=$F41,I$5<=$F41+$G41-1),2,IF(AND($C41="Marco",I$5>=$F41,I$5<=$F41+$G41-1),1,"")) | J41: =IF(AND($C41="Objetivo",J$5>=$F41,J$5<=$F41+$G41-1),2,IF(AND($C41="Marco",J$5>=$F41,J$5<=$F41+$G41-1),1,"")) | K41: =IF(AND($C41="Objetivo",K$5>=$F41,K$5<=$F41+$G41-1),2,IF(AND($C41="Marco",K$5>=$F41,K$5<=$F41+$G41-1),1,"")) | L41: =IF(AND($C41="Objetivo",L$5>=$F41,L$5<=$F41+$G41-1),2,IF(AND($C41="Marco",L$5>=$F41,L$5<=$F41+$G41-1),1,"")) | M41: =IF(AND($C41="Objetivo",M$5>=$F41,M$5<=$F41+$G41-1),2,IF(AND($C41="Marco",M$5>=$F41,M$5<=$F41+$G41-1),1,"")) | N41: =IF(AND($C41="Objetivo",N$5>=$F41,N$5<=$F41+$G41-1),2,IF(AND($C41="Marco",N$5>=$F41,N$5<=$F41+$G41-1),1,"")) | O41: =IF(AND($C41="Objetivo",O$5>=$F41,O$5<=$F41+$G41-1),2,IF(AND($C41="Marco",O$5>=$F41,O$5<=$F41+$G41-1),1,"")) | P41: =IF(AND($C41="Objetivo",P$5>=$F41,P$5<=$F41+$G41-1),2,IF(AND($C41="Marco",P$5>=$F41,P$5<=$F41+$G41-1),1,"")) | ... BL41: =IF(AND($C41="Objetivo",BL$5>=$F41,BL$5<=$F41+$G41-1),2,IF(AND($C41="Marco",BL$5>=$F41,BL$5<=$F41+$G41-1),1,""))
A42: Verificar ligação do monitor de energia. | B42: Fazer a instalação do monitor de energia em um painel | C42: Médio risco | D42: ='Dicionario EAP2'!G49 -> Leandro Costa João Miranda | E42: ='Dicionario EAP2'!T49 -> 1 | F42: ='Dicionario EAP2'!I49 -> 44487 | G42: 11
A43: Fazer o monitor de energia funcionar. | B43: colocar o circuito em serie com o quadro de energia através de suas respectivas conexões | C43: Médio risco | D43: ='Dicionario EAP2'!G50 -> Leandro Costa João Miranda | E43: ='Dicionario EAP2'!T50 -> 1 | F43: ='Dicionario EAP2'!I50 -> 44493 | G43: 1
A44: confirmar que o monitor de energia está funcionando corretamente. | B44: Usando um multimetro, o monitor de energia e uma carga verificar se os resultados batem | C44: Alto risco | D44: ='Dicionario EAP2'!G51 -> Leandro Costa João Miranda | E44: ='Dicionario EAP2'!T51 -> 1 | F44: ='Dicionario EAP2'!I51 -> 44493 | G44: 1
A45: Controlar alexa pelo app. | B45: fazer a programação e configurações da alexa atraves do aplicativo | C45: Baixo risco | D45: ='Dicionario EAP2'!G52 -> Pétrick Gomes João Miranda Nilton Guerra | E45: ='Dicionario EAP2'!T52 -> 1 | F45: ='Dicionario EAP2'!I53 -> 44497 | G45: 1
A46: Alexa Responder aos comandos corretamente | B46: fazer testes para conferir se a alexa está funcionando | C46: Médio risco | D46: ='Dicionario EAP2'!G53 -> Pétrick Gomes João Miranda Nilton Guerra | E46: ='Dicionario EAP2'!T53 -> 1 | F46: ='Dicionario EAP2'!I53 -> 44497 | G46: 1
A47: Alexa controlar outros dispositivos | B47: fazer a configuração da alexa com outros dispositivos | C47: Baixo risco | D47: ='Dicionario EAP2'!G54 -> Pétrick Gomes João Miranda Nilton Guerra | E47: ='Dicionario EAP2'!T54 -> 1 | F47: ='Dicionario EAP2'!I54 -> 44504 | G47: 1
A48: interfone estar fixado | B48: fazer a instalação do interfone na local | C48: Médio risco | D48: ='Dicionario EAP2'!G55 -> Nilton Guerra | E48: ='Dicionario EAP2'!T55 -> 1 | F48: ='Dicionario EAP2'!I55 -> 44469 | G48: 1
A49: interfone está funcionando | B49: fazer testes para conferir o funcionamento do interfone | C49: Médio risco | D49: ='Dicionario EAP2'!G56 -> Nilton Guerra | E49: ='Dicionario EAP2'!T56 -> 1 | F49: ='Dicionario EAP2'!I56 -> 44470 | G49: 4
A50: interfone funcionar junto ao sistema de segurança | B50: fazer a integração do interfone com a trava automatica | C50: Médio risco | D50: ='Dicionario EAP2'!G57 -> Nilton Guerra | E50: ='Dicionario EAP2'!T57 -> 1 | F50: ='Dicionario EAP2'!I57 -> 44470 | G50: 4 | I50: =IF(AND($C50="Objetivo",I$5>=$F50,I$5<=$F50+$G50-1),2,IF(AND($C50="Marco",I$5>=$F50,I$5<=$F50+$G50-1),1,"")) | J50: =IF(AND($C50="Objetivo",J$5>=$F50,J$5<=$F50+$G50-1),2,IF(AND($C50="Marco",J$5>=$F50,J$5<=$F50+$G50-1),1,"")) | K50: =IF(AND($C50="Objetivo",K$5>=$F50,K$5<=$F50+$G50-1),2,IF(AND($C50="Marco",K$5>=$F50,K$5<=$F50+$G50-1),1,"")) | L50: =IF(AND($C50="Objetivo",L$5>=$F50,L$5<=$F50+$G50-1),2,IF(AND($C50="Marco",L$5>=$F50,L$5<=$F50+$G50-1),1,"")) | M50: =IF(AND($C50="Objetivo",M$5>=$F50,M$5<=$F50+$G50-1),2,IF(AND($C50="Marco",M$5>=$F50,M$5<=$F50+$G50-1),1,"")) | N50: =IF(AND($C50="Objetivo",N$5>=$F50,N$5<=$F50+$G50-1),2,IF(AND($C50="Marco",N$5>=$F50,N$5<=$F50+$G50-1),1,"")) | O50: =IF(AND($C50="Objetivo",O$5>=$F50,O$5<=$F50+$G50-1),2,IF(AND($C50="Marco",O$5>=$F50,O$5<=$F50+$G50-1),1,"")) | P50: =IF(AND($C50="Objetivo",P$5>=$F50,P$5<=$F50+$G50-1),2,IF(AND($C50="Marco",P$5>=$F50,P$5<=$F50+$G50-1),1,"")) | ... BL50: =IF(AND($C50="Objetivo",BL$5>=$F50,BL$5<=$F50+$G50-1),2,IF(AND($C50="Marco",BL$5>=$F50,BL$5<=$F50+$G50-1),1,""))
A51: instalação das travas automaticas | B51: fazer a instalação das travas automaticas | C51: Médio risco | D51: ='Dicionario EAP2'!G58 -> Nilton Guerra | E51: ='Dicionario EAP2'!T58 -> 1 | F51: ='Dicionario EAP2'!I58 -> 44470 | G51: 1
A52: Fazer o funcionamento da trava | B52: fazer testes para conferir o funcionamento dos dispositivos | C52: Médio risco | D52: ='Dicionario EAP2'!G59 -> Nilton Guerra | E52: ='Dicionario EAP2'!T59 -> 1 | F52: ='Dicionario EAP2'!I59 -> 44470 | G52: 4
A53: integrar com sistema de segurança | B53: fazer a integração da trava automativa com o internofe | C53: Alto risco | D53: ='Dicionario EAP2'!G60 -> Nilton Guerra | E53: ='Dicionario EAP2'!T60 -> 1 | F53: ='Dicionario EAP2'!I60 -> 44470 | G53: 4
A54: Acrescentar base ao projeto. | B54: Levantamento dos equipamentos e manuais necessários | C54: Alto risco | D54: ='Dicionario EAP2'!G61 -> Nilton Guerra Cosme Sousa | E54: ='Dicionario EAP2'!T61 -> 0 | F54: ='Dicionario EAP2'!I61 -> 0
A55: Garantir material ao projeto. | B55: Configurações remotas e manuais | C55: Baixo risco | D55: ='Dicionario EAP2'!G62 -> Nilton Guerra Cosme Sousa | E55: ='Dicionario EAP2'!T62 -> 0 | F55: ='Dicionario EAP2'!I62 -> 0
A56: Ser um meio de realização do trabalho. | B56: Integração com centrais e redes sem fio | C56: Médio risco | D56: ='Dicionario EAP2'!G63 -> Nilton Guerra Cosme Sousa | E56: ='Dicionario EAP2'!T63 -> 0 | F56: ='Dicionario EAP2'!I63 -> 0
A57: Sistema base do projeto. | B57: Integração com o cliente | C57: Médio risco | D57: ='Dicionario EAP2'!G64 -> Nilton Guerra Cosme Sousa | E57: ='Dicionario EAP2'!T64 -> 0 | F57: ='Dicionario EAP2'!I64 -> 0
A58: Fazer a comunicação das câmeras com a central | B58: Central CFTV | C58: Alto risco | D58: ='Dicionario EAP2'!G65 -> Pétrick Gomes Cosme Sousa Damião Sousa Nilton Guerra | E58: ='Dicionario EAP2'!T65 -> 1 | F58: ='Dicionario EAP2'!I65 -> 44462 | G58: 2
A59: O acionamento da iluminaçao manualmente | B59: Sistemas de iluminação automatizada | C59: Médio risco | D59: ='Dicionario EAP2'!G66 -> Pétrick Gomes Cosme Sousa Damião Sousa Nilton Guerra | E59: ='Dicionario EAP2'!T66 -> 1 | F59: ='Dicionario EAP2'!I66 -> 44474
A60: Comunicação da central com os sensores. | B60: Central de alarme de incêndio | C60: Alto risco | D60: ='Dicionario EAP2'!G67 -> Cosme Sousa Damião Sousa Pétrick Gomes Nilton Guerra | E60: ='Dicionario EAP2'!T67 -> 1 | F60: ='Dicionario EAP2'!I67 -> 44466 | G60: 1
A61: Monitoramento do consumo de energia | B61: Sistema de monitoramento de energia | C61: Médio risco | D61: ='Dicionario EAP2'!G68 -> Leandro Costa João Miranda | E61: ='Dicionario EAP2'!T68 -> 1 | F61: ='Dicionario EAP2'!I68 -> 44487
A62: Fazer a comunicação via WI-FI | B62: Roteador WI-fi | C62: Médio risco | D62: ='Dicionario EAP2'!G69 -> Leandro Costa João Miranda | E62: ='Dicionario EAP2'!T69 -> 1 | F62: ='Dicionario EAP2'!I69 -> 44487 | G62: 4
A63: comunicação entre os dispositivos | B63: Integração dos sistemas | C63: Médio risco | D63: ='Dicionario EAP2'!G70 -> Leandro Costa Pétrick Gomes | E63: ='Dicionario EAP2'!T70 -> 1 | F63: ='Dicionario EAP2'!I69 -> 44487
A64: Analisar se as atividades realizadas satisfaz as expectativas da equipe. | B64: CFTV | C64: Médio risco | D64: ='Dicionario EAP2'!G71 -> Damião sousa | E64: ='Dicionario EAP2'!T71 -> 1 | F64: ='Dicionario EAP2'!I70 -> 44498
A65: Analizar se as atividades realizadas satisfaz as expectativas da equipe. | B65: Central de Incêndio | C65: Médio risco | D65: ='Dicionario EAP2'!G72 -> Nilton Guerra | E65: ='Dicionario EAP2'!T72 -> 1 | F65: ='Dicionario EAP2'!I71 -> 44501
A66: Analizar se as atividades realizadas satisfaz as expectativas da equipe. | B66: Alarme Patrimonial | C66: Médio risco | D66: ='Dicionario EAP2'!#REF! -> #REF! | E66: ='Dicionario EAP2'!#REF! -> #REF! | F66: ='Dicionario EAP2'!I72 -> 44501
A67: Analizar se as atividades realizadas satisfaz as expectativas da equipe. | B67: Iluminação Automatizada | C67: Médio risco | D67: ='Dicionario EAP2'!G73 -> Cosme Sousa | E67: ='Dicionario EAP2'!T73 -> 1 | F67: ='Dicionario EAP2'!I73 -> 44501
A68: Analizar se as atividades realizadas satisfaz as expectativas da equipe. | B68: Sistema de Monitoramento | C68: Médio risco | D68: ='Dicionario EAP2'!G74 -> Leandro Costa João Miranda | E68: ='Dicionario EAP2'!T74 -> 1 | F68: ='Dicionario EAP2'!I74 -> 44501
A69: Analizar se as atividades realizadas satisfaz as expectativas da equipe. | B69: Configurar a interação do sistema com as centrais e com sistema de redes sem fio. | C69: Alto risco | D69: ='Dicionario EAP2'!G75 -> Damião Sousa Pétrick Gomes | E69: ='Dicionario EAP2'!T75 -> 1 | F69: ='Dicionario EAP2'!I75 -> 44501
A70: Garantir que tudo esteja nos conformes | B70: Reunião | C70: Alto risco | D70: ='Dicionario EAP2'!G76 -> Todos integrantes | E70: ='Dicionario EAP2'!T76 -> 1 | F70: ='Dicionario EAP2'!I76 -> 44516
A71: Garantir que tudo esteja nos conformes | B71: Apresentação de Resultados | C71: Alto risco | D71: ='Dicionario EAP2'!G77 -> Leandro Costa Pétrick Gomes | E71: ='Dicionario EAP2'!T77 -> 1 | F71: ='Dicionario EAP2'!I77 -> 44503
A72: Aceitação do cliente de acordo com que foi pedido. | B72: Integração do cliente com o sistema | C72: Alto risco | D72: ='Dicionario EAP2'!G78 -> Leandro Costa Pétrick Gomes | E72: ='Dicionario EAP2'!T78 -> 1 | F72: ='Dicionario EAP2'!I78 -> 44518
A73: satisfação do cliente | B73: Feedback | C73: Alto risco | D73: ='Dicionario EAP2'!G79 -> Todos integrantes | E73: ='Dicionario EAP2'!T79 -> 1 | F73: ='Dicionario EAP2'!I79 -> 44518
A74: Garantir que tudo esteja nos conformes | B74: Após o termino de todas as etapas e tarefas, realizar uma revisão completa do projeto, analisando os critérios críticos e desejaveis buscando o máximo de qualidade | C74: Alto risco | D74: ='Dicionario EAP2'!G80 -> Todos os integrantes | E74: ='Dicionario EAP2'!T80 -> 1.027027 | F74: ='Dicionario EAP2'!I80 -> 44516
A75: Aprovação dos Orientadores | B75: Apresentar os resultados finais para os professores orientadores | C75: Alto risco | D75: ='Dicionario EAP2'!G81 -> Todos os integrantes | E75: ='Dicionario EAP2'!T81 -> 1 | F75: ='Dicionario EAP2'!I81 -> 44523
A76: Gerar um melhoramento | B76: Após a válidação e revisão, se necessário, efetuar as modificações necessárias | C76: Alto risco | D76: ='Dicionario EAP2'!G82 -> Todos os integrantes | E76: ='Dicionario EAP2'!T82 -> 1 | F76: ='Dicionario EAP2'!I82 -> 44524
A77: Executar entrega . | B77: Após todas as revisões, validações e modificações, efetuar a entrega do projeto. | C77: Alto risco | D77: ='Dicionario EAP2'!G83 -> Leandro Costa | E77: ='Dicionario EAP2'!T83 -> 1 | F77: ='Dicionario EAP2'!I83 -> 44525
A78: Fácil entendimento e que sirva de base para apresentação final. | B78: Elaborar slides para auxiliar os integrantes da equipe, contendo imagens, videos, gráficos e tabelas. | C78: Alto risco | D78: ='Dicionario EAP2'!G84 -> Nilton Guerra | E78: ='Dicionario EAP2'!T84 -> 1 | F78: ='Dicionario EAP2'!I84 -> 44477
... A81: Apresentar para o Orientador e empresa parceira | B81: Apresentação final e conclusão do TCC. | C81: Alto risco | D81: ='Dicionario EAP2'!G87 -> Todos os integrantes | E81: ='Dicionario EAP2'!T87 -> 5.5 | F81: ='Dicionario EAP2'!I87 -> 44531

Sheet Controle de Versões
B2: CONTROLE DE VERSÕES | I2: Horas trabalhadas
B3: Versão | C3: Data | D3: Autor | E3: Tempo de Trabalho | G3: Notas de Revisão
E4: Inicio (Horas) | F4: Termino (Horas)
B5: 1.0 | C5: 44435 | D5: Leandro | E5: 0.54166667 | F5: 0.68055556 | G5: Inicio da Documentação
B6: 1.1 | C6: 44436 | D6: Leandro | E6: 0.54166667 | F6: 0.68055556 | G6: Aplicando etapas já feitas; Inicio CheckList; Inicio Dicionário da EAP;
B7: 1.2 | C7: 44437 | D7: Leandro | E7: 0.54166667 | F7: 0.68055556 | G7: Formatação da Checklist; Colocando etapas na Checklist; Aplicação de Graficos; Conteudo EAP;
B8: 1.3 | C8: 44438 | D8: Leandro | E8: 0.54166667 | F8: 0.68055556 | G8: Dicionario da EAP; CheckList; Inicio Cronograma.
B9: 1.4 | C9: 44439 | D9: Leandro | E9: 0.54166667 | F9: 0.68055556 | G9: Dicionario da EAP
B10: 1.5 | C10: 44440 | D10: Leandro | E10: 0.54166667 | F10: 0.68055556 | G10: Termino do Pacote de Trabalho referente ao Dicionario.
B11: 1.6 | C11: 44441 | D11: Leandro | E11: 0.54166667 | F11: 0.68055556 | G11: Inicio do Responsaveis no Dicionario; Inicio dos Criterios de Aceitação no Dicionario; Termino das descrições do Dicionario; Inicio do Burndown Chart.
B12: 1.7 | C12: 44442 | D12: Leandro | E12: 0.54166667 | F12: 0.68055556 | G12: Termino das descrições e criterios do dicionario.
B13: 1.8 | C13: 44443 | D13: Leandro | E13: 0.54166667 | F13: 0.68055556 | G13: Grafico de Gantt.
B14: 1.9 | C14: 44444 | D14: Leandro | E14: 0.54166667 | F14: 0.68055556 | G14: Termino do Grafico de Gantt
B15: 2.0 | C15: 44445 | D15: Leandro | E15: 0.54166667 | F15: 0.68055556 | G15: Realocação da Etapa Motagem do Painel, Aprimoramento do dicionario
B16: 2.1 | C16: 44446 | D16: Leandro | E16: 0.54166667 | F16: 0.68055556 | G16: Acresentado Inflaestrutura na EAP (Foi retirado)
B17: 2.2 | C17: 44447 | D17: Leandro | E17: 0.54166667 | F17: 0.68055556 | G17: Acresentado Custos.
B18: 2.3 | C18: 44448 | D18: Leandro | E18: 0.54166667 | F18: 0.68055556 | G18: Atualização dos Custos.
B19: 2.4 | C19: 44449 | D19: Leandro | E19: 0.54166667 | F19: 0.68055556 | G19: Testes NR-12

Sheet APR- PAINÉIS
A1: LOGAN | B1: ANÁLISE PRELIMINAR DE RISCOS - PAINÉIS
F3: DATA: Nº Item Programa:
F4: 16/09/2021 01
A6: SITUAÇÃO:
A8: Parada Programada ( X ) | B8: Fora de Parada ( ) | C8: Parada Acidental ( ) | D8: Atividade de Segurança ( ) | E8: Reparo ( ) | F8: Obra Nova ( )
A9: ORIENTADOR RESPONSÁVEL: | B9: LOCAL DE TRABALHO: | C9: EQUIPAMENTO / MÁQUINA / INSTALAÇÃO: | E9: DESCRIÇÃO DA ATIVIDADE:
A12: POSSÍVEIS RISCOS DA ATIVIDADE: INTEGRIDADE FÍSICA
C14: X
A23: ( ) Outros:
A25: RECURSOS MATERIAIS NECESSÁRIOS:
A26: Cabos ( ) Furadeira ( ) Perfilados/Eletrocalhas/Eletrodutos ( ) Ferramentas de medições ( ) Ferramentas Manuais ( ) Escada ( )
A27: Outros ( ) Especficar: _______________________________________________________________________________________________________________________
A29: RECOMENDAÇÕES DE SEGURANÇA (GERAIS E ESPECÍFICAS):
A30: Cuidados ao utilizar ferramentas manuais.
A31: EQUIPAMENTOS DE PROTEÇÃO INDIVIDUAIS OBRIGATÓRIOS: | D31: EQUIPAMENTOS DE PROTEÇÃO COLETIVA NECESSÁRIOS:
A32: ( ) Avental | B32: ( ) Rede protetora para cabelos | C32: ( ) ....................................................
A33: ( ) Luvas de segurança | B33: ( ) Outros (ESPECIFICAR). | C33: ( ) ....................................................
A34: ( ) Calçados de segurança | C34: ( ) ....................................................
A35: ( ) Protetor auricular | C35: ( ) ....................................................
A36: ( ) Óculos de segurança | C36: ( ) ....................................................
A37: ( ) Creme protetor | C37: ( ) ....................................................
A38: RESPONSÁVEIS PELA EXECUÇÃO DA ATIVIDADE:
A39: NOME: | B39: CARGO: | C39: RA: | D39: NOME: | E39: CARGO: | F39: RA:
A40: Damiao de sousa alves | B40: tecnico1
A41: NOME: | B41: CARGO: | C41: RA: | D41: NOME: | E41: CARGO: | F41: RA:
A42: cosme de sousa alves | B42: tecnico2
A43: NOME: | B43: CARGO: | C43: RA: | D43: NOME: | E43: CARGO: | F43: RA:
A45: OBSERVAÇÕES FINAIS:
A49: APROVAÇÃO: | E49: DATA | F49: HORA
A51: ________________________________________________ | C51: ________________________________________________
A52: Responsável pela Equipe de Execução | C52: Orientador Responsável

Sheet APR - ILUMINAÇÃO
A1: LOGAN | B1: ANÁLISE PRELIMINAR DE RISCOS
F3: DATA: Nº Item Programa:
A6: SITUAÇÃO:
A8: Parada Programada ( ) | B8: Fora de Parada ( ) | C8: Parada Acidental ( ) | D8: Atividade de Segurança ( ) | E8: Reparo ( ) | F8: Obra Nova ( )
A9: ORIENTADOR RESPONSÁVEL: | B9: LOCAL DE TRABALHO: | C9: EQUIPAMENTO / MÁQUINA / INSTALAÇÃO: | E9: DESCRIÇÃO DA ATIVIDADE:
A12: POSSÍVEIS RISCOS DA ATIVIDADE: INTEGRIDADE FÍSICA
A23: ( ) Outros:
A25: RECURSOS MATERIAIS NECESSÁRIOS:
A26: Cabos ( ) Furadeira ( ) Perfilados/Eletrocalhas/Eletrodutos ( ) Ferramentas de medições ( ) Ferramentas Manuais ( ) Escada ( )
A27: Outros ( ) Especficar: _______________________________________________________________________________________________________________________
A29: RECOMENDAÇÕES DE SEGURANÇA (GERAIS E ESPECÍFICAS):
A31: EQUIPAMENTOS DE PROTEÇÃO INDIVIDUAIS OBRIGATÓRIOS: | D31: EQUIPAMENTOS DE PROTEÇÃO COLETIVA NECESSÁRIOS:
A32: ( ) Avental | B32: ( ) Rede protetora para cabelos | C32: ( ) ....................................................
A33: ( ) Luvas de segurança | B33: ( ) Outros (ESPECIFICAR). | C33: ( ) ....................................................
A34: ( ) Calçados de segurança | C34: ( ) ....................................................
A35: ( ) Protetor auricular | C35: ( ) ....................................................
A36: ( ) Óculos de segurança | C36: ( ) ....................................................
A37: ( ) Creme protetor | C37: ( ) ....................................................
A38: RESPONSÁVEIS PELA EXECUÇÃO DA ATIVIDADE:
A39: NOME: | B39: CARGO: | C39: RA: | D39: NOME: | E39: CARGO: | F39: RA:
A40: Leandro
A41: NOME: | B41: CARGO: | C41: RA: | D41: NOME: | E41: CARGO: | F41: RA:
A43: NOME: | B43: CARGO: | C43: RA: | D43: NOME: | E43: CARGO: | F43: RA:
A45: OBSERVAÇÕES FINAIS:
A49: APROVAÇÃO: | E49: DATA | F49: HORA
A51: ________________________________________________ | C51: ________________________________________________
A52: Responsável pela Equipe de Execução | C52: Orientador Responsável

Sheet APR - CENTRAL DE INCÊNDIO
A1: LOGAN | B1: ANÁLISE PRELIMINAR DE RISCOS
F3: DATA: Nº Item Programa:
A6: SITUAÇÃO:
A8: Parada Programada ( ) | B8: Fora de Parada ( ) | C8: Parada Acidental ( ) | D8: Atividade de Segurança ( ) | E8: Reparo ( ) | F8: Obra Nova ( )
A9: ORIENTADOR RESPONSÁVEL: | B9: LOCAL DE TRABALHO: | C9: EQUIPAMENTO / MÁQUINA / INSTALAÇÃO: | E9: DESCRIÇÃO DA ATIVIDADE: | F9: CENTRAL DE INCÊNDIO
A10: Alex | B10: Ofiina IEL01
A12: POSSÍVEIS RISCOS DA ATIVIDADE: INTEGRIDADE FÍSICA
A23: ( ) Outros:
A25: RECURSOS MATERIAIS NECESSÁRIOS:
A26: Cabos ( ) Furadeira ( ) Perfilados/Eletrocalhas/Eletrodutos ( ) Ferramentas de medições ( ) Ferramentas Manuais ( ) Escada ( )
A27: Outros ( ) Especficar: _______________________________________________________________________________________________________________________
A29: RECOMENDAÇÕES DE SEGURANÇA (GERAIS E ESPECÍFICAS):
A31: EQUIPAMENTOS DE PROTEÇÃO INDIVIDUAIS OBRIGATÓRIOS: | D31: EQUIPAMENTOS DE PROTEÇÃO COLETIVA NECESSÁRIOS:
A32: ( ) Avental | B32: ( ) Rede protetora para cabelos | C32: ( ) .................................................... | D32: Dispositivi loto para bloqueio de enegias
A33: ( ) Luvas de segurança | B33: ( ) Outros (ESPECIFICAR). | C33: ( ) ....................................................
A34: ( ) Calçados de segurança | C34: ( ) ....................................................
A35: ( ) Protetor auricular | C35: ( ) ....................................................
A36: ( ) Óculos de segurança | C36: ( ) ....................................................
A37: ( ) Creme protetor | C37: ( ) ....................................................
A38: RESPONSÁVEIS PELA EXECUÇÃO DA ATIVIDADE:
A39: NOME: | B39: CARGO: | C39: RA: | D39: NOME: | E39: CARGO: | F39: RA:
A40: Pétrick Kauã | B40: Técnico
A41: NOME: | B41: CARGO: | C41: RA: | D41: NOME: | E41: CARGO: | F41: RA:
A42: Cosme Souza | B42: Técnico
A43: NOME: | B43: CARGO: | C43: RA: | D43: NOME: | E43: CARGO: | F43: RA:
A44: Damião Souza | B44: Técnico
A45: OBSERVAÇÕES FINAIS:
A49: APROVAÇÃO: | E49: DATA | F49: HORA
A51: ________________________________________________ | C51: ________________________________________________
A52: Responsável pela Equipe de Execução | C52: Orientador Responsável

Sheet APR - ILUMINAÇÃO (2)
A1: LOGAN | B1: ANÁLISE PRELIMINAR DE RISCOS - ILUMINAÇÃO
F3: DATA: Nº Item Programa:
A6: SITUAÇÃO:
A8: Parada Programada ( ) | B8: Fora de Parada ( ) | C8: Parada Acidental ( ) | D8: Atividade de Segurança ( ) | E8: Reparo ( ) | F8: Obra Nova ( )
A9: ORIENTADOR RESPONSÁVEL: | B9: LOCAL DE TRABALHO: | C9: EQUIPAMENTO / MÁQUINA / INSTALAÇÃO: | E9: DESCRIÇÃO DA ATIVIDADE:
A12: POSSÍVEIS RISCOS DA ATIVIDADE: INTEGRIDADE FÍSICA
A23: ( ) Outros:
A25: RECURSOS MATERIAIS NECESSÁRIOS:
A26: Cabos ( ) Furadeira ( ) Perfilados/Eletrocalhas/Eletrodutos ( ) Ferramentas de medições ( ) Ferramentas Manuais ( ) Escada ( )
A27: Outros ( ) Especficar: _______________________________________________________________________________________________________________________
A29: RECOMENDAÇÕES DE SEGURANÇA (GERAIS E ESPECÍFICAS):
A30: Fazer a instalação com painel desenirgizado
A31: EQUIPAMENTOS DE PROTEÇÃO INDIVIDUAIS OBRIGATÓRIOS: | D31: EQUIPAMENTOS DE PROTEÇÃO COLETIVA NECESSÁRIOS:
A32: ( ) Avental | B32: ( ) Rede protetora para cabelos | C32: ( ) ....................................................
A33: ( ) Luvas de segurança | B33: ( ) Outros (ESPECIFICAR). | C33: ( ) ....................................................
A34: ( ) Calçados de segurança | C34: ( ) ....................................................
A35: ( ) Protetor auricular | C35: ( ) ....................................................
A36: ( ) Óculos de segurança | C36: ( ) ....................................................
A37: ( ) Creme protetor | C37: ( ) ....................................................
A38: RESPONSÁVEIS PELA EXECUÇÃO DA ATIVIDADE:
A39: NOME: | B39: CARGO: | C39: RA: | D39: NOME: | E39: CARGO: | F39: RA:
A40: Cosme de sousa | B40: Técnico
A41: NOME: | B41: CARGO: | C41: RA: | D41: NOME: | E41: CARGO: | F41: RA:
A43: NOME: | B43: CARGO: | C43: RA: | D43: NOME: | E43: CARGO: | F43: RA:
A45: OBSERVAÇÕES FINAIS:
A49: APROVAÇÃO: | E49: DATA | F49: HORA
A51: ________________________________________________ | C51: ________________________________________________
A52: Responsável pela Equipe de Execução | C52: Orientador Responsável

Sheet APR - INTERFONE 
A1: LOGAN | B1: ANÁLISE PRELIMINAR DE RISCOS
F3: DATA: Nº Item Programa:
A6: SITUAÇÃO:
A8: Parada Programada ( ) | B8: Fora de Parada ( ) | C8: Parada Acidental ( ) | D8: Atividade de Segurança ( ) | E8: Reparo ( ) | F8: Obra Nova ( )
A9: ORIENTADOR RESPONSÁVEL: | B9: LOCAL DE TRABALHO: | C9: EQUIPAMENTO / MÁQUINA / INSTALAÇÃO: | E9: DESCRIÇÃO DA ATIVIDADE:
B10: Laboratório IELI 1 | E10: INTERFONE
A12: POSSÍVEIS RISCOS DA ATIVIDADE: INTEGRIDADE FÍSICA
A23: ( ) Outros:
A25: RECURSOS MATERIAIS NECESSÁRIOS:
A26: Cabos ( ) Furadeira ( ) Perfilados/Eletrocalhas/Eletrodutos ( ) Ferramentas de medições ( ) Ferramentas Manuais ( ) Escada ( )
A27: Outros ( ) Especficar: _______________________________________________________________________________________________________________________
A29: RECOMENDAÇÕES DE SEGURANÇA (GERAIS E ESPECÍFICAS):
A30: Realizar a instalação do equipamento com o sistema desenergizado;
A31: EQUIPAMENTOS DE PROTEÇÃO INDIVIDUAIS OBRIGATÓRIOS: | D31: EQUIPAMENTOS DE PROTEÇÃO COLETIVA NECESSÁRIOS:
A32: ( ) Avental | B32: ( ) Rede protetora para cabelos | C32: ( ) ....................................................
A33: ( x ) Luvas de segurança | B33: ( ) Outros (ESPECIFICAR). | C33: ( ) ....................................................
A34: ( x ) Calçados de segurança | C34: ( ) ....................................................
A35: ( ) Protetor auricular | C35: ( ) ....................................................
A36: ( x ) Óculos de segurança | C36: ( ) ....................................................
A37: ( ) Creme protetor | C37: ( ) ....................................................
A38: RESPONSÁVEIS PELA EXECUÇÃO DA ATIVIDADE:
A39: NOME: | B39: CARGO: | C39: RA: | D39: NOME: | E39: CARGO: | F39: RA:
A40: Nilton Guerra | B40: Técnico
A41: NOME: | B41: CARGO: | C41: RA: | D41: NOME: | E41: CARGO: | F41: RA:
A43: NOME: | B43: CARGO: | C43: RA: | D43: NOME: | E43: CARGO: | F43: RA:
A45: OBSERVAÇÕES FINAIS:
A49: APROVAÇÃO: | E49: DATA | F49: HORA
A51: ________________________________________________ | C51: ________________________________________________
A52: Responsável pela Equipe de Execução | C52: Orientador Responsável

Sheet APR-CFTV
A1: LOGAN | B1: ANÁLISE PRELIMINAR DE RISCOS
F3: DATA: Nº Item Programa:
A6: SITUAÇÃO:
A8: Parada Programada ( ) | B8: Fora de Parada ( ) | C8: Parada Acidental ( ) | D8: Atividade de Segurança ( ) | E8: Reparo ( ) | F8: Obra Nova ( )
A9: ORIENTADOR RESPONSÁVEL: | B9: LOCAL DE TRABALHO: | C9: EQUIPAMENTO / MÁQUINA / INSTALAÇÃO: | E9: DESCRIÇÃO DA ATIVIDADE:
E10: CFTV
A12: POSSÍVEIS RISCOS DA ATIVIDADE: INTEGRIDADE FÍSICA
A23: ( ) Outros:
A25: RECURSOS MATERIAIS NECESSÁRIOS:
A26: Cabos ( ) Furadeira ( ) Perfilados/Eletrocalhas/Eletrodutos ( ) Ferramentas de medições ( ) Ferramentas Manuais ( ) Escada ( )
A27: Outros ( ) Especficar: câmeras, cabos coaxial,conector P4 macro,conector P4 femêa, conector balun, DVR, monitor_______________________________________________________________________________________________________________________
A29: RECOMENDAÇÕES DE SEGURANÇA (GERAIS E ESPECÍFICAS):
A30: Enquanto uma pessoa estiver na escada a outra pessoa terá que segurar a escada; Não deixar nada em cima da escada, pois pode cair e machucar a cameça de alguém; Apenas ligar os equipamento após fazer uma conferencia por mais dois técnicos para evitar danificar os equipamentos;
A31: EQUIPAMENTOS DE PROTEÇÃO INDIVIDUAIS OBRIGATÓRIOS: | D31: EQUIPAMENTOS DE PROTEÇÃO COLETIVA NECESSÁRIOS:
A32: ( ) Avental | B32: ( ) Rede protetora para cabelos | C32: ( ) ....................................................
A33: ( X ) Luvas de segurança | B33: ( ) Outros (ESPECIFICAR). | C33: ( ) ....................................................
A34: ( X ) Calçados de segurança | C34: ( ) ....................................................
A35: ( ) Protetor auricular | C35: ( ) ....................................................
A36: ( X ) Óculos de segurança | C36: ( ) ....................................................
A37: ( ) Creme protetor | C37: ( ) ....................................................
A38: RESPONSÁVEIS PELA EXECUÇÃO DA ATIVIDADE:
A39: NOME: | B39: CARGO: | C39: RA: | D39: NOME: | E39: CARGO: | F39: RA:
A40: Cosme Sousa | B40: Técnico | D40: Nilton Guerra | E40: Técnico
A41: NOME: | B41: CARGO: | C41: RA: | D41: NOME: | E41: CARGO: | F41: RA:
A42: Damião Sousa | B42: Técnico
A43: NOME: | B43: CARGO: | C43: RA: | D43: NOME: | E43: CARGO: | F43: RA:
A44: Pétrick kauã | B44: Técnico
A45: OBSERVAÇÕES FINAIS:
A49: APROVAÇÃO: | E49: DATA | F49: HORA
A51: ____________________Leandro Costa____________________________ | C51: ________________________________________________
A52: Responsável pela Equipe de Execução | C52: Orientador Responsável

Sheet APR- SISTEMA DE MONITORAMENTO 
A1: LOGAN | B1: ANÁLISE PRELIMINAR DE RISCOS - MONITOR DE ENERGIA
F3: DATA: Nº Item Programa:
A6: SITUAÇÃO:
A8: Parada Programada ( ) | B8: Fora de Parada ( ) | C8: Parada Acidental ( ) | D8: Atividade de Segurança ( ) | E8: Reparo ( ) | F8: Obra Nova ( )
A9: ORIENTADOR RESPONSÁVEL: | B9: LOCAL DE TRABALHO: | C9: EQUIPAMENTO / MÁQUINA / INSTALAÇÃO: | E9: DESCRIÇÃO DA ATIVIDADE: | F9: MONITOR DE ENERGIA
A12: POSSÍVEIS RISCOS DA ATIVIDADE: INTEGRIDADE FÍSICA
A23: ( ) Outros:
A25: RECURSOS MATERIAIS NECESSÁRIOS:
A26: Cabos ( ) Furadeira ( ) Perfilados/Eletrocalhas/Eletrodutos ( ) Ferramentas de medições ( ) Ferramentas Manuais ( ) Escada ( )
A27: Outros ( ) Especficar: _______________________________________________________________________________________________________________________
A29: RECOMENDAÇÕES DE SEGURANÇA (GERAIS E ESPECÍFICAS):
A31: EQUIPAMENTOS DE PROTEÇÃO INDIVIDUAIS OBRIGATÓRIOS: | D31: EQUIPAMENTOS DE PROTEÇÃO COLETIVA NECESSÁRIOS:
A32: ( ) Avental | B32: ( ) Rede protetora para cabelos | C32: ( ) ....................................................
A33: ( ) Luvas de segurança | B33: ( ) Outros (ESPECIFICAR). | C33: ( ) ....................................................
A34: ( ) Calçados de segurança | C34: ( ) ....................................................
A35: ( ) Protetor auricular | C35: ( ) ....................................................
A36: ( ) Óculos de segurança | C36: ( ) ....................................................
A37: ( ) Creme protetor | C37: ( ) ....................................................
A38: RESPONSÁVEIS PELA EXECUÇÃO DA ATIVIDADE:
A39: NOME: | B39: CARGO: | C39: RA: | D39: NOME: | E39: CARGO: | F39: RA:
A40: João miranda | B40: Técnico
A41: NOME: | B41: CARGO: | C41: RA: | D41: NOME: | E41: CARGO: | F41: RA:
A43: NOME: | B43: CARGO: | C43: RA: | D43: NOME: | E43: CARGO: | F43: RA:
A45: OBSERVAÇÕES FINAIS:
A49: APROVAÇÃO: | E49: DATA | F49: HORA
A51: ________________________________________________ | C51: ________________________________________________
A52: Responsável pela Equipe de Execução | C52: Orientador Responsável

Sheet TRAVA AUTOMATIVA
A1: LOGAN | B1: ANÁLISE PRELIMINAR DE RISCOS
F3: DATA: Nº Item Programa:
A6: SITUAÇÃO:
A8: Parada Programada ( ) | B8: Fora de Parada ( ) | C8: Parada Acidental ( ) | D8: Atividade de Segurança ( ) | E8: Reparo ( ) | F8: Obra Nova ( )
A9: ORIENTADOR RESPONSÁVEL: | B9: LOCAL DE TRABALHO: | C9: EQUIPAMENTO / MÁQUINA / INSTALAÇÃO: | E9: DESCRIÇÃO DA ATIVIDADE:
E10: TRAVA AUTOMATIVA
A12: POSSÍVEIS RISCOS DA ATIVIDADE: INTEGRIDADE FÍSICA
A23: ( ) Outros:
A25: RECURSOS MATERIAIS NECESSÁRIOS:
A26: Cabos ( ) Furadeira ( ) Perfilados/Eletrocalhas/Eletrodutos ( ) Ferramentas de medições ( ) Ferramentas Manuais ( ) Escada ( )
A27: Outros ( ) Especficar: _______________________________________________________________________________________________________________________
A29: RECOMENDAÇÕES DE SEGURANÇA (GERAIS E ESPECÍFICAS):
A30: Fazer a instalação com o sistema desenergizado.
A31: EQUIPAMENTOS DE PROTEÇÃO INDIVIDUAIS OBRIGATÓRIOS: | D31: EQUIPAMENTOS DE PROTEÇÃO COLETIVA NECESSÁRIOS:
A32: ( ) Avental | B32: ( ) Rede protetora para cabelos | C32: ( ) ....................................................
A33: ( x ) Luvas de segurança | B33: ( ) Outros (ESPECIFICAR). | C33: ( ) ....................................................
A34: ( x ) Calçados de segurança | C34: ( ) ....................................................
A35: ( ) Protetor auricular | C35: ( ) ....................................................
A36: ( x ) Óculos de segurança | C36: ( ) ....................................................
A37: ( ) Creme protetor | C37: ( ) ....................................................
A38: RESPONSÁVEIS PELA EXECUÇÃO DA ATIVIDADE:
A39: NOME: | B39: CARGO: | C39: RA: | D39: NOME: | E39: CARGO: | F39: RA:
A40: Nilton Guerra | B40: Técnico
A41: NOME: | B41: CARGO: | C41: RA: | D41: NOME: | E41: CARGO: | F41: RA:
A43: NOME: | B43: CARGO: | C43: RA: | D43: NOME: | E43: CARGO: | F43: RA:
A45: OBSERVAÇÕES FINAIS:
A49: APROVAÇÃO: | E49: DATA | F49: HORA
A51: ________________________________________________ | C51: ________________________________________________
A52: Responsável pela Equipe de Execução | C52: Orientador Responsável
